Workbook

Sheet main
A1: election_number | B1: logical_order | C1: election_year | D1: party | E1: elected_president | F1: president_number | G1: popular_vote | H1: popular_vote_percent | I1: electoral_votes | J1: t1 | K1: t2 | L1: t3 | M1: t4 | N1: t5 | O1: t6 | P1: pvt | Q1: misc | R1: link | S1: desc | T1: popular_vote_percent_vat | U1: election_number_text | V1: won_the_election | W1: candidates | X1: candidates_won | Y1: candidates_lost | Z1: election_link | AA1: comment
A2: 1 | B2: =VLOOKUP(D2,party!A:E,5,0) -> 1 | C2: 1788 | D2: Independent | E2: George Washington | G2: 43782 | H2: 1 | I2: 69 | P2: 100.0% * | Q2: =IF(IFERROR(VLOOKUP($D2,party!$A:$D,2,0),"")="","",IFERROR(VLOOKUP($D2,party!$A:$D,2,0),"")) -> Not a party. | R2: =IF(IFERROR(VLOOKUP($D2,party!$A:$D,3,0),"")="","",IFERROR(VLOOKUP($D2,party!$A:$D,3,0),"")) -> https://en.wikipedia.org/wiki/Independent_politician | S2: =IF(IFERROR(VLOOKUP($D2,party!$A:$D,4,0),"")="","",IFERROR(VLOOKUP($D2,party!$A:$D,4,0),"")) -> An independent, non-partisan politician or non-affiliated politician is a politician not affiliated with any political party or bureaucratic association. There are numerous reasons why someone may stand for office as an independent. George Washington is the only U.S. president elected as an independent to date. Washington opposed the development of political parties. He feared that partisanship would eventually destroy the country, and famously warned against "the baneful effects of the spirit of party" in his 1796 Farewell Address. | T2: =IF(H2="", "", VALUE(H2)) -> 1 | U2: =_xlfn.CONCAT(TEXT(A2,"#"), IF(AND(A2>=10, A2<=19), "th", IF(MOD(A2,10) = 1, "st", IF(MOD(A2,10) = 2, "nd", IF(MOD(A2,10) = 3, "rd", "th"))))) -> 1st | V2: TRUE | X2: =IF(V2, W2, "") | Y2: =IF(NOT(V2), W2, "") | Z2: https://en.wikipedia.org/wiki/1788%E2%80%9389_United_States_presidential_election | AA2: * States had varying methods for choosing presidential electors. In five states, the state legislature chose electors. The other six chose electors through some form involving a popular vote, though in only two states did the choice depend directly on a statewide vote.
A3: 1 | B3: =VLOOKUP(D3,party!A:E,5,0) -> 10 | C3: 1788 | D3: Federalist | G3: 0 | I3: 65 | P3: n/a * | Q3: =IF(IFERROR(VLOOKUP($D3,party!$A:$D,2,0),"")="","",IFERROR(VLOOKUP($D3,party!$A:$D,2,0),"")) | R3: =IF(IFERROR(VLOOKUP($D3,party!$A:$D,3,0),"")="","",IFERROR(VLOOKUP($D3,party!$A:$D,3,0),"")) -> https://en.wikipedia.org/wiki/Federalist_Party | S3: =IF(IFERROR(VLOOKUP($D3,party!$A:$D,4,0),"")="","",IFERROR(VLOOKUP($D3,party!$A:$D,4,0),"")) -> The Federalist Party was a conservative and nationalist American political party and the first political party in the United States. It dominated the national government under Alexander Hamilton from 1789 to 1801. The party was defeated by the Democratic-Republican Party in 1800, and it became a minority party while keeping its stronghold in New England. It made a brief resurgence by opposing the War of 1812, then collapsed with its last presidential candidate in 1816. Remnants lasted for a few years afterwards. | T3: =IF(H3="", "", VALUE(H3)) | U3: =_xlfn.CONCAT(TEXT(A3,"#"), IF(AND(A3>=10, A3<=19), "th", IF(MOD(A3,10) = 1, "st", IF(MOD(A3,10) = 2, "nd", IF(MOD(A3,10) = 3, "rd", "th"))))) -> 1st | V3: FALSE | W3: John Adams and 8 more | X3: =IF(V3, W3, "") | Y3: =IF(NOT(V3), W3, "") -> John Adams and 8 more | Z3: https://en.wikipedia.org/wiki/1788%E2%80%9389_United_States_presidential_election | AA3: * States had varying methods for choosing presidential electors. In five states, the state legislature chose electors. The other six chose electors through some form involving a popular vote, though in only two states did the choice depend directly on a statewide vote.
A4: 1 | B4: =VLOOKUP(D4,party!A:E,5,0) -> 21 | C4: 1788 | D4: Anti-Administration | G4: 0 | I4: 4 | P4: n/a * | Q4: =IF(IFERROR(VLOOKUP($D4,party!$A:$D,2,0),"")="","",IFERROR(VLOOKUP($D4,party!$A:$D,2,0),"")) -> Not a party. | R4: =IF(IFERROR(VLOOKUP($D4,party!$A:$D,3,0),"")="","",IFERROR(VLOOKUP($D4,party!$A:$D,3,0),"")) -> https://en.wikipedia.org/wiki/Anti-Administration_party | S4: =IF(IFERROR(VLOOKUP($D4,party!$A:$D,4,0),"")="","",IFERROR(VLOOKUP($D4,party!$A:$D,4,0),"")) -> The Anti-Administration party was an informal political faction in the United States led by James Madison and Thomas Jefferson that opposed policies of then Secretary of the Treasury Alexander Hamilton in the first term of U.S. president George Washington. It was not an organized political party, but an unorganized faction. Most members had been Anti-Federalists in 1788, when they opposed ratification of the U.S. Constitution. Although contemporaries often referred to Hamilton's opponents as "Anti-Federalists", that term is now seen as imprecise since several Anti-Administration leaders supported ratification, including Virginia Representative James Madison. | T4: =IF(H4="", "", VALUE(H4)) | U4: =_xlfn.CONCAT(TEXT(A4,"#"), IF(AND(A4>=10, A4<=19), "th", IF(MOD(A4,10) = 1, "st", IF(MOD(A4,10) = 2, "nd", IF(MOD(A4,10) = 3, "rd", "th"))))) -> 1st | V4: FALSE | W4: George Clinton and 1 more | X4: =IF(V4, W4, "") | Y4: =IF(NOT(V4), W4, "") -> George Clinton and 1 more | Z4: https://en.wikipedia.org/wiki/1788%E2%80%9389_United_States_presidential_election | AA4: * States had varying methods for choosing presidential electors. In five states, the state legislature chose electors. The other six chose electors through some form involving a popular vote, though in only two states did the choice depend directly on a statewide vote.
A5: 2 | B5: =VLOOKUP(D5,party!A:E,5,0) -> 1 | C5: 1792 | D5: Independent | E5: George Washington | G5: 28579 | H5: 1 | I5: 132 | P5: 100.0% * | Q5: =IF(IFERROR(VLOOKUP($D5,party!$A:$D,2,0),"")="","",IFERROR(VLOOKUP($D5,party!$A:$D,2,0),"")) -> Not a party. | R5: =IF(IFERROR(VLOOKUP($D5,party!$A:$D,3,0),"")="","",IFERROR(VLOOKUP($D5,party!$A:$D,3,0),"")) -> https://en.wikipedia.org/wiki/Independent_politician | S5: =IF(IFERROR(VLOOKUP($D5,party!$A:$D,4,0),"")="","",IFERROR(VLOOKUP($D5,party!$A:$D,4,0),"")) -> An independent, non-partisan politician or non-affiliated politician is a politician not affiliated with any political party or bureaucratic association. There are numerous reasons why someone may stand for office as an independent. George Washington is the only U.S. president elected as an independent to date. Washington opposed the development of political parties. He feared that partisanship would eventually destroy the country, and famously warned against "the baneful effects of the spirit of party" in his 1796 Farewell Address. | T5: =IF(H5="", "", VALUE(H5)) -> 1 | U5: =_xlfn.CONCAT(TEXT(A5,"#"), IF(AND(A5>=10, A5<=19), "th", IF(MOD(A5,10) = 1, "st", IF(MOD(A5,10) = 2, "nd", IF(MOD(A5,10) = 3, "rd", "th"))))) -> 2nd | V5: TRUE | X5: =IF(V5, W5, "") | Y5: =IF(NOT(V5), W5, "") | Z5: =_xlfn.CONCAT("https://en.wikipedia.org/wiki/", C5, "_United_States_presidential_election") -> https://en.wikipedia.org/wiki/1792_United_States_presidential_election | AA5: * Nine of the 15 states eligible to choose representatives to the electoral college did so by a vote of the state legislature; the remaining six employed some form of popular vote.
A6: 2 | B6: =VLOOKUP(D6,party!A:E,5,0) -> 10 | C6: 1792 | D6: Federalist | G6: 0 | I6: 77 | P6: n/a * | Q6: =IF(IFERROR(VLOOKUP($D6,party!$A:$D,2,0),"")="","",IFERROR(VLOOKUP($D6,party!$A:$D,2,0),"")) | R6: =IF(IFERROR(VLOOKUP($D6,party!$A:$D,3,0),"")="","",IFERROR(VLOOKUP($D6,party!$A:$D,3,0),"")) -> https://en.wikipedia.org/wiki/Federalist_Party | S6: =IF(IFERROR(VLOOKUP($D6,party!$A:$D,4,0),"")="","",IFERROR(VLOOKUP($D6,party!$A:$D,4,0),"")) -> The Federalist Party was a conservative and nationalist American political party and the first political party in the United States. It dominated the national government under Alexander Hamilton from 1789 to 1801. The party was defeated by the Democratic-Republican Party in 1800, and it became a minority party while keeping its stronghold in New England. It made a brief resurgence by opposing the War of 1812, then collapsed with its last presidential candidate in 1816. Remnants lasted for a few years afterwards. | T6: =IF(H6="", "", VALUE(H6)) | U6: =_xlfn.CONCAT(TEXT(A6,"#"), IF(AND(A6>=10, A6<=19), "th", IF(MOD(A6,10) = 1, "st", IF(MOD(A6,10) = 2, "nd", IF(MOD(A6,10) = 3, "rd", "th"))))) -> 2nd | V6: FALSE | W6: John Adams | X6: =IF(V6, W6, "") | Y6: =IF(NOT(V6), W6, "") -> John Adams | Z6: =_xlfn.CONCAT("https://en.wikipedia.org/wiki/", C6, "_United_States_presidential_election") -> https://en.wikipedia.org/wiki/1792_United_States_presidential_election | AA6: * Nine of the 15 states eligible to choose representatives to the electoral college did so by a vote of the state legislature; the remaining six employed some form of popular vote.
A7: 2 | B7: =VLOOKUP(D7,party!A:E,5,0) -> 23 | C7: 1792 | D7: Democratic-Republican | G7: 0 | I7: 55 | P7: n/a * | Q7: =IF(IFERROR(VLOOKUP($D7,party!$A:$D,2,0),"")="","",IFERROR(VLOOKUP($D7,party!$A:$D,2,0),"")) | R7: =IF(IFERROR(VLOOKUP($D7,party!$A:$D,3,0),"")="","",IFERROR(VLOOKUP($D7,party!$A:$D,3,0),"")) -> https://en.wikipedia.org/wiki/Democratic-Republican_Party | S7: =IF(IFERROR(VLOOKUP($D7,party!$A:$D,4,0),"")="","",IFERROR(VLOOKUP($D7,party!$A:$D,4,0),"")) -> The Republican Party, known retroactively as the Democratic-Republican Party (also referred to by historians as the Jeffersonian Republican Party), was an American political party founded by Thomas Jefferson and James Madison in the early 1790s. It championed liberalism, republicanism, individual liberty, equal rights, decentralization, free markets, free trade, and agrarianism. In foreign policy it was hostile to Great Britain and in sympathy with the French Revolution. The party became increasingly dominant after the 1800 elections as the opposing Federalist Party collapsed. | T7: =IF(H7="", "", VALUE(H7)) | U7: =_xlfn.CONCAT(TEXT(A7,"#"), IF(AND(A7>=10, A7<=19), "th", IF(MOD(A7,10) = 1, "st", IF(MOD(A7,10) = 2, "nd", IF(MOD(A7,10) = 3, "rd", "th"))))) -> 2nd | V7: FALSE | W7: George Clinton and 2 more | X7: =IF(V7, W7, "") | Y7: =IF(NOT(V7), W7, "") -> George Clinton and 2 more | Z7: =_xlfn.CONCAT("https://en.wikipedia.org/wiki/", C7, "_United_States_presidential_election") -> https://en.wikipedia.org/wiki/1792_United_States_presidential_election | AA7: * Nine of the 15 states eligible to choose representatives to the electoral college did so by a vote of the state legislature; the remaining six employed some form of popular vote.
A8: 3 | B8: =VLOOKUP(D8,party!A:E,5,0) -> 1 | C8: 1796 | D8: Independent | G8: 0 | I8: 2 | P8: n/a * | Q8: =IF(IFERROR(VLOOKUP($D8,party!$A:$D,2,0),"")="","",IFERROR(VLOOKUP($D8,party!$A:$D,2,0),"")) -> Not a party. | R8: =IF(IFERROR(VLOOKUP($D8,party!$A:$D,3,0),"")="","",IFERROR(VLOOKUP($D8,party!$A:$D,3,0),"")) -> https://en.wikipedia.org/wiki/Independent_politician | S8: =IF(IFERROR(VLOOKUP($D8,party!$A:$D,4,0),"")="","",IFERROR(VLOOKUP($D8,party!$A:$D,4,0),"")) -> An independent, non-partisan politician or non-affiliated politician is a politician not affiliated with any political party or bureaucratic association. There are numerous reasons why someone may stand for office as an independent. George Washington is the only U.S. president elected as an independent to date. Washington opposed the development of political parties. He feared that partisanship would eventually destroy the country, and famously warned against "the baneful effects of the spirit of party" in his 1796 Farewell Address. | T8: =IF(H8="", "", VALUE(H8)) | U8: =_xlfn.CONCAT(TEXT(A8,"#"), IF(AND(A8>=10, A8<=19), "th", IF(MOD(A8,10) = 1, "st", IF(MOD(A8,10) = 2, "nd", IF(MOD(A8,10) = 3, "rd", "th"))))) -> 3rd | V8: FALSE | W8: George Washington | X8: =IF(V8, W8, "") | Y8: =IF(NOT(V8), W8, "") -> George Washington | Z8: =_xlfn.CONCAT("https://en.wikipedia.org/wiki/", C8, "_United_States_presidential_election") -> https://en.wikipedia.org/wiki/1796_United_States_presidential_election | AA8: * Only 9 of the 16 states used any form of popular vote. Those states that did choose electors by popular vote had widely varying restrictions on suffrage via property requirements.
A9: 3 | B9: =VLOOKUP(D9,party!A:E,5,0) -> 10 | C9: 1796 | D9: Federalist | E9: John Adams | G9: 35726 | H9: 0.534 | I9: 152 | J9: 71 | K9: 81 | P9: 53.4% * | Q9: =IF(IFERROR(VLOOKUP($D9,party!$A:$D,2,0),"")="","",IFERROR(VLOOKUP($D9,party!$A:$D,2,0),"")) | R9: =IF(IFERROR(VLOOKUP($D9,party!$A:$D,3,0),"")="","",IFERROR(VLOOKUP($D9,party!$A:$D,3,0),"")) -> https://en.wikipedia.org/wiki/Federalist_Party | S9: =IF(IFERROR(VLOOKUP($D9,party!$A:$D,4,0),"")="","",IFERROR(VLOOKUP($D9,party!$A:$D,4,0),"")) -> The Federalist Party was a conservative and nationalist American political party and the first political party in the United States. It dominated the national government under Alexander Hamilton from 1789 to 1801. The party was defeated by the Democratic-Republican Party in 1800, and it became a minority party while keeping its stronghold in New England. It made a brief resurgence by opposing the War of 1812, then collapsed with its last presidential candidate in 1816. Remnants lasted for a few years afterwards. | T9: =IF(H9="", "", VALUE(H9)) -> 0.534 | U9: =_xlfn.CONCAT(TEXT(A9,"#"), IF(AND(A9>=10, A9<=19), "th", IF(MOD(A9,10) = 1, "st", IF(MOD(A9,10) = 2, "nd", IF(MOD(A9,10) = 3, "rd", "th"))))) -> 3rd | V9: TRUE | W9: Thomas Pinckney and 5 more | X9: =IF(V9, W9, "") -> Thomas Pinckney and 5 more | Y9: =IF(NOT(V9), W9, "") | Z9: =_xlfn.CONCAT("https://en.wikipedia.org/wiki/", C9, "_United_States_presidential_election") -> https://en.wikipedia.org/wiki/1796_United_States_presidential_election | AA9: * Only 9 of the 16 states used any form of popular vote. Those states that did choose electors by popular vote had widely varying restrictions on suffrage via property requirements.
A10: 3 | B10: =VLOOKUP(D10,party!A:E,5,0) -> 23 | C10: 1796 | D10: Democratic-Republican | G10: 31115 | H10: 0.466 | I10: 122 | J10: 68 | K10: 54 | P10: 46.6% * | Q10: =IF(IFERROR(VLOOKUP($D10,party!$A:$D,2,0),"")="","",IFERROR(VLOOKUP($D10,party!$A:$D,2,0),"")) | R10: =IF(IFERROR(VLOOKUP($D10,party!$A:$D,3,0),"")="","",IFERROR(VLOOKUP($D10,party!$A:$D,3,0),"")) -> https://en.wikipedia.org/wiki/Democratic-Republican_Party | S10: =IF(IFERROR(VLOOKUP($D10,party!$A:$D,4,0),"")="","",IFERROR(VLOOKUP($D10,party!$A:$D,4,0),"")) -> The Republican Party, known retroactively as the Democratic-Republican Party (also referred to by historians as the Jeffersonian Republican Party), was an American political party founded by Thomas Jefferson and James Madison in the early 1790s. It championed liberalism, republicanism, individual liberty, equal rights, decentralization, free markets, free trade, and agrarianism. In foreign policy it was hostile to Great Britain and in sympathy with the French Revolution. The party became increasingly dominant after the 1800 elections as the opposing Federalist Party collapsed. | T10: =IF(H10="", "", VALUE(H10)) -> 0.466 | U10: =_xlfn.CONCAT(TEXT(A10,"#"), IF(AND(A10>=10, A10<=19), "th", IF(MOD(A10,10) = 1, "st", IF(MOD(A10,10) = 2, "nd", IF(MOD(A10,10) = 3, "rd", "th"))))) -> 3rd | V10: FALSE | W10: Thomas Jefferson and 4 more | X10: =IF(V10, W10, "") | Y10: =IF(NOT(V10), W10, "") -> Thomas Jefferson and 4 more | Z10: =_xlfn.CONCAT("https://en.wikipedia.org/wiki/", C10, "_United_States_presidential_election") -> https://en.wikipedia.org/wiki/1796_United_States_presidential_election | AA10: * Only 9 of the 16 states used any form of popular vote. Those states that did choose electors by popular vote had widely varying restrictions on suffrage via property requirements.
A11: 4 | B11: =VLOOKUP(D11,party!A:E,5,0) -> 23 | C11: 1800 | D11: Democratic-Republican | E11: Thomas Jefferson | G11: 41330 | H11: 0.614 | I11: 73 | P11: =TEXT(H11,"0.0%") -> 61.4% | Q11: =IF(IFERROR(VLOOKUP($D11,party!$A:$D,2,0),"")="","",IFERROR(VLOOKUP($D11,party!$A:$D,2,0),"")) | R11: =IF(IFERROR(VLOOKUP($D11,party!$A:$D,3,0),"")="","",IFERROR(VLOOKUP($D11,party!$A:$D,3,0),"")) -> https://en.wikipedia.org/wiki/Democratic-Republican_Party | S11: =IF(IFERROR(VLOOKUP($D11,party!$A:$D,4,0),"")="","",IFERROR(VLOOKUP($D11,party!$A:$D,4,0),"")) -> The Republican Party, known retroactively as the Democratic-Republican Party (also referred to by historians as the Jeffersonian Republican Party), was an American political party founded by Thomas Jefferson and James Madison in the early 1790s. It championed liberalism, republicanism, individual liberty, equal rights, decentralization, free markets, free trade, and agrarianism. In foreign policy it was hostile to Great Britain and in sympathy with the French Revolution. The party became increasingly dominant after the 1800 elections as the opposing Federalist Party collapsed. | T11: =IF(H11="", "", VALUE(H11)) -> 0.614 | U11: =_xlfn.CONCAT(TEXT(A11,"#"), IF(AND(A11>=10, A11<=19), "th", IF(MOD(A11,10) = 1, "st", IF(MOD(A11,10) = 2, "nd", IF(MOD(A11,10) = 3, "rd", "th"))))) -> 4th | V11: TRUE | X11: =IF(V11, W11, "") | Y11: =IF(NOT(V11), W11, "") | Z11: =_xlfn.CONCAT("https://en.wikipedia.org/wiki/", C11, "_United_States_presidential_election") -> https://en.wikipedia.org/wiki/1800_United_States_presidential_election
A12: 4 | B12: =VLOOKUP(D12,party!A:E,5,0) -> 10 | C12: 1800 | D12: Federalist | G12: 25952 | H12: 0.386 | I12: 65 | P12: =TEXT(H12,"0.0%") -> 38.6% | Q12: =IF(IFERROR(VLOOKUP($D12,party!$A:$D,2,0),"")="","",IFERROR(VLOOKUP($D12,party!$A:$D,2,0),"")) | R12: =IF(IFERROR(VLOOKUP($D12,party!$A:$D,3,0),"")="","",IFERROR(VLOOKUP($D12,party!$A:$D,3,0),"")) -> https://en.wikipedia.org/wiki/Federalist_Party | S12: =IF(IFERROR(VLOOKUP($D12,party!$A:$D,4,0),"")="","",IFERROR(VLOOKUP($D12,party!$A:$D,4,0),"")) -> The Federalist Party was a conservative and nationalist American political party and the first political party in the United States. It dominated the national government under Alexander Hamilton from 1789 to 1801. The party was defeated by the Democratic-Republican Party in 1800, and it became a minority party while keeping its stronghold in New England. It made a brief resurgence by opposing the War of 1812, then collapsed with its last presidential candidate in 1816. Remnants lasted for a few years afterwards. | T12: =IF(H12="", "", VALUE(H12)) -> 0.386 | U12: =_xlfn.CONCAT(TEXT(A12,"#"), IF(AND(A12>=10, A12<=19), "th", IF(MOD(A12,10) = 1, "st", IF(MOD(A12,10) = 2, "nd", IF(MOD(A12,10) = 3, "rd", "th"))))) -> 4th | V12: FALSE | W12: John Adams | X12: =IF(V12, W12, "") | Y12: =IF(NOT(V12), W12, "") -> John Adams | Z12: =_xlfn.CONCAT("https://en.wikipedia.org/wiki/", C12, "_United_States_presidential_election") -> https://en.wikipedia.org/wiki/1800_United_States_presidential_election
A13: 5 | B13: =VLOOKUP(D13,party!A:E,5,0) -> 23 | C13: 1804 | D13: Democratic-Republican | E13: Thomas Jefferson | G13: 104110 | H13: 0.728 | I13: 162 | P13: =TEXT(H13,"0.0%") -> 72.8% | Q13: =IF(IFERROR(VLOOKUP($D13,party!$A:$D,2,0),"")="","",IFERROR(VLOOKUP($D13,party!$A:$D,2,0),"")) | R13: =IF(IFERROR(VLOOKUP($D13,party!$A:$D,3,0),"")="","",IFERROR(VLOOKUP($D13,party!$A:$D,3,0),"")) -> https://en.wikipedia.org/wiki/Democratic-Republican_Party | S13: =IF(IFERROR(VLOOKUP($D13,party!$A:$D,4,0),"")="","",IFERROR(VLOOKUP($D13,party!$A:$D,4,0),"")) -> The Republican Party, known retroactively as the Democratic-Republican Party (also referred to by historians as the Jeffersonian Republican Party), was an American political party founded by Thomas Jefferson and James Madison in the early 1790s. It championed liberalism, republicanism, individual liberty, equal rights, decentralization, free markets, free trade, and agrarianism. In foreign policy it was hostile to Great Britain and in sympathy with the French Revolution. The party became increasingly dominant after the 1800 elections as the opposing Federalist Party collapsed. | T13: =IF(H13="", "", VALUE(H13)) -> 0.728 | U13: =_xlfn.CONCAT(TEXT(A13,"#"), IF(AND(A13>=10, A13<=19), "th", IF(MOD(A13,10) = 1, "st", IF(MOD(A13,10) = 2, "nd", IF(MOD(A13,10) = 3, "rd", "th"))))) -> 5th | V13: TRUE | X13: =IF(V13, W13, "") | Y13: =IF(NOT(V13), W13, "") | Z13: =_xlfn.CONCAT("https://en.wikipedia.org/wiki/", C13, "_United_States_presidential_election") -> https://en.wikipedia.org/wiki/1804_United_States_presidential_election
A14: 5 | B14: =VLOOKUP(D14,party!A:E,5,0) -> 10 | C14: 1804 | D14: Federalist | G14: 38919 | H14: 0.272 | I14: 14 | P14: =TEXT(H14,"0.0%") -> 27.2% | Q14: =IF(IFERROR(VLOOKUP($D14,party!$A:$D,2,0),"")="","",IFERROR(VLOOKUP($D14,party!$A:$D,2,0),"")) | R14: =IF(IFERROR(VLOOKUP($D14,party!$A:$D,3,0),"")="","",IFERROR(VLOOKUP($D14,party!$A:$D,3,0),"")) -> https://en.wikipedia.org/wiki/Federalist_Party | S14: =IF(IFERROR(VLOOKUP($D14,party!$A:$D,4,0),"")="","",IFERROR(VLOOKUP($D14,party!$A:$D,4,0),"")) -> The Federalist Party was a conservative and nationalist American political party and the first political party in the United States. It dominated the national government under Alexander Hamilton from 1789 to 1801. The party was defeated by the Democratic-Republican Party in 1800, and it became a minority party while keeping its stronghold in New England. It made a brief resurgence by opposing the War of 1812, then collapsed with its last presidential candidate in 1816. Remnants lasted for a few years afterwards. | T14: =IF(H14="", "", VALUE(H14)) -> 0.272 | U14: =_xlfn.CONCAT(TEXT(A14,"#"), IF(AND(A14>=10, A14<=19), "th", IF(MOD(A14,10) = 1, "st", IF(MOD(A14,10) = 2, "nd", IF(MOD(A14,10) = 3, "rd", "th"))))) -> 5th | V14: FALSE | W14: Charles Cotesworth Pinckney | X14: =IF(V14, W14, "") | Y14: =IF(NOT(V14), W14, "") -> Charles Cotesworth Pinckney | Z14: =_xlfn.CONCAT("https://en.wikipedia.org/wiki/", C14, "_United_States_presidential_election") -> https://en.wikipedia.org/wiki/1804_United_States_presidential_election
A15: 6 | B15: =VLOOKUP(D15,party!A:E,5,0) -> 23 | C15: 1808 | D15: Democratic-Republican | E15: James Madison | G15: 124732 | H15: 0.647 | I15: 128 | J15: 122 | K15: 6 | P15: =TEXT(H15,"0.0%") -> 64.7% | Q15: =IF(IFERROR(VLOOKUP($D15,party!$A:$D,2,0),"")="","",IFERROR(VLOOKUP($D15,party!$A:$D,2,0),"")) | R15: =IF(IFERROR(VLOOKUP($D15,party!$A:$D,3,0),"")="","",IFERROR(VLOOKUP($D15,party!$A:$D,3,0),"")) -> https://en.wikipedia.org/wiki/Democratic-Republican_Party | S15: =IF(IFERROR(VLOOKUP($D15,party!$A:$D,4,0),"")="","",IFERROR(VLOOKUP($D15,party!$A:$D,4,0),"")) -> The Republican Party, known retroactively as the Democratic-Republican Party (also referred to by historians as the Jeffersonian Republican Party), was an American political party founded by Thomas Jefferson and James Madison in the early 1790s. It championed liberalism, republicanism, individual liberty, equal rights, decentralization, free markets, free trade, and agrarianism. In foreign policy it was hostile to Great Britain and in sympathy with the French Revolution. The party became increasingly dominant after the 1800 elections as the opposing Federalist Party collapsed. | T15: =IF(H15="", "", VALUE(H15)) -> 0.647 | U15: =_xlfn.CONCAT(TEXT(A15,"#"), IF(AND(A15>=10, A15<=19), "th", IF(MOD(A15,10) = 1, "st", IF(MOD(A15,10) = 2, "nd", IF(MOD(A15,10) = 3, "rd", "th"))))) -> 6th | V15: TRUE | W15: George Clinton | X15: =IF(V15, W15, "") -> George Clinton | Y15: =IF(NOT(V15), W15, "") | Z15: =_xlfn.CONCAT("https://en.wikipedia.org/wiki/", C15, "_United_States_presidential_election") -> https://en.wikipedia.org/wiki/1808_United_States_presidential_election
A16: 6 | B16: =VLOOKUP(D16,party!A:E,5,0) -> 10 | C16: 1808 | D16: Federalist | G16: 62431 | H16: 0.324 | I16: 47 | P16: =TEXT(H16,"0.0%") -> 32.4% | Q16: =IF(IFERROR(VLOOKUP($D16,party!$A:$D,2,0),"")="","",IFERROR(VLOOKUP($D16,party!$A:$D,2,0),"")) | R16: =IF(IFERROR(VLOOKUP($D16,party!$A:$D,3,0),"")="","",IFERROR(VLOOKUP($D16,party!$A:$D,3,0),"")) -> https://en.wikipedia.org/wiki/Federalist_Party | S16: =IF(IFERROR(VLOOKUP($D16,party!$A:$D,4,0),"")="","",IFERROR(VLOOKUP($D16,party!$A:$D,4,0),"")) -> The Federalist Party was a conservative and nationalist American political party and the first political party in the United States. It dominated the national government under Alexander Hamilton from 1789 to 1801. The party was defeated by the Democratic-Republican Party in 1800, and it became a minority party while keeping its stronghold in New England. It made a brief resurgence by opposing the War of 1812, then collapsed with its last presidential candidate in 1816. Remnants lasted for a few years afterwards. | T16: =IF(H16="", "", VALUE(H16)) -> 0.324 | U16: =_xlfn.CONCAT(TEXT(A16,"#"), IF(AND(A16>=10, A16<=19), "th", IF(MOD(A16,10) = 1, "st", IF(MOD(A16,10) = 2, "nd", IF(MOD(A16,10) = 3, "rd", "th"))))) -> 6th | V16: FALSE | W16: Charles Cotesworth Pinckney | X16: =IF(V16, W16, "") | Y16: =IF(NOT(V16), W16, "") -> Charles Cotesworth Pinckney | Z16: =_xlfn.CONCAT("https://en.wikipedia.org/wiki/", C16, "_United_States_presidential_election") -> https://en.wikipedia.org/wiki/1808_United_States_presidential_election
A17: 7 | B17: =VLOOKUP(D17,party!A:E,5,0) -> 23 | C17: 1812 | D17: Democratic-Republican | E17: James Madison | G17: 140431 | H17: 0.504 | I17: 128 | P17: =TEXT(H17,"0.0%") -> 50.4% | Q17: =IF(IFERROR(VLOOKUP($D17,party!$A:$D,2,0),"")="","",IFERROR(VLOOKUP($D17,party!$A:$D,2,0),"")) | R17: =IF(IFERROR(VLOOKUP($D17,party!$A:$D,3,0),"")="","",IFERROR(VLOOKUP($D17,party!$A:$D,3,0),"")) -> https://en.wikipedia.org/wiki/Democratic-Republican_Party | S17: =IF(IFERROR(VLOOKUP($D17,party!$A:$D,4,0),"")="","",IFERROR(VLOOKUP($D17,party!$A:$D,4,0),"")) -> The Republican Party, known retroactively as the Democratic-Republican Party (also referred to by historians as the Jeffersonian Republican Party), was an American political party founded by Thomas Jefferson and James Madison in the early 1790s. It championed liberalism, republicanism, individual liberty, equal rights, decentralization, free markets, free trade, and agrarianism. In foreign policy it was hostile to Great Britain and in sympathy with the French Revolution. The party became increasingly dominant after the 1800 elections as the opposing Federalist Party collapsed. | T17: =IF(H17="", "", VALUE(H17)) -> 0.504 | U17: =_xlfn.CONCAT(TEXT(A17,"#"), IF(AND(A17>=10, A17<=19), "th", IF(MOD(A17,10) = 1, "st", IF(MOD(A17,10) = 2, "nd", IF(MOD(A17,10) = 3, "rd", "th"))))) -> 7th | V17: TRUE | X17: =IF(V17, W17, "") | Y17: =IF(NOT(V17), W17, "") | Z17: =_xlfn.CONCAT("https://en.wikipedia.org/wiki/", C17, "_United_States_presidential_election") -> https://en.wikipedia.org/wiki/1812_United_States_presidential_election
A18: 7 | B18: =VLOOKUP(D18,party!A:E,5,0) -> 22 | C18: 1812 | D18: Democratic-Republican / Federalist | G18: 132781 | H18: 0.476 | I18: 89 | P18: =TEXT(H18,"0.0%") -> 47.6% | Q18: =IF(IFERROR(VLOOKUP($D18,party!$A:$D,2,0),"")="","",IFERROR(VLOOKUP($D18,party!$A:$D,2,0),"")) -> Not a party. | R18: =IF(IFERROR(VLOOKUP($D18,party!$A:$D,3,0),"")="","",IFERROR(VLOOKUP($D18,party!$A:$D,3,0),"")) -> https://en.wikipedia.org/wiki/1812_United_States_presidential_election | S18: =IF(IFERROR(VLOOKUP($D18,party!$A:$D,4,0),"")="","",IFERROR(VLOOKUP($D18,party!$A:$D,4,0),"")) -> While commonly labeled as the Federalist candidate, Clinton technically ran as a Democratic-Republican and was not nominated by the Federalist party itself, the latter simply deciding not to field a candidate. This did not prevent endorsements from state Federalist parties (such as in Pennsylvania), but he received the endorsement from the New York state Democratic-Republicans as well. | T18: =IF(H18="", "", VALUE(H18)) -> 0.476 | U18: =_xlfn.CONCAT(TEXT(A18,"#"), IF(AND(A18>=10, A18<=19), "th", IF(MOD(A18,10) = 1, "st", IF(MOD(A18,10) = 2, "nd", IF(MOD(A18,10) = 3, "rd", "th"))))) -> 7th | V18: FALSE | W18: DeWitt Clinton | X18: =IF(V18, W18, "") | Y18: =IF(NOT(V18), W18, "") -> DeWitt Clinton | Z18: =_xlfn.CONCAT("https://en.wikipedia.org/wiki/", C18, "_United_States_presidential_election") -> https://en.wikipedia.org/wiki/1812_United_States_presidential_election
A19: 8 | B19: =VLOOKUP(D19,party!A:E,5,0) -> 23 | C19: 1816 | D19: Democratic-Republican | E19: James Monroe | G19: 76592 | H19: 0.682 | I19: 183 | P19: =TEXT(H19,"0.0%") -> 68.2% | Q19: =IF(IFERROR(VLOOKUP($D19,party!$A:$D,2,0),"")="","",IFERROR(VLOOKUP($D19,party!$A:$D,2,0),"")) | R19: =IF(IFERROR(VLOOKUP($D19,party!$A:$D,3,0),"")="","",IFERROR(VLOOKUP($D19,party!$A:$D,3,0),"")) -> https://en.wikipedia.org/wiki/Democratic-Republican_Party | S19: =IF(IFERROR(VLOOKUP($D19,party!$A:$D,4,0),"")="","",IFERROR(VLOOKUP($D19,party!$A:$D,4,0),"")) -> The Republican Party, known retroactively as the Democratic-Republican Party (also referred to by historians as the Jeffersonian Republican Party), was an American political party founded by Thomas Jefferson and James Madison in the early 1790s. It championed liberalism, republicanism, individual liberty, equal rights, decentralization, free markets, free trade, and agrarianism. In foreign policy it was hostile to Great Britain and in sympathy with the French Revolution. The party became increasingly dominant after the 1800 elections as the opposing Federalist Party collapsed. | T19: =IF(H19="", "", VALUE(H19)) -> 0.682 | U19: =_xlfn.CONCAT(TEXT(A19,"#"), IF(AND(A19>=10, A19<=19), "th", IF(MOD(A19,10) = 1, "st", IF(MOD(A19,10) = 2, "nd", IF(MOD(A19,10) = 3, "rd", "th"))))) -> 8th | V19: TRUE | X19: =IF(V19, W19, "") | Y19: =IF(NOT(V19), W19, "") | Z19: =_xlfn.CONCAT("https://en.wikipedia.org/wiki/", C19, "_United_States_presidential_election") -> https://en.wikipedia.org/wiki/1816_United_States_presidential_election
A20: 8 | B20: =VLOOKUP(D20,party!A:E,5,0) -> 10 | C20: 1816 | D20: Federalist | G20: 34740 | H20: 0.309 | I20: 34 | P20: =TEXT(H20,"0.0%") -> 30.9% | Q20: =IF(IFERROR(VLOOKUP($D20,party!$A:$D,2,0),"")="","",IFERROR(VLOOKUP($D20,party!$A:$D,2,0),"")) | R20: =IF(IFERROR(VLOOKUP($D20,party!$A:$D,3,0),"")="","",IFERROR(VLOOKUP($D20,party!$A:$D,3,0),"")) -> https://en.wikipedia.org/wiki/Federalist_Party | S20: =IF(IFERROR(VLOOKUP($D20,party!$A:$D,4,0),"")="","",IFERROR(VLOOKUP($D20,party!$A:$D,4,0),"")) -> The Federalist Party was a conservative and nationalist American political party and the first political party in the United States. It dominated the national government under Alexander Hamilton from 1789 to 1801. The party was defeated by the Democratic-Republican Party in 1800, and it became a minority party while keeping its stronghold in New England. It made a brief resurgence by opposing the War of 1812, then collapsed with its last presidential candidate in 1816. Remnants lasted for a few years afterwards. | T20: =IF(H20="", "", VALUE(H20)) -> 0.309 | U20: =_xlfn.CONCAT(TEXT(A20,"#"), IF(AND(A20>=10, A20<=19), "th", IF(MOD(A20,10) = 1, "st", IF(MOD(A20,10) = 2, "nd", IF(MOD(A20,10) = 3, "rd", "th"))))) -> 8th | V20: FALSE | W20: Rufus King | X20: =IF(V20, W20, "") | Y20: =IF(NOT(V20), W20, "") -> Rufus King | Z20: =_xlfn.CONCAT("https://en.wikipedia.org/wiki/", C20, "_United_States_presidential_election") -> https://en.wikipedia.org/wiki/1816_United_States_presidential_election
A21: 9 | B21: =VLOOKUP(D21,party!A:E,5,0) -> 23 | C21: 1820 | D21: Democratic-Republican | E21: James Monroe | G21: 87343 | H21: 0.806 | I21: 232 | P21: =TEXT(H21,"0.0%") -> 80.6% | Q21: =IF(IFERROR(VLOOKUP($D21,party!$A:$D,2,0),"")="","",IFERROR(VLOOKUP($D21,party!$A:$D,2,0),"")) | R21: =IF(IFERROR(VLOOKUP($D21,party!$A:$D,3,0),"")="","",IFERROR(VLOOKUP($D21,party!$A:$D,3,0),"")) -> https://en.wikipedia.org/wiki/Democratic-Republican_Party | S21: =IF(IFERROR(VLOOKUP($D21,party!$A:$D,4,0),"")="","",IFERROR(VLOOKUP($D21,party!$A:$D,4,0),"")) -> The Republican Party, known retroactively as the Democratic-Republican Party (also referred to by historians as the Jeffersonian Republican Party), was an American political party founded by Thomas Jefferson and James Madison in the early 1790s. It championed liberalism, republicanism, individual liberty, equal rights, decentralization, free markets, free trade, and agrarianism. In foreign policy it was hostile to Great Britain and in sympathy with the French Revolution. The party became increasingly dominant after the 1800 elections as the opposing Federalist Party collapsed. | T21: =IF(H21="", "", VALUE(H21)) -> 0.806 | U21: =_xlfn.CONCAT(TEXT(A21,"#"), IF(AND(A21>=10, A21<=19), "th", IF(MOD(A21,10) = 1, "st", IF(MOD(A21,10) = 2, "nd", IF(MOD(A21,10) = 3, "rd", "th"))))) -> 9th | V21: TRUE | W21: John Quincy Adams | X21: =IF(V21, W21, "") -> John Quincy Adams | Y21: =IF(NOT(V21), W21, "") | Z21: =_xlfn.CONCAT("https://en.wikipedia.org/wiki/", C21, "_United_States_presidential_election") -> https://en.wikipedia.org/wiki/1820_United_States_presidential_election
A22: 10 | B22: =VLOOKUP(D22,party!A:E,5,0) -> 12 | C22: 1824 | D22: Democratic-Republican (Adams faction) | E22: John Quincy Adams | G22: 113122 | H22: 0.309 | I22: 84 | P22: =TEXT(H22,"0.0%") -> 30.9% | Q22: =IF(IFERROR(VLOOKUP($D22,party!$A:$D,2,0),"")="","",IFERROR(VLOOKUP($D22,party!$A:$D,2,0),"")) -> Not a party. | R22: =IF(IFERROR(VLOOKUP($D22,party!$A:$D,3,0),"")="","",IFERROR(VLOOKUP($D22,party!$A:$D,3,0),"")) -> https://en.wikipedia.org/wiki/1824_United_States_presidential_election | S22: =IF(IFERROR(VLOOKUP($D22,party!$A:$D,4,0),"")="","",IFERROR(VLOOKUP($D22,party!$A:$D,4,0),"")) -> The Democratic-Republican Party had won six consecutive presidential elections and by 1824 was the only national political party. However, as the election approached, the presence of multiple viable candidates resulted in there being multiple nominations by the contending factions, signaling the splintering of the party and an end to the Era of Good Feelings, as well as the First Party System. Adams won New England, Jackson and Adams split the mid-Atlantic states, Jackson and Clay split the Western states, and Jackson and Crawford split the Southern states. | T22: =IF(H22="", "", VALUE(H22)) -> 0.309 | U22: =_xlfn.CONCAT(TEXT(A22,"#"), IF(AND(A22>=10, A22<=19), "th", IF(MOD(A22,10) = 1, "st", IF(MOD(A22,10) = 2, "nd", IF(MOD(A22,10) = 3, "rd", "th"))))) -> 10th | V22: TRUE | X22: =IF(V22, W22, "") | Y22: =IF(NOT(V22), W22, "") | Z22: =_xlfn.CONCAT("https://en.wikipedia.org/wiki/", C22, "_United_States_presidential_election") -> https://en.wikipedia.org/wiki/1824_United_States_presidential_election | AA22: Since no candidate received a majority of the electoral vote, the House of Representatives elected the president. In the House, 13 state delegations voted for Adams, seven for Jackson, and four for Crawford.
A23: 10 | B23: =VLOOKUP(D23,party!A:E,5,0) -> 25 | C23: 1824 | D23: Democratic-Republican (Jackson faction) | G23: 151271 | H23: 0.414 | I23: 99 | P23: =TEXT(H23,"0.0%") -> 41.4% | Q23: =IF(IFERROR(VLOOKUP($D23,party!$A:$D,2,0),"")="","",IFERROR(VLOOKUP($D23,party!$A:$D,2,0),"")) -> Not a party. | R23: =IF(IFERROR(VLOOKUP($D23,party!$A:$D,3,0),"")="","",IFERROR(VLOOKUP($D23,party!$A:$D,3,0),"")) -> https://en.wikipedia.org/wiki/1824_United_States_presidential_election | S23: =IF(IFERROR(VLOOKUP($D23,party!$A:$D,4,0),"")="","",IFERROR(VLOOKUP($D23,party!$A:$D,4,0),"")) -> The Democratic-Republican Party had won six consecutive presidential elections and by 1824 was the only national political party. However, as the election approached, the presence of multiple viable candidates resulted in there being multiple nominations by the contending factions, signaling the splintering of the party and an end to the Era of Good Feelings, as well as the First Party System. Adams won New England, Jackson and Adams split the mid-Atlantic states, Jackson and Clay split the Western states, and Jackson and Crawford split the Southern states. | T23: =IF(H23="", "", VALUE(H23)) -> 0.414 | U23: =_xlfn.CONCAT(TEXT(A23,"#"), IF(AND(A23>=10, A23<=19), "th", IF(MOD(A23,10) = 1, "st", IF(MOD(A23,10) = 2, "nd", IF(MOD(A23,10) = 3, "rd", "th"))))) -> 10th | V23: FALSE | W23: Andrew Jackson | X23: =IF(V23, W23, "") | Y23: =IF(NOT(V23), W23, "") -> Andrew Jackson | Z23: =_xlfn.CONCAT("https://en.wikipedia.org/wiki/", C23, "_United_States_presidential_election") -> https://en.wikipedia.org/wiki/1824_United_States_presidential_election | AA23: Since no candidate received a majority of the electoral vote, the House of Representatives elected the president. In the House, 13 state delegations voted for Adams, seven for Jackson, and four for Crawford.
A24: 10 | B24: =VLOOKUP(D24,party!A:E,5,0) -> 24 | C24: 1824 | D24: Democratic-Republican (Crawford faction) | G24: 40856 | H24: 0.112 | I24: 40 | P24: =TEXT(H24,"0.0%") -> 11.2% | Q24: =IF(IFERROR(VLOOKUP($D24,party!$A:$D,2,0),"")="","",IFERROR(VLOOKUP($D24,party!$A:$D,2,0),"")) -> Not a party. | R24: =IF(IFERROR(VLOOKUP($D24,party!$A:$D,3,0),"")="","",IFERROR(VLOOKUP($D24,party!$A:$D,3,0),"")) -> https://en.wikipedia.org/wiki/1824_United_States_presidential_election | S24: =IF(IFERROR(VLOOKUP($D24,party!$A:$D,4,0),"")="","",IFERROR(VLOOKUP($D24,party!$A:$D,4,0),"")) -> The Democratic-Republican Party had won six consecutive presidential elections and by 1824 was the only national political party. However, as the election approached, the presence of multiple viable candidates resulted in there being multiple nominations by the contending factions, signaling the splintering of the party and an end to the Era of Good Feelings, as well as the First Party System. Adams won New England, Jackson and Adams split the mid-Atlantic states, Jackson and Clay split the Western states, and Jackson and Crawford split the Southern states. | T24: =IF(H24="", "", VALUE(H24)) -> 0.112 | U24: =_xlfn.CONCAT(TEXT(A24,"#"), IF(AND(A24>=10, A24<=19), "th", IF(MOD(A24,10) = 1, "st", IF(MOD(A24,10) = 2, "nd", IF(MOD(A24,10) = 3, "rd", "th"))))) -> 10th | V24: FALSE | W24: William H. Crawford | X24: =IF(V24, W24, "") | Y24: =IF(NOT(V24), W24, "") -> William H. Crawford | Z24: =_xlfn.CONCAT("https://en.wikipedia.org/wiki/", C24, "_United_States_presidential_election") -> https://en.wikipedia.org/wiki/1824_United_States_presidential_election | AA24: Since no candidate received a majority of the electoral vote, the House of Representatives elected the president. In the House, 13 state delegations voted for Adams, seven for Jackson, and four for Crawford.
A25: 10 | B25: =VLOOKUP(D25,party!A:E,5,0) -> 11 | C25: 1824 | D25: Democratic-Republican (Clay faction) | G25: 47531 | H25: 0.13 | I25: 38 | P25: =TEXT(H25,"0.0%") -> 13.0% | Q25: =IF(IFERROR(VLOOKUP($D25,party!$A:$D,2,0),"")="","",IFERROR(VLOOKUP($D25,party!$A:$D,2,0),"")) -> Not a party. | R25: =IF(IFERROR(VLOOKUP($D25,party!$A:$D,3,0),"")="","",IFERROR(VLOOKUP($D25,party!$A:$D,3,0),"")) -> https://en.wikipedia.org/wiki/1824_United_States_presidential_election | S25: =IF(IFERROR(VLOOKUP($D25,party!$A:$D,4,0),"")="","",IFERROR(VLOOKUP($D25,party!$A:$D,4,0),"")) -> The Democratic-Republican Party had won six consecutive presidential elections and by 1824 was the only national political party. However, as the election approached, the presence of multiple viable candidates resulted in there being multiple nominations by the contending factions, signaling the splintering of the party and an end to the Era of Good Feelings, as well as the First Party System. Adams won New England, Jackson and Adams split the mid-Atlantic states, Jackson and Clay split the Western states, and Jackson and Crawford split the Southern states. | T25: =IF(H25="", "", VALUE(H25)) -> 0.13 | U25: =_xlfn.CONCAT(TEXT(A25,"#"), IF(AND(A25>=10, A25<=19), "th", IF(MOD(A25,10) = 1, "st", IF(MOD(A25,10) = 2, "nd", IF(MOD(A25,10) = 3, "rd", "th"))))) -> 10th | V25: FALSE | W25: Henry Clay | X25: =IF(V25, W25, "") | Y25: =IF(NOT(V25), W25, "") -> Henry Clay | Z25: =_xlfn.CONCAT("https://en.wikipedia.org/wiki/", C25, "_United_States_presidential_election") -> https://en.wikipedia.org/wiki/1824_United_States_presidential_election | AA25: Since no candidate received a majority of the electoral vote, the House of Representatives elected the president. In the House, 13 state delegations voted for Adams, seven for Jackson, and four for Crawford.
A26: 11 | B26: =VLOOKUP(D26,party!A:E,5,0) -> 26 | C26: 1828 | D26: Democratic | E26: Andrew Jackson | G26: 642553 | H26: 0.56 | I26: 178 | P26: =TEXT(H26,"0.0%") -> 56.0% | Q26: =IF(IFERROR(VLOOKUP($D26,party!$A:$D,2,0),"")="","",IFERROR(VLOOKUP($D26,party!$A:$D,2,0),"")) | R26: =IF(IFERROR(VLOOKUP($D26,party!$A:$D,3,0),"")="","",IFERROR(VLOOKUP($D26,party!$A:$D,3,0),"")) -> https://en.wikipedia.org/wiki/Democratic_Party_(United_States) | S26: =IF(IFERROR(VLOOKUP($D26,party!$A:$D,4,0),"")="","",IFERROR(VLOOKUP($D26,party!$A:$D,4,0),"")) -> The Democratic Party is one of the two major contemporary political parties in the United States. Since the late 1850s, its main political rival has been the Republican Party; the two parties have since dominated American politics. The Democratic Party was founded in 1828. The Democratic Party is the world's oldest active political party. It initially supported expansive presidential power, the interests of slave states, agrarianism, and geographical expansionism, while opposing a national bank and high tariffs. It split in 1860 over slavery and won the presidency only twice between 1860 and 1912, although it won the popular vote two more times in that period. | T26: =IF(H26="", "", VALUE(H26)) -> 0.56 | U26: =_xlfn.CONCAT(TEXT(A26,"#"), IF(AND(A26>=10, A26<=19), "th", IF(MOD(A26,10) = 1, "st", IF(MOD(A26,10) = 2, "nd", IF(MOD(A26,10) = 3, "rd", "th"))))) -> 11th | V26: TRUE | X26: =IF(V26, W26, "") | Y26: =IF(NOT(V26), W26, "") | Z26: =_xlfn.CONCAT("https://en.wikipedia.org/wiki/", C26, "_United_States_presidential_election") -> https://en.wikipedia.org/wiki/1828_United_States_presidential_election
A27: 11 | B27: =VLOOKUP(D27,party!A:E,5,0) -> 13 | C27: 1828 | D27: National Republican | G27: 500897 | H27: 0.436 | I27: 83 | P27: =TEXT(H27,"0.0%") -> 43.6% | Q27: =IF(IFERROR(VLOOKUP($D27,party!$A:$D,2,0),"")="","",IFERROR(VLOOKUP($D27,party!$A:$D,2,0),"")) | R27: =IF(IFERROR(VLOOKUP($D27,party!$A:$D,3,0),"")="","",IFERROR(VLOOKUP($D27,party!$A:$D,3,0),"")) -> https://en.wikipedia.org/wiki/National_Republican_Party | S27: =IF(IFERROR(VLOOKUP($D27,party!$A:$D,4,0),"")="","",IFERROR(VLOOKUP($D27,party!$A:$D,4,0),"")) -> The National Republican Party, also known as the Anti-Jacksonian Party or simply Republicans, was a political party in the United States which evolved from a conservative-leaning faction of the Democratic-Republican Party that supported John Quincy Adams in the 1824 presidential election. After the 1832 election, opponents of Jackson coalesced into the Whig Party. National Republicans, Anti-Masons and others joined the new party. | T27: =IF(H27="", "", VALUE(H27)) -> 0.436 | U27: =_xlfn.CONCAT(TEXT(A27,"#"), IF(AND(A27>=10, A27<=19), "th", IF(MOD(A27,10) = 1, "st", IF(MOD(A27,10) = 2, "nd", IF(MOD(A27,10) = 3, "rd", "th"))))) -> 11th | V27: FALSE | W27: John Quincy Adams | X27: =IF(V27, W27, "") | Y27: =IF(NOT(V27), W27, "") -> John Quincy Adams | Z27: =_xlfn.CONCAT("https://en.wikipedia.org/wiki/", C27, "_United_States_presidential_election") -> https://en.wikipedia.org/wiki/1828_United_States_presidential_election
A28: 12 | B28: =VLOOKUP(D28,party!A:E,5,0) -> 26 | C28: 1832 | D28: Democratic | E28: Andrew Jackson | G28: 701780 | H28: 0.542 | I28: 219 | P28: =TEXT(H28,"0.0%") -> 54.2% | Q28: =IF(IFERROR(VLOOKUP($D28,party!$A:$D,2,0),"")="","",IFERROR(VLOOKUP($D28,party!$A:$D,2,0),"")) | R28: =IF(IFERROR(VLOOKUP($D28,party!$A:$D,3,0),"")="","",IFERROR(VLOOKUP($D28,party!$A:$D,3,0),"")) -> https://en.wikipedia.org/wiki/Democratic_Party_(United_States) | S28: =IF(IFERROR(VLOOKUP($D28,party!$A:$D,4,0),"")="","",IFERROR(VLOOKUP($D28,party!$A:$D,4,0),"")) -> The Democratic Party is one of the two major contemporary political parties in the United States. Since the late 1850s, its main political rival has been the Republican Party; the two parties have since dominated American politics. The Democratic Party was founded in 1828. The Democratic Party is the world's oldest active political party. It initially supported expansive presidential power, the interests of slave states, agrarianism, and geographical expansionism, while opposing a national bank and high tariffs. It split in 1860 over slavery and won the presidency only twice between 1860 and 1912, although it won the popular vote two more times in that period. | T28: =IF(H28="", "", VALUE(H28)) -> 0.542 | U28: =_xlfn.CONCAT(TEXT(A28,"#"), IF(AND(A28>=10, A28<=19), "th", IF(MOD(A28,10) = 1, "st", IF(MOD(A28,10) = 2, "nd", IF(MOD(A28,10) = 3, "rd", "th"))))) -> 12th | V28: TRUE | X28: =IF(V28, W28, "") | Y28: =IF(NOT(V28), W28, "") | Z28: =_xlfn.CONCAT("https://en.wikipedia.org/wiki/", C28, "_United_States_presidential_election") -> https://en.wikipedia.org/wiki/1832_United_States_presidential_election
A29: 12 | B29: =VLOOKUP(D29,party!A:E,5,0) -> 13 | C29: 1832 | D29: National Republican | G29: 484205 | H29: 0.374 | I29: 49 | P29: =TEXT(H29,"0.0%") -> 37.4% | Q29: =IF(IFERROR(VLOOKUP($D29,party!$A:$D,2,0),"")="","",IFERROR(VLOOKUP($D29,party!$A:$D,2,0),"")) | R29: =IF(IFERROR(VLOOKUP($D29,party!$A:$D,3,0),"")="","",IFERROR(VLOOKUP($D29,party!$A:$D,3,0),"")) -> https://en.wikipedia.org/wiki/National_Republican_Party | S29: =IF(IFERROR(VLOOKUP($D29,party!$A:$D,4,0),"")="","",IFERROR(VLOOKUP($D29,party!$A:$D,4,0),"")) -> The National Republican Party, also known as the Anti-Jacksonian Party or simply Republicans, was a political party in the United States which evolved from a conservative-leaning faction of the Democratic-Republican Party that supported John Quincy Adams in the 1824 presidential election. After the 1832 election, opponents of Jackson coalesced into the Whig Party. National Republicans, Anti-Masons and others joined the new party. | T29: =IF(H29="", "", VALUE(H29)) -> 0.374 | U29: =_xlfn.CONCAT(TEXT(A29,"#"), IF(AND(A29>=10, A29<=19), "th", IF(MOD(A29,10) = 1, "st", IF(MOD(A29,10) = 2, "nd", IF(MOD(A29,10) = 3, "rd", "th"))))) -> 12th | V29: FALSE | W29: Henry Clay | X29: =IF(V29, W29, "") | Y29: =IF(NOT(V29), W29, "") -> Henry Clay | Z29: =_xlfn.CONCAT("https://en.wikipedia.org/wiki/", C29, "_United_States_presidential_election") -> https://en.wikipedia.org/wiki/1832_United_States_presidential_election
A30: 12 | B30: =VLOOKUP(D30,party!A:E,5,0) -> 2 | C30: 1832 | D30: Nullifier | G30: 0 | I30: 11 | P30: n/a * | Q30: =IF(IFERROR(VLOOKUP($D30,party!$A:$D,2,0),"")="","",IFERROR(VLOOKUP($D30,party!$A:$D,2,0),"")) | R30: =IF(IFERROR(VLOOKUP($D30,party!$A:$D,3,0),"")="","",IFERROR(VLOOKUP($D30,party!$A:$D,3,0),"")) -> https://en.wikipedia.org/wiki/Nullifier_Party | S30: =IF(IFERROR(VLOOKUP($D30,party!$A:$D,4,0),"")="","",IFERROR(VLOOKUP($D30,party!$A:$D,4,0),"")) -> The Nullifier Party was an American political party based in South Carolina in the 1830s. Considered an early American third party, it was started by John C. Calhoun in 1828. The Nullifier Party was a states' rights, pro-slavery party that supported strict constructionism with regards to the U.S. government's enumerated powers, holding that states could nullify federal laws within their borders. It narrowly missed claiming the unofficial title of being the first ever third party to be created within the United States—that title belongs to the Anti-Masonic Party, which was created in New York in February 1828. | T30: =IF(H30="", "", VALUE(H30)) | U30: =_xlfn.CONCAT(TEXT(A30,"#"), IF(AND(A30>=10, A30<=19), "th", IF(MOD(A30,10) = 1, "st", IF(MOD(A30,10) = 2, "nd", IF(MOD(A30,10) = 3, "rd", "th"))))) -> 12th | V30: FALSE | W30: John Floyd | X30: =IF(V30, W30, "") | Y30: =IF(NOT(V30), W30, "") -> John Floyd | Z30: =_xlfn.CONCAT("https://en.wikipedia.org/wiki/", C30, "_United_States_presidential_election") -> https://en.wikipedia.org/wiki/1832_United_States_presidential_election | AA30: * All the electoral votes came from South Carolina, where the electors were chosen by the legislature and not by popular vote.
A31: 12 | B31: =VLOOKUP(D31,party!A:E,5,0) -> 14 | C31: 1832 | D31: Anti-Masonic | G31: 100715 | H31: 0.078 | I31: 7 | P31: =TEXT(H31,"0.0%") -> 7.8% | Q31: =IF(IFERROR(VLOOKUP($D31,party!$A:$D,2,0),"")="","",IFERROR(VLOOKUP($D31,party!$A:$D,2,0),"")) | R31: =IF(IFERROR(VLOOKUP($D31,party!$A:$D,3,0),"")="","",IFERROR(VLOOKUP($D31,party!$A:$D,3,0),"")) -> https://en.wikipedia.org/wiki/Anti-Masonic_Party | S31: =IF(IFERROR(VLOOKUP($D31,party!$A:$D,4,0),"")="","",IFERROR(VLOOKUP($D31,party!$A:$D,4,0),"")) -> The Anti-Masonic Party was the earliest third party in the United States. Formally a single-issue party, it strongly opposed Freemasonry in the United States. It was active from the late 1820s, especially in the Northeast, and later attempted to become a major party by expanding its platform to take positions on other issues. It declined quickly after 1832 as most members joined the new Whig Party; it disappeared after 1838. | T31: =IF(H31="", "", VALUE(H31)) -> 0.078 | U31: =_xlfn.CONCAT(TEXT(A31,"#"), IF(AND(A31>=10, A31<=19), "th", IF(MOD(A31,10) = 1, "st", IF(MOD(A31,10) = 2, "nd", IF(MOD(A31,10) = 3, "rd", "th"))))) -> 12th | V31: FALSE | W31: William Wirt | X31: =IF(V31, W31, "") | Y31: =IF(NOT(V31), W31, "") -> William Wirt | Z31: =_xlfn.CONCAT("https://en.wikipedia.org/wiki/", C31, "_United_States_presidential_election") -> https://en.wikipedia.org/wiki/1832_United_States_presidential_election
A32: 13 | B32: =VLOOKUP(D32,party!A:E,5,0) -> 26 | C32: 1836 | D32: Democratic | E32: Martin Van Buren | G32: 763291 | H32: 0.508 | I32: 170 | P32: =TEXT(H32,"0.0%") -> 50.8% | Q32: =IF(IFERROR(VLOOKUP($D32,party!$A:$D,2,0),"")="","",IFERROR(VLOOKUP($D32,party!$A:$D,2,0),"")) | R32: =IF(IFERROR(VLOOKUP($D32,party!$A:$D,3,0),"")="","",IFERROR(VLOOKUP($D32,party!$A:$D,3,0),"")) -> https://en.wikipedia.org/wiki/Democratic_Party_(United_States) | S32: =IF(IFERROR(VLOOKUP($D32,party!$A:$D,4,0),"")="","",IFERROR(VLOOKUP($D32,party!$A:$D,4,0),"")) -> The Democratic Party is one of the two major contemporary political parties in the United States. Since the late 1850s, its main political rival has been the Republican Party; the two parties have since dominated American politics. The Democratic Party was founded in 1828. The Democratic Party is the world's oldest active political party. It initially supported expansive presidential power, the interests of slave states, agrarianism, and geographical expansionism, while opposing a national bank and high tariffs. It split in 1860 over slavery and won the presidency only twice between 1860 and 1912, although it won the popular vote two more times in that period. | T32: =IF(H32="", "", VALUE(H32)) -> 0.508 | U32: =_xlfn.CONCAT(TEXT(A32,"#"), IF(AND(A32>=10, A32<=19), "th", IF(MOD(A32,10) = 1, "st", IF(MOD(A32,10) = 2, "nd", IF(MOD(A32,10) = 3, "rd", "th"))))) -> 13th | V32: TRUE | X32: =IF(V32, W32, "") | Y32: =IF(NOT(V32), W32, "") | Z32: =_xlfn.CONCAT("https://en.wikipedia.org/wiki/", C32, "_United_States_presidential_election") -> https://en.wikipedia.org/wiki/1836_United_States_presidential_election
A33: 13 | B33: =VLOOKUP(D33,party!A:E,5,0) -> 15 | C33: 1836 | D33: Whig | G33: 737215 | H33: 0.49 | I33: 124 | P33: =TEXT(H33,"0.0%") -> 49.0% | Q33: =IF(IFERROR(VLOOKUP($D33,party!$A:$D,2,0),"")="","",IFERROR(VLOOKUP($D33,party!$A:$D,2,0),"")) | R33: =IF(IFERROR(VLOOKUP($D33,party!$A:$D,3,0),"")="","",IFERROR(VLOOKUP($D33,party!$A:$D,3,0),"")) -> https://en.wikipedia.org/wiki/Whig_Party_(United_States) | S33: =IF(IFERROR(VLOOKUP($D33,party!$A:$D,4,0),"")="","",IFERROR(VLOOKUP($D33,party!$A:$D,4,0),"")) -> The Whig Party was a mid-19th century political party in the United States. Alongside the Democratic Party, it was one of two major parties between the late 1830s and the early 1850s and part of the Second Party System. The Whigs emerged in the 1830s in opposition to President Andrew Jackson, pulling together former members of the National Republican Party, the Anti-Masonic Party, and disaffected Democrats. | T33: =IF(H33="", "", VALUE(H33)) -> 0.49 | U33: =_xlfn.CONCAT(TEXT(A33,"#"), IF(AND(A33>=10, A33<=19), "th", IF(MOD(A33,10) = 1, "st", IF(MOD(A33,10) = 2, "nd", IF(MOD(A33,10) = 3, "rd", "th"))))) -> 13th | V33: FALSE | W33: William Henry Harrison and 3 more | X33: =IF(V33, W33, "") | Y33: =IF(NOT(V33), W33, "") -> William Henry Harrison and 3 more | Z33: =_xlfn.CONCAT("https://en.wikipedia.org/wiki/", C33, "_United_States_presidential_election") -> https://en.wikipedia.org/wiki/1836_United_States_presidential_election
A34: 14 | B34: =VLOOKUP(D34,party!A:E,5,0) -> 26 | C34: 1840 | D34: Democratic | G34: 1128854 | H34: 0.468 | I34: 60 | P34: =TEXT(H34,"0.0%") -> 46.8% | Q34: =IF(IFERROR(VLOOKUP($D34,party!$A:$D,2,0),"")="","",IFERROR(VLOOKUP($D34,party!$A:$D,2,0),"")) | R34: =IF(IFERROR(VLOOKUP($D34,party!$A:$D,3,0),"")="","",IFERROR(VLOOKUP($D34,party!$A:$D,3,0),"")) -> https://en.wikipedia.org/wiki/Democratic_Party_(United_States) | S34: =IF(IFERROR(VLOOKUP($D34,party!$A:$D,4,0),"")="","",IFERROR(VLOOKUP($D34,party!$A:$D,4,0),"")) -> The Democratic Party is one of the two major contemporary political parties in the United States. Since the late 1850s, its main political rival has been the Republican Party; the two parties have since dominated American politics. The Democratic Party was founded in 1828. The Democratic Party is the world's oldest active political party. It initially supported expansive presidential power, the interests of slave states, agrarianism, and geographical expansionism, while opposing a national bank and high tariffs. It split in 1860 over slavery and won the presidency only twice between 1860 and 1912, although it won the popular vote two more times in that period. | T34: =IF(H34="", "", VALUE(H34)) -> 0.468 | U34: =_xlfn.CONCAT(TEXT(A34,"#"), IF(AND(A34>=10, A34<=19), "th", IF(MOD(A34,10) = 1, "st", IF(MOD(A34,10) = 2, "nd", IF(MOD(A34,10) = 3, "rd", "th"))))) -> 14th | V34: FALSE | W34: Martin Van Buren | X34: =IF(V34, W34, "") | Y34: =IF(NOT(V34), W34, "") -> Martin Van Buren | Z34: =_xlfn.CONCAT("https://en.wikipedia.org/wiki/", C34, "_United_States_presidential_election") -> https://en.wikipedia.org/wiki/1840_United_States_presidential_election
A35: 14 | B35: =VLOOKUP(D35,party!A:E,5,0) -> 15 | C35: 1840 | D35: Whig | E35: William Henry Harrison | G35: 1275390 | H35: 0.529 | I35: 234 | P35: =TEXT(H35,"0.0%") -> 52.9% | Q35: =IF(IFERROR(VLOOKUP($D35,party!$A:$D,2,0),"")="","",IFERROR(VLOOKUP($D35,party!$A:$D,2,0),"")) | R35: =IF(IFERROR(VLOOKUP($D35,party!$A:$D,3,0),"")="","",IFERROR(VLOOKUP($D35,party!$A:$D,3,0),"")) -> https://en.wikipedia.org/wiki/Whig_Party_(United_States) | S35: =IF(IFERROR(VLOOKUP($D35,party!$A:$D,4,0),"")="","",IFERROR(VLOOKUP($D35,party!$A:$D,4,0),"")) -> The Whig Party was a mid-19th century political party in the United States. Alongside the Democratic Party, it was one of two major parties between the late 1830s and the early 1850s and part of the Second Party System. The Whigs emerged in the 1830s in opposition to President Andrew Jackson, pulling together former members of the National Republican Party, the Anti-Masonic Party, and disaffected Democrats. | T35: =IF(H35="", "", VALUE(H35)) -> 0.529 | U35: =_xlfn.CONCAT(TEXT(A35,"#"), IF(AND(A35>=10, A35<=19), "th", IF(MOD(A35,10) = 1, "st", IF(MOD(A35,10) = 2, "nd", IF(MOD(A35,10) = 3, "rd", "th"))))) -> 14th | V35: TRUE | X35: =IF(V35, W35, "") | Y35: =IF(NOT(V35), W35, "") | Z35: =_xlfn.CONCAT("https://en.wikipedia.org/wiki/", C35, "_United_States_presidential_election") -> https://en.wikipedia.org/wiki/1840_United_States_presidential_election
A36: 15 | B36: =VLOOKUP(D36,party!A:E,5,0) -> 26 | C36: 1844 | D36: Democratic | E36: James K. Polk | G36: 1339494 | H36: 0.495 | I36: 170 | P36: =TEXT(H36,"0.0%") -> 49.5% | Q36: =IF(IFERROR(VLOOKUP($D36,party!$A:$D,2,0),"")="","",IFERROR(VLOOKUP($D36,party!$A:$D,2,0),"")) | R36: =IF(IFERROR(VLOOKUP($D36,party!$A:$D,3,0),"")="","",IFERROR(VLOOKUP($D36,party!$A:$D,3,0),"")) -> https://en.wikipedia.org/wiki/Democratic_Party_(United_States) | S36: =IF(IFERROR(VLOOKUP($D36,party!$A:$D,4,0),"")="","",IFERROR(VLOOKUP($D36,party!$A:$D,4,0),"")) -> The Democratic Party is one of the two major contemporary political parties in the United States. Since the late 1850s, its main political rival has been the Republican Party; the two parties have since dominated American politics. The Democratic Party was founded in 1828. The Democratic Party is the world's oldest active political party. It initially supported expansive presidential power, the interests of slave states, agrarianism, and geographical expansionism, while opposing a national bank and high tariffs. It split in 1860 over slavery and won the presidency only twice between 1860 and 1912, although it won the popular vote two more times in that period. | T36: =IF(H36="", "", VALUE(H36)) -> 0.495 | U36: =_xlfn.CONCAT(TEXT(A36,"#"), IF(AND(A36>=10, A36<=19), "th", IF(MOD(A36,10) = 1, "st", IF(MOD(A36,10) = 2, "nd", IF(MOD(A36,10) = 3, "rd", "th"))))) -> 15th | V36: TRUE | X36: =IF(V36, W36, "") | Y36: =IF(NOT(V36), W36, "") | Z36: =_xlfn.CONCAT("https://en.wikipedia.org/wiki/", C36, "_United_States_presidential_election") -> https://en.wikipedia.org/wiki/1844_United_States_presidential_election
A37: 15 | B37: =VLOOKUP(D37,party!A:E,5,0) -> 15 | C37: 1844 | D37: Whig | G37: 1300004 | H37: 0.481 | I37: 105 | P37: =TEXT(H37,"0.0%") -> 48.1% | Q37: =IF(IFERROR(VLOOKUP($D37,party!$A:$D,2,0),"")="","",IFERROR(VLOOKUP($D37,party!$A:$D,2,0),"")) | R37: =IF(IFERROR(VLOOKUP($D37,party!$A:$D,3,0),"")="","",IFERROR(VLOOKUP($D37,party!$A:$D,3,0),"")) -> https://en.wikipedia.org/wiki/Whig_Party_(United_States) | S37: =IF(IFERROR(VLOOKUP($D37,party!$A:$D,4,0),"")="","",IFERROR(VLOOKUP($D37,party!$A:$D,4,0),"")) -> The Whig Party was a mid-19th century political party in the United States. Alongside the Democratic Party, it was one of two major parties between the late 1830s and the early 1850s and part of the Second Party System. The Whigs emerged in the 1830s in opposition to President Andrew Jackson, pulling together former members of the National Republican Party, the Anti-Masonic Party, and disaffected Democrats. | T37: =IF(H37="", "", VALUE(H37)) -> 0.481 | U37: =_xlfn.CONCAT(TEXT(A37,"#"), IF(AND(A37>=10, A37<=19), "th", IF(MOD(A37,10) = 1, "st", IF(MOD(A37,10) = 2, "nd", IF(MOD(A37,10) = 3, "rd", "th"))))) -> 15th | V37: FALSE | W37: Henry Clay | X37: =IF(V37, W37, "") | Y37: =IF(NOT(V37), W37, "") -> Henry Clay | Z37: =_xlfn.CONCAT("https://en.wikipedia.org/wiki/", C37, "_United_States_presidential_election") -> https://en.wikipedia.org/wiki/1844_United_States_presidential_election
A38: 16 | B38: =VLOOKUP(D38,party!A:E,5,0) -> 26 | C38: 1848 | D38: Democratic | G38: 1223460 | H38: 0.425 | I38: 127 | P38: =TEXT(H38,"0.0%") -> 42.5% | Q38: =IF(IFERROR(VLOOKUP($D38,party!$A:$D,2,0),"")="","",IFERROR(VLOOKUP($D38,party!$A:$D,2,0),"")) | R38: =IF(IFERROR(VLOOKUP($D38,party!$A:$D,3,0),"")="","",IFERROR(VLOOKUP($D38,party!$A:$D,3,0),"")) -> https://en.wikipedia.org/wiki/Democratic_Party_(United_States) | S38: =IF(IFERROR(VLOOKUP($D38,party!$A:$D,4,0),"")="","",IFERROR(VLOOKUP($D38,party!$A:$D,4,0),"")) -> The Democratic Party is one of the two major contemporary political parties in the United States. Since the late 1850s, its main political rival has been the Republican Party; the two parties have since dominated American politics. The Democratic Party was founded in 1828. The Democratic Party is the world's oldest active political party. It initially supported expansive presidential power, the interests of slave states, agrarianism, and geographical expansionism, while opposing a national bank and high tariffs. It split in 1860 over slavery and won the presidency only twice between 1860 and 1912, although it won the popular vote two more times in that period. | T38: =IF(H38="", "", VALUE(H38)) -> 0.425 | U38: =_xlfn.CONCAT(TEXT(A38,"#"), IF(AND(A38>=10, A38<=19), "th", IF(MOD(A38,10) = 1, "st", IF(MOD(A38,10) = 2, "nd", IF(MOD(A38,10) = 3, "rd", "th"))))) -> 16th | V38: FALSE | W38: Lewis Cass | X38: =IF(V38, W38, "") | Y38: =IF(NOT(V38), W38, "") -> Lewis Cass | Z38: =_xlfn.CONCAT("https://en.wikipedia.org/wiki/", C38, "_United_States_presidential_election") -> https://en.wikipedia.org/wiki/1848_United_States_presidential_election
A39: 16 | B39: =VLOOKUP(D39,party!A:E,5,0) -> 15 | C39: 1848 | D39: Whig | E39: Zachary Taylor | G39: 1361393 | H39: 0.473 | I39: 163 | P39: =TEXT(H39,"0.0%") -> 47.3% | Q39: =IF(IFERROR(VLOOKUP($D39,party!$A:$D,2,0),"")="","",IFERROR(VLOOKUP($D39,party!$A:$D,2,0),"")) | R39: =IF(IFERROR(VLOOKUP($D39,party!$A:$D,3,0),"")="","",IFERROR(VLOOKUP($D39,party!$A:$D,3,0),"")) -> https://en.wikipedia.org/wiki/Whig_Party_(United_States) | S39: =IF(IFERROR(VLOOKUP($D39,party!$A:$D,4,0),"")="","",IFERROR(VLOOKUP($D39,party!$A:$D,4,0),"")) -> The Whig Party was a mid-19th century political party in the United States. Alongside the Democratic Party, it was one of two major parties between the late 1830s and the early 1850s and part of the Second Party System. The Whigs emerged in the 1830s in opposition to President Andrew Jackson, pulling together former members of the National Republican Party, the Anti-Masonic Party, and disaffected Democrats. | T39: =IF(H39="", "", VALUE(H39)) -> 0.473 | U39: =_xlfn.CONCAT(TEXT(A39,"#"), IF(AND(A39>=10, A39<=19), "th", IF(MOD(A39,10) = 1, "st", IF(MOD(A39,10) = 2, "nd", IF(MOD(A39,10) = 3, "rd", "th"))))) -> 16th | V39: TRUE | X39: =IF(V39, W39, "") | Y39: =IF(NOT(V39), W39, "") | Z39: =_xlfn.CONCAT("https://en.wikipedia.org/wiki/", C39, "_United_States_presidential_election") -> https://en.wikipedia.org/wiki/1848_United_States_presidential_election
A40: 16 | B40: =VLOOKUP(D40,party!A:E,5,0) -> 16 | C40: 1848 | D40: Free Soil | G40: 291501 | H40: 0.101 | I40: 0 | P40: =TEXT(H40,"0.0%") -> 10.1% | Q40: =IF(IFERROR(VLOOKUP($D40,party!$A:$D,2,0),"")="","",IFERROR(VLOOKUP($D40,party!$A:$D,2,0),"")) | R40: =IF(IFERROR(VLOOKUP($D40,party!$A:$D,3,0),"")="","",IFERROR(VLOOKUP($D40,party!$A:$D,3,0),"")) -> https://en.wikipedia.org/wiki/Free_Soil_Party | S40: =IF(IFERROR(VLOOKUP($D40,party!$A:$D,4,0),"")="","",IFERROR(VLOOKUP($D40,party!$A:$D,4,0),"")) -> The Free Soil Party was a political party in the United States from 1848 to 1854, when it merged into the Republican Party. The party was focused on opposing the expansion of slavery into the western territories of the United States. | T40: =IF(H40="", "", VALUE(H40)) -> 0.101 | U40: =_xlfn.CONCAT(TEXT(A40,"#"), IF(AND(A40>=10, A40<=19), "th", IF(MOD(A40,10) = 1, "st", IF(MOD(A40,10) = 2, "nd", IF(MOD(A40,10) = 3, "rd", "th"))))) -> 16th | V40: FALSE | W40: Martin Van Buren | X40: =IF(V40, W40, "") | Y40: =IF(NOT(V40), W40, "") -> Martin Van Buren | Z40: =_xlfn.CONCAT("https://en.wikipedia.org/wiki/", C40, "_United_States_presidential_election") -> https://en.wikipedia.org/wiki/1848_United_States_presidential_election
A41: 17 | B41: =VLOOKUP(D41,party!A:E,5,0) -> 26 | C41: 1852 | D41: Democratic | E41: Franklin Pierce | G41: 1607510 | H41: 0.508 | I41: 254 | P41: =TEXT(H41,"0.0%") -> 50.8% | Q41: =IF(IFERROR(VLOOKUP($D41,party!$A:$D,2,0),"")="","",IFERROR(VLOOKUP($D41,party!$A:$D,2,0),"")) | R41: =IF(IFERROR(VLOOKUP($D41,party!$A:$D,3,0),"")="","",IFERROR(VLOOKUP($D41,party!$A:$D,3,0),"")) -> https://en.wikipedia.org/wiki/Democratic_Party_(United_States) | S41: =IF(IFERROR(VLOOKUP($D41,party!$A:$D,4,0),"")="","",IFERROR(VLOOKUP($D41,party!$A:$D,4,0),"")) -> The Democratic Party is one of the two major contemporary political parties in the United States. Since the late 1850s, its main political rival has been the Republican Party; the two parties have since dominated American politics. The Democratic Party was founded in 1828. The Democratic Party is the world's oldest active political party. It initially supported expansive presidential power, the interests of slave states, agrarianism, and geographical expansionism, while opposing a national bank and high tariffs. It split in 1860 over slavery and won the presidency only twice between 1860 and 1912, although it won the popular vote two more times in that period. | T41: =IF(H41="", "", VALUE(H41)) -> 0.508 | U41: =_xlfn.CONCAT(TEXT(A41,"#"), IF(AND(A41>=10, A41<=19), "th", IF(MOD(A41,10) = 1, "st", IF(MOD(A41,10) = 2, "nd", IF(MOD(A41,10) = 3, "rd", "th"))))) -> 17th | V41: TRUE | X41: =IF(V41, W41, "") | Y41: =IF(NOT(V41), W41, "") | Z41: =_xlfn.CONCAT("https://en.wikipedia.org/wiki/", C41, "_United_States_presidential_election") -> https://en.wikipedia.org/wiki/1852_United_States_presidential_election
A42: 17 | B42: =VLOOKUP(D42,party!A:E,5,0) -> 15 | C42: 1852 | D42: Whig | G42: 1386942 | H42: 0.439 | I42: 42 | P42: =TEXT(H42,"0.0%") -> 43.9% | Q42: =IF(IFERROR(VLOOKUP($D42,party!$A:$D,2,0),"")="","",IFERROR(VLOOKUP($D42,party!$A:$D,2,0),"")) | R42: =IF(IFERROR(VLOOKUP($D42,party!$A:$D,3,0),"")="","",IFERROR(VLOOKUP($D42,party!$A:$D,3,0),"")) -> https://en.wikipedia.org/wiki/Whig_Party_(United_States) | S42: =IF(IFERROR(VLOOKUP($D42,party!$A:$D,4,0),"")="","",IFERROR(VLOOKUP($D42,party!$A:$D,4,0),"")) -> The Whig Party was a mid-19th century political party in the United States. Alongside the Democratic Party, it was one of two major parties between the late 1830s and the early 1850s and part of the Second Party System. The Whigs emerged in the 1830s in opposition to President Andrew Jackson, pulling together former members of the National Republican Party, the Anti-Masonic Party, and disaffected Democrats. | T42: =IF(H42="", "", VALUE(H42)) -> 0.439 | U42: =_xlfn.CONCAT(TEXT(A42,"#"), IF(AND(A42>=10, A42<=19), "th", IF(MOD(A42,10) = 1, "st", IF(MOD(A42,10) = 2, "nd", IF(MOD(A42,10) = 3, "rd", "th"))))) -> 17th | V42: FALSE | W42: Winfield Scott | X42: =IF(V42, W42, "") | Y42: =IF(NOT(V42), W42, "") -> Winfield Scott | Z42: =_xlfn.CONCAT("https://en.wikipedia.org/wiki/", C42, "_United_States_presidential_election") -> https://en.wikipedia.org/wiki/1852_United_States_presidential_election
A43: 17 | B43: =VLOOKUP(D43,party!A:E,5,0) -> 16 | C43: 1852 | D43: Free Soil | G43: 155210 | H43: 0.049 | I43: 0 | P43: =TEXT(H43,"0.0%") -> 4.9% | Q43: =IF(IFERROR(VLOOKUP($D43,party!$A:$D,2,0),"")="","",IFERROR(VLOOKUP($D43,party!$A:$D,2,0),"")) | R43: =IF(IFERROR(VLOOKUP($D43,party!$A:$D,3,0),"")="","",IFERROR(VLOOKUP($D43,party!$A:$D,3,0),"")) -> https://en.wikipedia.org/wiki/Free_Soil_Party | S43: =IF(IFERROR(VLOOKUP($D43,party!$A:$D,4,0),"")="","",IFERROR(VLOOKUP($D43,party!$A:$D,4,0),"")) -> The Free Soil Party was a political party in the United States from 1848 to 1854, when it merged into the Republican Party. The party was focused on opposing the expansion of slavery into the western territories of the United States. | T43: =IF(H43="", "", VALUE(H43)) -> 0.049 | U43: =_xlfn.CONCAT(TEXT(A43,"#"), IF(AND(A43>=10, A43<=19), "th", IF(MOD(A43,10) = 1, "st", IF(MOD(A43,10) = 2, "nd", IF(MOD(A43,10) = 3, "rd", "th"))))) -> 17th | V43: FALSE | W43: John P. Hale | X43: =IF(V43, W43, "") | Y43: =IF(NOT(V43), W43, "") -> John P. Hale | Z43: =_xlfn.CONCAT("https://en.wikipedia.org/wiki/", C43, "_United_States_presidential_election") -> https://en.wikipedia.org/wiki/1852_United_States_presidential_election
A44: 18 | B44: =VLOOKUP(D44,party!A:E,5,0) -> 26 | C44: 1856 | D44: Democratic | E44: James Buchanan | G44: 1836072 | H44: 0.453 | I44: 174 | P44: =TEXT(H44,"0.0%") -> 45.3% | Q44: =IF(IFERROR(VLOOKUP($D44,party!$A:$D,2,0),"")="","",IFERROR(VLOOKUP($D44,party!$A:$D,2,0),"")) | R44: =IF(IFERROR(VLOOKUP($D44,party!$A:$D,3,0),"")="","",IFERROR(VLOOKUP($D44,party!$A:$D,3,0),"")) -> https://en.wikipedia.org/wiki/Democratic_Party_(United_States) | S44: =IF(IFERROR(VLOOKUP($D44,party!$A:$D,4,0),"")="","",IFERROR(VLOOKUP($D44,party!$A:$D,4,0),"")) -> The Democratic Party is one of the two major contemporary political parties in the United States. Since the late 1850s, its main political rival has been the Republican Party; the two parties have since dominated American politics. The Democratic Party was founded in 1828. The Democratic Party is the world's oldest active political party. It initially supported expansive presidential power, the interests of slave states, agrarianism, and geographical expansionism, while opposing a national bank and high tariffs. It split in 1860 over slavery and won the presidency only twice between 1860 and 1912, although it won the popular vote two more times in that period. | T44: =IF(H44="", "", VALUE(H44)) -> 0.453 | U44: =_xlfn.CONCAT(TEXT(A44,"#"), IF(AND(A44>=10, A44<=19), "th", IF(MOD(A44,10) = 1, "st", IF(MOD(A44,10) = 2, "nd", IF(MOD(A44,10) = 3, "rd", "th"))))) -> 18th | V44: TRUE | X44: =IF(V44, W44, "") | Y44: =IF(NOT(V44), W44, "") | Z44: =_xlfn.CONCAT("https://en.wikipedia.org/wiki/", C44, "_United_States_presidential_election") -> https://en.wikipedia.org/wiki/1856_United_States_presidential_election
A45: 18 | B45: =VLOOKUP(D45,party!A:E,5,0) -> 17 | C45: 1856 | D45: Republican | G45: 1342345 | H45: 0.331 | I45: 114 | P45: =TEXT(H45,"0.0%") -> 33.1% | Q45: =IF(IFERROR(VLOOKUP($D45,party!$A:$D,2,0),"")="","",IFERROR(VLOOKUP($D45,party!$A:$D,2,0),"")) | R45: =IF(IFERROR(VLOOKUP($D45,party!$A:$D,3,0),"")="","",IFERROR(VLOOKUP($D45,party!$A:$D,3,0),"")) -> https://en.wikipedia.org/wiki/Republican_Party_(United_States) | S45: =IF(IFERROR(VLOOKUP($D45,party!$A:$D,4,0),"")="","",IFERROR(VLOOKUP($D45,party!$A:$D,4,0),"")) -> The Republican Party, also known as the GOP (Grand Old Party), is one of the two major contemporary political parties in the United States. It emerged as the main political rival of the then-dominant Democratic Party in the mid-1850s, and the two parties have dominated American politics ever since. The party was founded in 1854 by anti-slavery activists who opposed the Kansas–Nebraska Act, an act which allowed for the potential expansion of chattel slavery into the western territories of Kansas and Nebraska. It supported classical liberalism and economic reform while opposing the expansion of slavery into the free territories. The party initially had a very limited presence in the South, but was successful in the North. | T45: =IF(H45="", "", VALUE(H45)) -> 0.331 | U45: =_xlfn.CONCAT(TEXT(A45,"#"), IF(AND(A45>=10, A45<=19), "th", IF(MOD(A45,10) = 1, "st", IF(MOD(A45,10) = 2, "nd", IF(MOD(A45,10) = 3, "rd", "th"))))) -> 18th | V45: FALSE | W45: John C. Frémont | X45: =IF(V45, W45, "") | Y45: =IF(NOT(V45), W45, "") -> John C. Frémont | Z45: =_xlfn.CONCAT("https://en.wikipedia.org/wiki/", C45, "_United_States_presidential_election") -> https://en.wikipedia.org/wiki/1856_United_States_presidential_election
A46: 18 | B46: =VLOOKUP(D46,party!A:E,5,0) -> 3 | C46: 1856 | D46: American | G46: 873053 | H46: 0.216 | I46: 8 | P46: =TEXT(H46,"0.0%") -> 21.6% | Q46: =IF(IFERROR(VLOOKUP($D46,party!$A:$D,2,0),"")="","",IFERROR(VLOOKUP($D46,party!$A:$D,2,0),"")) | R46: =IF(IFERROR(VLOOKUP($D46,party!$A:$D,3,0),"")="","",IFERROR(VLOOKUP($D46,party!$A:$D,3,0),"")) -> https://en.wikipedia.org/wiki/Know_Nothing | S46: =IF(IFERROR(VLOOKUP($D46,party!$A:$D,4,0),"")="","",IFERROR(VLOOKUP($D46,party!$A:$D,4,0),"")) -> The Know Nothings were a nativist political movement in the United States in the 1850s, officially known as the Native American Party before 1855, and afterwards simply the American Party. Members of the movement were required to say "I know nothing" whenever they were asked about its specifics by outsiders, providing the group with its colloquial name. Supporters of the Know Nothing movement believed that an alleged "Romanist" conspiracy to subvert civil and religious liberty in the United States was being hatched by Catholics. Therefore, they sought to politically organize native-born Protestants in defense of their traditional religious and political values. The Know Nothing movement briefly emerged as a major political party in the form of the American Party. The collapse of the Whig Party after the passage of the Kansas–Nebraska Act left an opening for the emergence of a new major political party in opposition to the Democratic Party. | T46: =IF(H46="", "", VALUE(H46)) -> 0.216 | U46: =_xlfn.CONCAT(TEXT(A46,"#"), IF(AND(A46>=10, A46<=19), "th", IF(MOD(A46,10) = 1, "st", IF(MOD(A46,10) = 2, "nd", IF(MOD(A46,10) = 3, "rd", "th"))))) -> 18th | V46: FALSE | W46: Millard Fillmore | X46: =IF(V46, W46, "") | Y46: =IF(NOT(V46), W46, "") -> Millard Fillmore | Z46: =_xlfn.CONCAT("https://en.wikipedia.org/wiki/", C46, "_United_States_presidential_election") -> https://en.wikipedia.org/wiki/1856_United_States_presidential_election
A47: 19 | B47: =VLOOKUP(D47,party!A:E,5,0) -> 17 | C47: 1860 | D47: Republican | E47: Abraham Lincoln | G47: 1865908 | H47: 0.398 | I47: 180 | P47: =TEXT(H47,"0.0%") -> 39.8% | Q47: =IF(IFERROR(VLOOKUP($D47,party!$A:$D,2,0),"")="","",IFERROR(VLOOKUP($D47,party!$A:$D,2,0),"")) | R47: =IF(IFERROR(VLOOKUP($D47,party!$A:$D,3,0),"")="","",IFERROR(VLOOKUP($D47,party!$A:$D,3,0),"")) -> https://en.wikipedia.org/wiki/Republican_Party_(United_States) | S47: =IF(IFERROR(VLOOKUP($D47,party!$A:$D,4,0),"")="","",IFERROR(VLOOKUP($D47,party!$A:$D,4,0),"")) -> The Republican Party, also known as the GOP (Grand Old Party), is one of the two major contemporary political parties in the United States. It emerged as the main political rival of the then-dominant Democratic Party in the mid-1850s, and the two parties have dominated American politics ever since. The party was founded in 1854 by anti-slavery activists who opposed the Kansas–Nebraska Act, an act which allowed for the potential expansion of chattel slavery into the western territories of Kansas and Nebraska. It supported classical liberalism and economic reform while opposing the expansion of slavery into the free territories. The party initially had a very limited presence in the South, but was successful in the North. | T47: =IF(H47="", "", VALUE(H47)) -> 0.398 | U47: =_xlfn.CONCAT(TEXT(A47,"#"), IF(AND(A47>=10, A47<=19), "th", IF(MOD(A47,10) = 1, "st", IF(MOD(A47,10) = 2, "nd", IF(MOD(A47,10) = 3, "rd", "th"))))) -> 19th | V47: TRUE | X47: =IF(V47, W47, "") | Y47: =IF(NOT(V47), W47, "") | Z47: =_xlfn.CONCAT("https://en.wikipedia.org/wiki/", C47, "_United_States_presidential_election") -> https://en.wikipedia.org/wiki/1860_United_States_presidential_election
A48: 19 | B48: =VLOOKUP(D48,party!A:E,5,0) -> 28 | C48: 1860 | D48: Democratic (Southerrn) | G48: 848019 | H48: 0.181 | I48: 72 | P48: =TEXT(H48,"0.0%") -> 18.1% | Q48: =IF(IFERROR(VLOOKUP($D48,party!$A:$D,2,0),"")="","",IFERROR(VLOOKUP($D48,party!$A:$D,2,0),"")) -> Not a party. | R48: =IF(IFERROR(VLOOKUP($D48,party!$A:$D,3,0),"")="","",IFERROR(VLOOKUP($D48,party!$A:$D,3,0),"")) -> https://en.wikipedia.org/wiki/Southern_Democrats | S48: =IF(IFERROR(VLOOKUP($D48,party!$A:$D,4,0),"")="","",IFERROR(VLOOKUP($D48,party!$A:$D,4,0),"")) -> Southern Democrats are members of the U.S. Democratic Party who reside in the Southern United States. Before the American Civil War, Southern Democrats were mostly whites living in the South who believed in Jacksonian democracy. In the 19th century, they defended slavery in the United States and promoted its expansion into the Western United States against the Free Soil opposition in the Northern United States. The United States presidential election of 1860 formalized the split in the Democratic Party and brought about the American Civil War. After the Reconstruction Era ended in the late 1870s, so-called redeemers were Southern Democrats who controlled all the southern states and disenfranchised African-Americans. | T48: =IF(H48="", "", VALUE(H48)) -> 0.181 | U48: =_xlfn.CONCAT(TEXT(A48,"#"), IF(AND(A48>=10, A48<=19), "th", IF(MOD(A48,10) = 1, "st", IF(MOD(A48,10) = 2, "nd", IF(MOD(A48,10) = 3, "rd", "th"))))) -> 19th | V48: FALSE | W48: John C. Breckinridge | X48: =IF(V48, W48, "") | Y48: =IF(NOT(V48), W48, "") -> John C. Breckinridge | Z48: =_xlfn.CONCAT("https://en.wikipedia.org/wiki/", C48, "_United_States_presidential_election") -> https://en.wikipedia.org/wiki/1860_United_States_presidential_election
A49: 19 | B49: =VLOOKUP(D49,party!A:E,5,0) -> 4 | C49: 1860 | D49: Constitutional Union | G49: 590901 | H49: 0.126 | I49: 39 | P49: =TEXT(H49,"0.0%") -> 12.6% | Q49: =IF(IFERROR(VLOOKUP($D49,party!$A:$D,2,0),"")="","",IFERROR(VLOOKUP($D49,party!$A:$D,2,0),"")) | R49: =IF(IFERROR(VLOOKUP($D49,party!$A:$D,3,0),"")="","",IFERROR(VLOOKUP($D49,party!$A:$D,3,0),"")) -> https://en.wikipedia.org/wiki/Constitutional_Union_Party_(United_States) | S49: =IF(IFERROR(VLOOKUP($D49,party!$A:$D,4,0),"")="","",IFERROR(VLOOKUP($D49,party!$A:$D,4,0),"")) -> The Constitutional Union Party was a political party which stood in the 1860 United States elections. It mostly consisted of conservative former Whigs from the Southern United States who wanted to avoid secession over slavery and refused to join either the Republican Party or Democratic Party. | T49: =IF(H49="", "", VALUE(H49)) -> 0.126 | U49: =_xlfn.CONCAT(TEXT(A49,"#"), IF(AND(A49>=10, A49<=19), "th", IF(MOD(A49,10) = 1, "st", IF(MOD(A49,10) = 2, "nd", IF(MOD(A49,10) = 3, "rd", "th"))))) -> 19th | V49: FALSE | W49: John Bell | X49: =IF(V49, W49, "") | Y49: =IF(NOT(V49), W49, "") -> John Bell | Z49: =_xlfn.CONCAT("https://en.wikipedia.org/wiki/", C49, "_United_States_presidential_election") -> https://en.wikipedia.org/wiki/1860_United_States_presidential_election
A50: 19 | B50: =VLOOKUP(D50,party!A:E,5,0) -> 27 | C50: 1860 | D50: Democratic (Northern) | G50: 1380202 | H50: 0.295 | I50: 12 | P50: =TEXT(H50,"0.0%") -> 29.5% | Q50: =IF(IFERROR(VLOOKUP($D50,party!$A:$D,2,0),"")="","",IFERROR(VLOOKUP($D50,party!$A:$D,2,0),"")) -> Not a party. | R50: =IF(IFERROR(VLOOKUP($D50,party!$A:$D,3,0),"")="","",IFERROR(VLOOKUP($D50,party!$A:$D,3,0),"")) -> https://en.wikipedia.org/wiki/Northern_Democratic_Party | S50: =IF(IFERROR(VLOOKUP($D50,party!$A:$D,4,0),"")="","",IFERROR(VLOOKUP($D50,party!$A:$D,4,0),"")) -> The Northern Democratic Party was a leg of the Democratic Party during the 1860 presidential election, when the party split in two factions because of disagreements over slavery. They held two conventions before the election, in Charleston and Baltimore, where they established their platform. Democratic Candidate Stephen A. Douglas was the nominee and lost to Republican Candidate Abraham Lincoln, whose victory prompted the secession of 11 Southern states and the formation of the Confederate States of America. | T50: =IF(H50="", "", VALUE(H50)) -> 0.295 | U50: =_xlfn.CONCAT(TEXT(A50,"#"), IF(AND(A50>=10, A50<=19), "th", IF(MOD(A50,10) = 1, "st", IF(MOD(A50,10) = 2, "nd", IF(MOD(A50,10) = 3, "rd", "th"))))) -> 19th | V50: FALSE | W50: Stephen A. Douglas | X50: =IF(V50, W50, "") | Y50: =IF(NOT(V50), W50, "") -> Stephen A. Douglas | Z50: =_xlfn.CONCAT("https://en.wikipedia.org/wiki/", C50, "_United_States_presidential_election") -> https://en.wikipedia.org/wiki/1860_United_States_presidential_election
A51: 20 | B51: =VLOOKUP(D51,party!A:E,5,0) -> 26 | C51: 1864 | D51: Democratic | G51: 1812807 | H51: 0.45 | I51: 21 | P51: =TEXT(H51,"0.0%") -> 45.0% | Q51: =IF(IFERROR(VLOOKUP($D51,party!$A:$D,2,0),"")="","",IFERROR(VLOOKUP($D51,party!$A:$D,2,0),"")) | R51: =IF(IFERROR(VLOOKUP($D51,party!$A:$D,3,0),"")="","",IFERROR(VLOOKUP($D51,party!$A:$D,3,0),"")) -> https://en.wikipedia.org/wiki/Democratic_Party_(United_States) | S51: =IF(IFERROR(VLOOKUP($D51,party!$A:$D,4,0),"")="","",IFERROR(VLOOKUP($D51,party!$A:$D,4,0),"")) -> The Democratic Party is one of the two major contemporary political parties in the United States. Since the late 1850s, its main political rival has been the Republican Party; the two parties have since dominated American politics. The Democratic Party was founded in 1828. The Democratic Party is the world's oldest active political party. It initially supported expansive presidential power, the interests of slave states, agrarianism, and geographical expansionism, while opposing a national bank and high tariffs. It split in 1860 over slavery and won the presidency only twice between 1860 and 1912, although it won the popular vote two more times in that period. | T51: =IF(H51="", "", VALUE(H51)) -> 0.45 | U51: =_xlfn.CONCAT(TEXT(A51,"#"), IF(AND(A51>=10, A51<=19), "th", IF(MOD(A51,10) = 1, "st", IF(MOD(A51,10) = 2, "nd", IF(MOD(A51,10) = 3, "rd", "th"))))) -> 20th | V51: FALSE | W51: George B. McClellan | X51: =IF(V51, W51, "") | Y51: =IF(NOT(V51), W51, "") -> George B. McClellan | Z51: =_xlfn.CONCAT("https://en.wikipedia.org/wiki/", C51, "_United_States_presidential_election") -> https://en.wikipedia.org/wiki/1864_United_States_presidential_election
A52: 20 | B52: =VLOOKUP(D52,party!A:E,5,0) -> 18 | C52: 1864 | D52: National Union | E52: Abraham Lincoln | G52: 2218388 | H52: 0.55 | I52: 212 | P52: =TEXT(H52,"0.0%") -> 55.0% | Q52: =IF(IFERROR(VLOOKUP($D52,party!$A:$D,2,0),"")="","",IFERROR(VLOOKUP($D52,party!$A:$D,2,0),"")) | R52: =IF(IFERROR(VLOOKUP($D52,party!$A:$D,3,0),"")="","",IFERROR(VLOOKUP($D52,party!$A:$D,3,0),"")) -> https://en.wikipedia.org/wiki/National_Union_Party_(United_States) | S52: =IF(IFERROR(VLOOKUP($D52,party!$A:$D,4,0),"")="","",IFERROR(VLOOKUP($D52,party!$A:$D,4,0),"")) -> The National Union Party, commonly the Union Party or Unionists, was a wartime coalition of Republicans, War Democrats, and border state Unconditional Unionists that supported the Lincoln Administration during the American Civil War. It held the 1864 National Union Convention that nominated Abraham Lincoln for president and Andrew Johnson for vice president in the 1864 United States presidential election. | T52: =IF(H52="", "", VALUE(H52)) -> 0.55 | U52: =_xlfn.CONCAT(TEXT(A52,"#"), IF(AND(A52>=10, A52<=19), "th", IF(MOD(A52,10) = 1, "st", IF(MOD(A52,10) = 2, "nd", IF(MOD(A52,10) = 3, "rd", "th"))))) -> 20th | V52: TRUE | X52: =IF(V52, W52, "") | Y52: =IF(NOT(V52), W52, "") | Z52: =_xlfn.CONCAT("https://en.wikipedia.org/wiki/", C52, "_United_States_presidential_election") -> https://en.wikipedia.org/wiki/1864_United_States_presidential_election | AA52: Johnson, a Democrat, was nominated on the National Union ticket along with Lincoln, a Republican.
A53: 21 | B53: =VLOOKUP(D53,party!A:E,5,0) -> 26 | C53: 1868 | D53: Democratic | G53: 2708744 | H53: 0.473 | I53: 80 | P53: =TEXT(H53,"0.0%") -> 47.3% | Q53: =IF(IFERROR(VLOOKUP($D53,party!$A:$D,2,0),"")="","",IFERROR(VLOOKUP($D53,party!$A:$D,2,0),"")) | R53: =IF(IFERROR(VLOOKUP($D53,party!$A:$D,3,0),"")="","",IFERROR(VLOOKUP($D53,party!$A:$D,3,0),"")) -> https://en.wikipedia.org/wiki/Democratic_Party_(United_States) | S53: =IF(IFERROR(VLOOKUP($D53,party!$A:$D,4,0),"")="","",IFERROR(VLOOKUP($D53,party!$A:$D,4,0),"")) -> The Democratic Party is one of the two major contemporary political parties in the United States. Since the late 1850s, its main political rival has been the Republican Party; the two parties have since dominated American politics. The Democratic Party was founded in 1828. The Democratic Party is the world's oldest active political party. It initially supported expansive presidential power, the interests of slave states, agrarianism, and geographical expansionism, while opposing a national bank and high tariffs. It split in 1860 over slavery and won the presidency only twice between 1860 and 1912, although it won the popular vote two more times in that period. | T53: =IF(H53="", "", VALUE(H53)) -> 0.473 | U53: =_xlfn.CONCAT(TEXT(A53,"#"), IF(AND(A53>=10, A53<=19), "th", IF(MOD(A53,10) = 1, "st", IF(MOD(A53,10) = 2, "nd", IF(MOD(A53,10) = 3, "rd", "th"))))) -> 21st | V53: FALSE | W53: Horatio Seymour | X53: =IF(V53, W53, "") | Y53: =IF(NOT(V53), W53, "") -> Horatio Seymour | Z53: =_xlfn.CONCAT("https://en.wikipedia.org/wiki/", C53, "_United_States_presidential_election") -> https://en.wikipedia.org/wiki/1868_United_States_presidential_election
A54: 21 | B54: =VLOOKUP(D54,party!A:E,5,0) -> 17 | C54: 1868 | D54: Republican | E54: Ulysses S. Grant | G54: 3013650 | H54: 0.527 | I54: 214 | P54: =TEXT(H54,"0.0%") -> 52.7% | Q54: =IF(IFERROR(VLOOKUP($D54,party!$A:$D,2,0),"")="","",IFERROR(VLOOKUP($D54,party!$A:$D,2,0),"")) | R54: =IF(IFERROR(VLOOKUP($D54,party!$A:$D,3,0),"")="","",IFERROR(VLOOKUP($D54,party!$A:$D,3,0),"")) -> https://en.wikipedia.org/wiki/Republican_Party_(United_States) | S54: =IF(IFERROR(VLOOKUP($D54,party!$A:$D,4,0),"")="","",IFERROR(VLOOKUP($D54,party!$A:$D,4,0),"")) -> The Republican Party, also known as the GOP (Grand Old Party), is one of the two major contemporary political parties in the United States. It emerged as the main political rival of the then-dominant Democratic Party in the mid-1850s, and the two parties have dominated American politics ever since. The party was founded in 1854 by anti-slavery activists who opposed the Kansas–Nebraska Act, an act which allowed for the potential expansion of chattel slavery into the western territories of Kansas and Nebraska. It supported classical liberalism and economic reform while opposing the expansion of slavery into the free territories. The party initially had a very limited presence in the South, but was successful in the North. | T54: =IF(H54="", "", VALUE(H54)) -> 0.527 | U54: =_xlfn.CONCAT(TEXT(A54,"#"), IF(AND(A54>=10, A54<=19), "th", IF(MOD(A54,10) = 1, "st", IF(MOD(A54,10) = 2, "nd", IF(MOD(A54,10) = 3, "rd", "th"))))) -> 21st | V54: TRUE | X54: =IF(V54, W54, "") | Y54: =IF(NOT(V54), W54, "") | Z54: =_xlfn.CONCAT("https://en.wikipedia.org/wiki/", C54, "_United_States_presidential_election") -> https://en.wikipedia.org/wiki/1868_United_States_presidential_election
A55: 22 | B55: =VLOOKUP(D55,party!A:E,5,0) -> 17 | C55: 1872 | D55: Republican | E55: Ulysses S. Grant | G55: 3598235 | H55: 0.556 | I55: 286 | P55: =TEXT(H55,"0.0%") -> 55.6% | Q55: =IF(IFERROR(VLOOKUP($D55,party!$A:$D,2,0),"")="","",IFERROR(VLOOKUP($D55,party!$A:$D,2,0),"")) | R55: =IF(IFERROR(VLOOKUP($D55,party!$A:$D,3,0),"")="","",IFERROR(VLOOKUP($D55,party!$A:$D,3,0),"")) -> https://en.wikipedia.org/wiki/Republican_Party_(United_States) | S55: =IF(IFERROR(VLOOKUP($D55,party!$A:$D,4,0),"")="","",IFERROR(VLOOKUP($D55,party!$A:$D,4,0),"")) -> The Republican Party, also known as the GOP (Grand Old Party), is one of the two major contemporary political parties in the United States. It emerged as the main political rival of the then-dominant Democratic Party in the mid-1850s, and the two parties have dominated American politics ever since. The party was founded in 1854 by anti-slavery activists who opposed the Kansas–Nebraska Act, an act which allowed for the potential expansion of chattel slavery into the western territories of Kansas and Nebraska. It supported classical liberalism and economic reform while opposing the expansion of slavery into the free territories. The party initially had a very limited presence in the South, but was successful in the North. | T55: =IF(H55="", "", VALUE(H55)) -> 0.556 | U55: =_xlfn.CONCAT(TEXT(A55,"#"), IF(AND(A55>=10, A55<=19), "th", IF(MOD(A55,10) = 1, "st", IF(MOD(A55,10) = 2, "nd", IF(MOD(A55,10) = 3, "rd", "th"))))) -> 22nd | V55: TRUE | X55: =IF(V55, W55, "") | Y55: =IF(NOT(V55), W55, "") | Z55: =_xlfn.CONCAT("https://en.wikipedia.org/wiki/", C55, "_United_States_presidential_election") -> https://en.wikipedia.org/wiki/1872_United_States_presidential_election
A56: 22 | B56: =VLOOKUP(D56,party!A:E,5,0) -> 26 | C56: 1872 | D56: Democratic | G56: 2834761 | H56: 0.438 | I56: ? | P56: 43.8% * | Q56: =IF(IFERROR(VLOOKUP($D56,party!$A:$D,2,0),"")="","",IFERROR(VLOOKUP($D56,party!$A:$D,2,0),"")) | R56: =IF(IFERROR(VLOOKUP($D56,party!$A:$D,3,0),"")="","",IFERROR(VLOOKUP($D56,party!$A:$D,3,0),"")) -> https://en.wikipedia.org/wiki/Democratic_Party_(United_States) | S56: =IF(IFERROR(VLOOKUP($D56,party!$A:$D,4,0),"")="","",IFERROR(VLOOKUP($D56,party!$A:$D,4,0),"")) -> The Democratic Party is one of the two major contemporary political parties in the United States. Since the late 1850s, its main political rival has been the Republican Party; the two parties have since dominated American politics. The Democratic Party was founded in 1828. The Democratic Party is the world's oldest active political party. It initially supported expansive presidential power, the interests of slave states, agrarianism, and geographical expansionism, while opposing a national bank and high tariffs. It split in 1860 over slavery and won the presidency only twice between 1860 and 1912, although it won the popular vote two more times in that period. | T56: 0.438 | U56: =_xlfn.CONCAT(TEXT(A56,"#"), IF(AND(A56>=10, A56<=19), "th", IF(MOD(A56,10) = 1, "st", IF(MOD(A56,10) = 2, "nd", IF(MOD(A56,10) = 3, "rd", "th"))))) -> 22nd | V56: FALSE | W56: Thomas A. Hendricks and 1 more | X56: =IF(V56, W56, "") | Y56: =IF(NOT(V56), W56, "") -> Thomas A. Hendricks and 1 more | Z56: =_xlfn.CONCAT("https://en.wikipedia.org/wiki/", C56, "_United_States_presidential_election") -> https://en.wikipedia.org/wiki/1872_United_States_presidential_election | AA56: * All popular votes were originally for Horace Greeley and Benjamin Gratz Brown.
A57: 22 | B57: =VLOOKUP(D57,party!A:E,5,0) -> 19 | C57: 1872 | D57: Liberal Republican | H57: 0.438 | P57: 43.8% * | Q57: =IF(IFERROR(VLOOKUP($D57,party!$A:$D,2,0),"")="","",IFERROR(VLOOKUP($D57,party!$A:$D,2,0),"")) | R57: =IF(IFERROR(VLOOKUP($D57,party!$A:$D,3,0),"")="","",IFERROR(VLOOKUP($D57,party!$A:$D,3,0),"")) -> https://en.wikipedia.org/wiki/Liberal_Republican_Party_(United_States) | S57: =IF(IFERROR(VLOOKUP($D57,party!$A:$D,4,0),"")="","",IFERROR(VLOOKUP($D57,party!$A:$D,4,0),"")) -> The Liberal Republican Party was an American political party that was organized in May 1872 to oppose the reelection of President Ulysses S. Grant and his Radical Republican supporters in the presidential election of 1872. The party opposed Grant's Reconstruction policies, particularly the Enforcement Acts that destroyed the Ku Klux Klan. It lost in a landslide, and disappeared from the national stage after the 1872 election. | T57: 0.438 | U57: =_xlfn.CONCAT(TEXT(A57,"#"), IF(AND(A57>=10, A57<=19), "th", IF(MOD(A57,10) = 1, "st", IF(MOD(A57,10) = 2, "nd", IF(MOD(A57,10) = 3, "rd", "th"))))) -> 22nd | V57: FALSE | W57: Benjamin Gratz Brown and 2 more | X57: =IF(V57, W57, "") | Y57: =IF(NOT(V57), W57, "") -> Benjamin Gratz Brown and 2 more | Z57: =_xlfn.CONCAT("https://en.wikipedia.org/wiki/", C57, "_United_States_presidential_election") -> https://en.wikipedia.org/wiki/1872_United_States_presidential_election | AA57: * All popular votes were originally for Horace Greeley and Benjamin Gratz Brown.
A58: 23 | B58: =VLOOKUP(D58,party!A:E,5,0) -> 26 | C58: 1876 | D58: Democratic | G58: 4286808 | H58: 0.509 | I58: 184 | P58: =TEXT(H58,"0.0%") -> 50.9% | Q58: =IF(IFERROR(VLOOKUP($D58,party!$A:$D,2,0),"")="","",IFERROR(VLOOKUP($D58,party!$A:$D,2,0),"")) | R58: =IF(IFERROR(VLOOKUP($D58,party!$A:$D,3,0),"")="","",IFERROR(VLOOKUP($D58,party!$A:$D,3,0),"")) -> https://en.wikipedia.org/wiki/Democratic_Party_(United_States) | S58: =IF(IFERROR(VLOOKUP($D58,party!$A:$D,4,0),"")="","",IFERROR(VLOOKUP($D58,party!$A:$D,4,0),"")) -> The Democratic Party is one of the two major contemporary political parties in the United States. Since the late 1850s, its main political rival has been the Republican Party; the two parties have since dominated American politics. The Democratic Party was founded in 1828. The Democratic Party is the world's oldest active political party. It initially supported expansive presidential power, the interests of slave states, agrarianism, and geographical expansionism, while opposing a national bank and high tariffs. It split in 1860 over slavery and won the presidency only twice between 1860 and 1912, although it won the popular vote two more times in that period. | T58: =IF(H58="", "", VALUE(H58)) -> 0.509 | U58: =_xlfn.CONCAT(TEXT(A58,"#"), IF(AND(A58>=10, A58<=19), "th", IF(MOD(A58,10) = 1, "st", IF(MOD(A58,10) = 2, "nd", IF(MOD(A58,10) = 3, "rd", "th"))))) -> 23rd | V58: FALSE | W58: Samuel J. Tilden | X58: =IF(V58, W58, "") | Y58: =IF(NOT(V58), W58, "") -> Samuel J. Tilden | Z58: =_xlfn.CONCAT("https://en.wikipedia.org/wiki/", C58, "_United_States_presidential_election") -> https://en.wikipedia.org/wiki/1876_United_States_presidential_election
A59: 23 | B59: =VLOOKUP(D59,party!A:E,5,0) -> 17 | C59: 1876 | D59: Republican | E59: Rutherford B. Hayes | G59: 4034142 | H59: 0.479 | I59: 185 | P59: =TEXT(H59,"0.0%") -> 47.9% | Q59: =IF(IFERROR(VLOOKUP($D59,party!$A:$D,2,0),"")="","",IFERROR(VLOOKUP($D59,party!$A:$D,2,0),"")) | R59: =IF(IFERROR(VLOOKUP($D59,party!$A:$D,3,0),"")="","",IFERROR(VLOOKUP($D59,party!$A:$D,3,0),"")) -> https://en.wikipedia.org/wiki/Republican_Party_(United_States) | S59: =IF(IFERROR(VLOOKUP($D59,party!$A:$D,4,0),"")="","",IFERROR(VLOOKUP($D59,party!$A:$D,4,0),"")) -> The Republican Party, also known as the GOP (Grand Old Party), is one of the two major contemporary political parties in the United States. It emerged as the main political rival of the then-dominant Democratic Party in the mid-1850s, and the two parties have dominated American politics ever since. The party was founded in 1854 by anti-slavery activists who opposed the Kansas–Nebraska Act, an act which allowed for the potential expansion of chattel slavery into the western territories of Kansas and Nebraska. It supported classical liberalism and economic reform while opposing the expansion of slavery into the free territories. The party initially had a very limited presence in the South, but was successful in the North. | T59: =IF(H59="", "", VALUE(H59)) -> 0.479 | U59: =_xlfn.CONCAT(TEXT(A59,"#"), IF(AND(A59>=10, A59<=19), "th", IF(MOD(A59,10) = 1, "st", IF(MOD(A59,10) = 2, "nd", IF(MOD(A59,10) = 3, "rd", "th"))))) -> 23rd | V59: TRUE | X59: =IF(V59, W59, "") | Y59: =IF(NOT(V59), W59, "") | Z59: =_xlfn.CONCAT("https://en.wikipedia.org/wiki/", C59, "_United_States_presidential_election") -> https://en.wikipedia.org/wiki/1876_United_States_presidential_election
A60: 24 | B60: =VLOOKUP(D60,party!A:E,5,0) -> 26 | C60: 1880 | D60: Democratic | G60: 4444260 | H60: 0.483 | I60: 155 | P60: =TEXT(H60,"0.0%") -> 48.3% | Q60: =IF(IFERROR(VLOOKUP($D60,party!$A:$D,2,0),"")="","",IFERROR(VLOOKUP($D60,party!$A:$D,2,0),"")) | R60: =IF(IFERROR(VLOOKUP($D60,party!$A:$D,3,0),"")="","",IFERROR(VLOOKUP($D60,party!$A:$D,3,0),"")) -> https://en.wikipedia.org/wiki/Democratic_Party_(United_States) | S60: =IF(IFERROR(VLOOKUP($D60,party!$A:$D,4,0),"")="","",IFERROR(VLOOKUP($D60,party!$A:$D,4,0),"")) -> The Democratic Party is one of the two major contemporary political parties in the United States. Since the late 1850s, its main political rival has been the Republican Party; the two parties have since dominated American politics. The Democratic Party was founded in 1828. The Democratic Party is the world's oldest active political party. It initially supported expansive presidential power, the interests of slave states, agrarianism, and geographical expansionism, while opposing a national bank and high tariffs. It split in 1860 over slavery and won the presidency only twice between 1860 and 1912, although it won the popular vote two more times in that period. | T60: =IF(H60="", "", VALUE(H60)) -> 0.483 | U60: =_xlfn.CONCAT(TEXT(A60,"#"), IF(AND(A60>=10, A60<=19), "th", IF(MOD(A60,10) = 1, "st", IF(MOD(A60,10) = 2, "nd", IF(MOD(A60,10) = 3, "rd", "th"))))) -> 24th | V60: FALSE | W60: Winfield Scott Hancock | X60: =IF(V60, W60, "") | Y60: =IF(NOT(V60), W60, "") -> Winfield Scott Hancock | Z60: =_xlfn.CONCAT("https://en.wikipedia.org/wiki/", C60, "_United_States_presidential_election") -> https://en.wikipedia.org/wiki/1880_United_States_presidential_election
A61: 24 | B61: =VLOOKUP(D61,party!A:E,5,0) -> 17 | C61: 1880 | D61: Republican | E61: James A. Garfield | G61: 4446158 | H61: 0.483 | I61: 214 | P61: =TEXT(H61,"0.0%") -> 48.3% | Q61: =IF(IFERROR(VLOOKUP($D61,party!$A:$D,2,0),"")="","",IFERROR(VLOOKUP($D61,party!$A:$D,2,0),"")) | R61: =IF(IFERROR(VLOOKUP($D61,party!$A:$D,3,0),"")="","",IFERROR(VLOOKUP($D61,party!$A:$D,3,0),"")) -> https://en.wikipedia.org/wiki/Republican_Party_(United_States) | S61: =IF(IFERROR(VLOOKUP($D61,party!$A:$D,4,0),"")="","",IFERROR(VLOOKUP($D61,party!$A:$D,4,0),"")) -> The Republican Party, also known as the GOP (Grand Old Party), is one of the two major contemporary political parties in the United States. It emerged as the main political rival of the then-dominant Democratic Party in the mid-1850s, and the two parties have dominated American politics ever since. The party was founded in 1854 by anti-slavery activists who opposed the Kansas–Nebraska Act, an act which allowed for the potential expansion of chattel slavery into the western territories of Kansas and Nebraska. It supported classical liberalism and economic reform while opposing the expansion of slavery into the free territories. The party initially had a very limited presence in the South, but was successful in the North. | T61: =IF(H61="", "", VALUE(H61)) -> 0.483 | U61: =_xlfn.CONCAT(TEXT(A61,"#"), IF(AND(A61>=10, A61<=19), "th", IF(MOD(A61,10) = 1, "st", IF(MOD(A61,10) = 2, "nd", IF(MOD(A61,10) = 3, "rd", "th"))))) -> 24th | V61: TRUE | X61: =IF(V61, W61, "") | Y61: =IF(NOT(V61), W61, "") | Z61: =_xlfn.CONCAT("https://en.wikipedia.org/wiki/", C61, "_United_States_presidential_election") -> https://en.wikipedia.org/wiki/1880_United_States_presidential_election
A62: 25 | B62: =VLOOKUP(D62,party!A:E,5,0) -> 26 | C62: 1884 | D62: Democratic | E62: Grover Cleveland | G62: 4914482 | H62: 0.489 | I62: 219 | P62: =TEXT(H62,"0.0%") -> 48.9% | Q62: =IF(IFERROR(VLOOKUP($D62,party!$A:$D,2,0),"")="","",IFERROR(VLOOKUP($D62,party!$A:$D,2,0),"")) | R62: =IF(IFERROR(VLOOKUP($D62,party!$A:$D,3,0),"")="","",IFERROR(VLOOKUP($D62,party!$A:$D,3,0),"")) -> https://en.wikipedia.org/wiki/Democratic_Party_(United_States) | S62: =IF(IFERROR(VLOOKUP($D62,party!$A:$D,4,0),"")="","",IFERROR(VLOOKUP($D62,party!$A:$D,4,0),"")) -> The Democratic Party is one of the two major contemporary political parties in the United States. Since the late 1850s, its main political rival has been the Republican Party; the two parties have since dominated American politics. The Democratic Party was founded in 1828. The Democratic Party is the world's oldest active political party. It initially supported expansive presidential power, the interests of slave states, agrarianism, and geographical expansionism, while opposing a national bank and high tariffs. It split in 1860 over slavery and won the presidency only twice between 1860 and 1912, although it won the popular vote two more times in that period. | T62: =IF(H62="", "", VALUE(H62)) -> 0.489 | U62: =_xlfn.CONCAT(TEXT(A62,"#"), IF(AND(A62>=10, A62<=19), "th", IF(MOD(A62,10) = 1, "st", IF(MOD(A62,10) = 2, "nd", IF(MOD(A62,10) = 3, "rd", "th"))))) -> 25th | V62: TRUE | X62: =IF(V62, W62, "") | Y62: =IF(NOT(V62), W62, "") | Z62: =_xlfn.CONCAT("https://en.wikipedia.org/wiki/", C62, "_United_States_presidential_election") -> https://en.wikipedia.org/wiki/1884_United_States_presidential_election
A63: 25 | B63: =VLOOKUP(D63,party!A:E,5,0) -> 17 | C63: 1884 | D63: Republican | G63: 4856903 | H63: 0.483 | I63: 182 | P63: =TEXT(H63,"0.0%") -> 48.3% | Q63: =IF(IFERROR(VLOOKUP($D63,party!$A:$D,2,0),"")="","",IFERROR(VLOOKUP($D63,party!$A:$D,2,0),"")) | R63: =IF(IFERROR(VLOOKUP($D63,party!$A:$D,3,0),"")="","",IFERROR(VLOOKUP($D63,party!$A:$D,3,0),"")) -> https://en.wikipedia.org/wiki/Republican_Party_(United_States) | S63: =IF(IFERROR(VLOOKUP($D63,party!$A:$D,4,0),"")="","",IFERROR(VLOOKUP($D63,party!$A:$D,4,0),"")) -> The Republican Party, also known as the GOP (Grand Old Party), is one of the two major contemporary political parties in the United States. It emerged as the main political rival of the then-dominant Democratic Party in the mid-1850s, and the two parties have dominated American politics ever since. The party was founded in 1854 by anti-slavery activists who opposed the Kansas–Nebraska Act, an act which allowed for the potential expansion of chattel slavery into the western territories of Kansas and Nebraska. It supported classical liberalism and economic reform while opposing the expansion of slavery into the free territories. The party initially had a very limited presence in the South, but was successful in the North. | T63: =IF(H63="", "", VALUE(H63)) -> 0.483 | U63: =_xlfn.CONCAT(TEXT(A63,"#"), IF(AND(A63>=10, A63<=19), "th", IF(MOD(A63,10) = 1, "st", IF(MOD(A63,10) = 2, "nd", IF(MOD(A63,10) = 3, "rd", "th"))))) -> 25th | V63: FALSE | W63: James G. Blaine | X63: =IF(V63, W63, "") | Y63: =IF(NOT(V63), W63, "") -> James G. Blaine | Z63: =_xlfn.CONCAT("https://en.wikipedia.org/wiki/", C63, "_United_States_presidential_election") -> https://en.wikipedia.org/wiki/1884_United_States_presidential_election
A64: 26 | B64: =VLOOKUP(D64,party!A:E,5,0) -> 26 | C64: 1888 | D64: Democratic | G64: 5534488 | H64: 0.486 | I64: 168 | P64: =TEXT(H64,"0.0%") -> 48.6% | Q64: =IF(IFERROR(VLOOKUP($D64,party!$A:$D,2,0),"")="","",IFERROR(VLOOKUP($D64,party!$A:$D,2,0),"")) | R64: =IF(IFERROR(VLOOKUP($D64,party!$A:$D,3,0),"")="","",IFERROR(VLOOKUP($D64,party!$A:$D,3,0),"")) -> https://en.wikipedia.org/wiki/Democratic_Party_(United_States) | S64: =IF(IFERROR(VLOOKUP($D64,party!$A:$D,4,0),"")="","",IFERROR(VLOOKUP($D64,party!$A:$D,4,0),"")) -> The Democratic Party is one of the two major contemporary political parties in the United States. Since the late 1850s, its main political rival has been the Republican Party; the two parties have since dominated American politics. The Democratic Party was founded in 1828. The Democratic Party is the world's oldest active political party. It initially supported expansive presidential power, the interests of slave states, agrarianism, and geographical expansionism, while opposing a national bank and high tariffs. It split in 1860 over slavery and won the presidency only twice between 1860 and 1912, although it won the popular vote two more times in that period. | T64: =IF(H64="", "", VALUE(H64)) -> 0.486 | U64: =_xlfn.CONCAT(TEXT(A64,"#"), IF(AND(A64>=10, A64<=19), "th", IF(MOD(A64,10) = 1, "st", IF(MOD(A64,10) = 2, "nd", IF(MOD(A64,10) = 3, "rd", "th"))))) -> 26th | V64: FALSE | W64: Grover Cleveland | X64: =IF(V64, W64, "") | Y64: =IF(NOT(V64), W64, "") -> Grover Cleveland | Z64: =_xlfn.CONCAT("https://en.wikipedia.org/wiki/", C64, "_United_States_presidential_election") -> https://en.wikipedia.org/wiki/1888_United_States_presidential_election
A65: 26 | B65: =VLOOKUP(D65,party!A:E,5,0) -> 17 | C65: 1888 | D65: Republican | E65: Benjamin Harrison | G65: 5443892 | H65: 0.478 | I65: 233 | P65: =TEXT(H65,"0.0%") -> 47.8% | Q65: =IF(IFERROR(VLOOKUP($D65,party!$A:$D,2,0),"")="","",IFERROR(VLOOKUP($D65,party!$A:$D,2,0),"")) | R65: =IF(IFERROR(VLOOKUP($D65,party!$A:$D,3,0),"")="","",IFERROR(VLOOKUP($D65,party!$A:$D,3,0),"")) -> https://en.wikipedia.org/wiki/Republican_Party_(United_States) | S65: =IF(IFERROR(VLOOKUP($D65,party!$A:$D,4,0),"")="","",IFERROR(VLOOKUP($D65,party!$A:$D,4,0),"")) -> The Republican Party, also known as the GOP (Grand Old Party), is one of the two major contemporary political parties in the United States. It emerged as the main political rival of the then-dominant Democratic Party in the mid-1850s, and the two parties have dominated American politics ever since. The party was founded in 1854 by anti-slavery activists who opposed the Kansas–Nebraska Act, an act which allowed for the potential expansion of chattel slavery into the western territories of Kansas and Nebraska. It supported classical liberalism and economic reform while opposing the expansion of slavery into the free territories. The party initially had a very limited presence in the South, but was successful in the North. | T65: =IF(H65="", "", VALUE(H65)) -> 0.478 | U65: =_xlfn.CONCAT(TEXT(A65,"#"), IF(AND(A65>=10, A65<=19), "th", IF(MOD(A65,10) = 1, "st", IF(MOD(A65,10) = 2, "nd", IF(MOD(A65,10) = 3, "rd", "th"))))) -> 26th | V65: TRUE | X65: =IF(V65, W65, "") | Y65: =IF(NOT(V65), W65, "") | Z65: =_xlfn.CONCAT("https://en.wikipedia.org/wiki/", C65, "_United_States_presidential_election") -> https://en.wikipedia.org/wiki/1888_United_States_presidential_election
A66: 27 | B66: =VLOOKUP(D66,party!A:E,5,0) -> 26 | C66: 1892 | D66: Democratic | E66: Grover Cleveland | G66: 5553898 | H66: 0.46 | I66: 277 | P66: =TEXT(H66,"0.0%") -> 46.0% | Q66: =IF(IFERROR(VLOOKUP($D66,party!$A:$D,2,0),"")="","",IFERROR(VLOOKUP($D66,party!$A:$D,2,0),"")) | R66: =IF(IFERROR(VLOOKUP($D66,party!$A:$D,3,0),"")="","",IFERROR(VLOOKUP($D66,party!$A:$D,3,0),"")) -> https://en.wikipedia.org/wiki/Democratic_Party_(United_States) | S66: =IF(IFERROR(VLOOKUP($D66,party!$A:$D,4,0),"")="","",IFERROR(VLOOKUP($D66,party!$A:$D,4,0),"")) -> The Democratic Party is one of the two major contemporary political parties in the United States. Since the late 1850s, its main political rival has been the Republican Party; the two parties have since dominated American politics. The Democratic Party was founded in 1828. The Democratic Party is the world's oldest active political party. It initially supported expansive presidential power, the interests of slave states, agrarianism, and geographical expansionism, while opposing a national bank and high tariffs. It split in 1860 over slavery and won the presidency only twice between 1860 and 1912, although it won the popular vote two more times in that period. | T66: =IF(H66="", "", VALUE(H66)) -> 0.46 | U66: =_xlfn.CONCAT(TEXT(A66,"#"), IF(AND(A66>=10, A66<=19), "th", IF(MOD(A66,10) = 1, "st", IF(MOD(A66,10) = 2, "nd", IF(MOD(A66,10) = 3, "rd", "th"))))) -> 27th | V66: TRUE | X66: =IF(V66, W66, "") | Y66: =IF(NOT(V66), W66, "") | Z66: =_xlfn.CONCAT("https://en.wikipedia.org/wiki/", C66, "_United_States_presidential_election") -> https://en.wikipedia.org/wiki/1892_United_States_presidential_election
A67: 27 | B67: =VLOOKUP(D67,party!A:E,5,0) -> 17 | C67: 1892 | D67: Republican | G67: 5190819 | H67: 0.43 | I67: 145 | P67: =TEXT(H67,"0.0%") -> 43.0% | Q67: =IF(IFERROR(VLOOKUP($D67,party!$A:$D,2,0),"")="","",IFERROR(VLOOKUP($D67,party!$A:$D,2,0),"")) | R67: =IF(IFERROR(VLOOKUP($D67,party!$A:$D,3,0),"")="","",IFERROR(VLOOKUP($D67,party!$A:$D,3,0),"")) -> https://en.wikipedia.org/wiki/Republican_Party_(United_States) | S67: =IF(IFERROR(VLOOKUP($D67,party!$A:$D,4,0),"")="","",IFERROR(VLOOKUP($D67,party!$A:$D,4,0),"")) -> The Republican Party, also known as the GOP (Grand Old Party), is one of the two major contemporary political parties in the United States. It emerged as the main political rival of the then-dominant Democratic Party in the mid-1850s, and the two parties have dominated American politics ever since. The party was founded in 1854 by anti-slavery activists who opposed the Kansas–Nebraska Act, an act which allowed for the potential expansion of chattel slavery into the western territories of Kansas and Nebraska. It supported classical liberalism and economic reform while opposing the expansion of slavery into the free territories. The party initially had a very limited presence in the South, but was successful in the North. | T67: =IF(H67="", "", VALUE(H67)) -> 0.43 | U67: =_xlfn.CONCAT(TEXT(A67,"#"), IF(AND(A67>=10, A67<=19), "th", IF(MOD(A67,10) = 1, "st", IF(MOD(A67,10) = 2, "nd", IF(MOD(A67,10) = 3, "rd", "th"))))) -> 27th | V67: FALSE | W67: Benjamin Harrison | X67: =IF(V67, W67, "") | Y67: =IF(NOT(V67), W67, "") -> Benjamin Harrison | Z67: =_xlfn.CONCAT("https://en.wikipedia.org/wiki/", C67, "_United_States_presidential_election") -> https://en.wikipedia.org/wiki/1892_United_States_presidential_election
A68: 27 | B68: =VLOOKUP(D68,party!A:E,5,0) -> 29 | C68: 1892 | D68: Populist | G68: 1026595 | H68: 0.085 | I68: 22 | P68: =TEXT(H68,"0.0%") -> 8.5% | Q68: =IF(IFERROR(VLOOKUP($D68,party!$A:$D,2,0),"")="","",IFERROR(VLOOKUP($D68,party!$A:$D,2,0),"")) | R68: =IF(IFERROR(VLOOKUP($D68,party!$A:$D,3,0),"")="","",IFERROR(VLOOKUP($D68,party!$A:$D,3,0),"")) -> https://en.wikipedia.org/wiki/People%27s_Party_(United_States) | S68: =IF(IFERROR(VLOOKUP($D68,party!$A:$D,4,0),"")="","",IFERROR(VLOOKUP($D68,party!$A:$D,4,0),"")) -> The People's Party, also known as the Populist Party or simply the Populists, was an agrarian populist political party in the United States in the late 19th century. The Populist Party emerged in the early 1890s as an important force in the Southern and Western United States, but declined rapidly after the 1896 United States presidential election in which most of its natural constituency was absorbed by the Bryan wing of the Democratic Party. | T68: =IF(H68="", "", VALUE(H68)) -> 0.085 | U68: =_xlfn.CONCAT(TEXT(A68,"#"), IF(AND(A68>=10, A68<=19), "th", IF(MOD(A68,10) = 1, "st", IF(MOD(A68,10) = 2, "nd", IF(MOD(A68,10) = 3, "rd", "th"))))) -> 27th | V68: FALSE | W68: James B. Weaver | X68: =IF(V68, W68, "") | Y68: =IF(NOT(V68), W68, "") -> James B. Weaver | Z68: =_xlfn.CONCAT("https://en.wikipedia.org/wiki/", C68, "_United_States_presidential_election") -> https://en.wikipedia.org/wiki/1892_United_States_presidential_election
A69: 28 | B69: =VLOOKUP(D69,party!A:E,5,0) -> 17 | C69: 1896 | D69: Republican | E69: William McKinley | G69: 7111607 | H69: 0.51 | I69: 271 | P69: =TEXT(H69,"0.0%") -> 51.0% | Q69: =IF(IFERROR(VLOOKUP($D69,party!$A:$D,2,0),"")="","",IFERROR(VLOOKUP($D69,party!$A:$D,2,0),"")) | R69: =IF(IFERROR(VLOOKUP($D69,party!$A:$D,3,0),"")="","",IFERROR(VLOOKUP($D69,party!$A:$D,3,0),"")) -> https://en.wikipedia.org/wiki/Republican_Party_(United_States) | S69: =IF(IFERROR(VLOOKUP($D69,party!$A:$D,4,0),"")="","",IFERROR(VLOOKUP($D69,party!$A:$D,4,0),"")) -> The Republican Party, also known as the GOP (Grand Old Party), is one of the two major contemporary political parties in the United States. It emerged as the main political rival of the then-dominant Democratic Party in the mid-1850s, and the two parties have dominated American politics ever since. The party was founded in 1854 by anti-slavery activists who opposed the Kansas–Nebraska Act, an act which allowed for the potential expansion of chattel slavery into the western territories of Kansas and Nebraska. It supported classical liberalism and economic reform while opposing the expansion of slavery into the free territories. The party initially had a very limited presence in the South, but was successful in the North. | T69: =IF(H69="", "", VALUE(H69)) -> 0.51 | U69: =_xlfn.CONCAT(TEXT(A69,"#"), IF(AND(A69>=10, A69<=19), "th", IF(MOD(A69,10) = 1, "st", IF(MOD(A69,10) = 2, "nd", IF(MOD(A69,10) = 3, "rd", "th"))))) -> 28th | V69: TRUE | X69: =IF(V69, W69, "") | Y69: =IF(NOT(V69), W69, "") | Z69: =_xlfn.CONCAT("https://en.wikipedia.org/wiki/", C69, "_United_States_presidential_election") -> https://en.wikipedia.org/wiki/1896_United_States_presidential_election
A70: 28 | B70: =VLOOKUP(D70,party!A:E,5,0) -> 30 | C70: 1896 | D70: Democratic/Populist | G70: 6509052 | H70: 0.467 | I70: 176 | P70: =TEXT(H70,"0.0%") -> 46.7% | Q70: =IF(IFERROR(VLOOKUP($D70,party!$A:$D,2,0),"")="","",IFERROR(VLOOKUP($D70,party!$A:$D,2,0),"")) -> Not a party. | R70: =IF(IFERROR(VLOOKUP($D70,party!$A:$D,3,0),"")="","",IFERROR(VLOOKUP($D70,party!$A:$D,3,0),"")) -> https://en.wikipedia.org/wiki/1896_United_States_presidential_election | S70: =IF(IFERROR(VLOOKUP($D70,party!$A:$D,4,0),"")="","",IFERROR(VLOOKUP($D70,party!$A:$D,4,0),"")) -> The 1896 Democratic National Convention repudiated the Cleveland administration and nominated Bryan on the fifth presidential ballot. Bryan then won the nomination of the Populist Party, which had won several states in 1892 and shared many of Bryan's policies. While the Democrats and Populists both nominated Bryan, the two parties had different vice presidential running mates. | T70: =IF(H70="", "", VALUE(H70)) -> 0.467 | U70: =_xlfn.CONCAT(TEXT(A70,"#"), IF(AND(A70>=10, A70<=19), "th", IF(MOD(A70,10) = 1, "st", IF(MOD(A70,10) = 2, "nd", IF(MOD(A70,10) = 3, "rd", "th"))))) -> 28th | V70: FALSE | W70: William Jennings Bryan | X70: =IF(V70, W70, "") | Y70: =IF(NOT(V70), W70, "") -> William Jennings Bryan | Z70: =_xlfn.CONCAT("https://en.wikipedia.org/wiki/", C70, "_United_States_presidential_election") -> https://en.wikipedia.org/wiki/1896_United_States_presidential_election
A71: 29 | B71: =VLOOKUP(D71,party!A:E,5,0) -> 26 | C71: 1900 | D71: Democratic | G71: 7228864 | H71: 0.516 | I71: 292 | P71: =TEXT(H71,"0.0%") -> 51.6% | Q71: =IF(IFERROR(VLOOKUP($D71,party!$A:$D,2,0),"")="","",IFERROR(VLOOKUP($D71,party!$A:$D,2,0),"")) | R71: =IF(IFERROR(VLOOKUP($D71,party!$A:$D,3,0),"")="","",IFERROR(VLOOKUP($D71,party!$A:$D,3,0),"")) -> https://en.wikipedia.org/wiki/Democratic_Party_(United_States) | S71: =IF(IFERROR(VLOOKUP($D71,party!$A:$D,4,0),"")="","",IFERROR(VLOOKUP($D71,party!$A:$D,4,0),"")) -> The Democratic Party is one of the two major contemporary political parties in the United States. Since the late 1850s, its main political rival has been the Republican Party; the two parties have since dominated American politics. The Democratic Party was founded in 1828. The Democratic Party is the world's oldest active political party. It initially supported expansive presidential power, the interests of slave states, agrarianism, and geographical expansionism, while opposing a national bank and high tariffs. It split in 1860 over slavery and won the presidency only twice between 1860 and 1912, although it won the popular vote two more times in that period. | T71: =IF(H71="", "", VALUE(H71)) -> 0.516 | U71: =_xlfn.CONCAT(TEXT(A71,"#"), IF(AND(A71>=10, A71<=19), "th", IF(MOD(A71,10) = 1, "st", IF(MOD(A71,10) = 2, "nd", IF(MOD(A71,10) = 3, "rd", "th"))))) -> 29th | V71: FALSE | W71: William Jennings Bryan | X71: =IF(V71, W71, "") | Y71: =IF(NOT(V71), W71, "") -> William Jennings Bryan | Z71: =_xlfn.CONCAT("https://en.wikipedia.org/wiki/", C71, "_United_States_presidential_election") -> https://en.wikipedia.org/wiki/1900_United_States_presidential_election
A72: 29 | B72: =VLOOKUP(D72,party!A:E,5,0) -> 17 | C72: 1900 | D72: Republican | E72: William McKinley | G72: 6370932 | H72: 0.455 | I72: 155 | P72: =TEXT(H72,"0.0%") -> 45.5% | Q72: =IF(IFERROR(VLOOKUP($D72,party!$A:$D,2,0),"")="","",IFERROR(VLOOKUP($D72,party!$A:$D,2,0),"")) | R72: =IF(IFERROR(VLOOKUP($D72,party!$A:$D,3,0),"")="","",IFERROR(VLOOKUP($D72,party!$A:$D,3,0),"")) -> https://en.wikipedia.org/wiki/Republican_Party_(United_States) | S72: =IF(IFERROR(VLOOKUP($D72,party!$A:$D,4,0),"")="","",IFERROR(VLOOKUP($D72,party!$A:$D,4,0),"")) -> The Republican Party, also known as the GOP (Grand Old Party), is one of the two major contemporary political parties in the United States. It emerged as the main political rival of the then-dominant Democratic Party in the mid-1850s, and the two parties have dominated American politics ever since. The party was founded in 1854 by anti-slavery activists who opposed the Kansas–Nebraska Act, an act which allowed for the potential expansion of chattel slavery into the western territories of Kansas and Nebraska. It supported classical liberalism and economic reform while opposing the expansion of slavery into the free territories. The party initially had a very limited presence in the South, but was successful in the North. | T72: =IF(H72="", "", VALUE(H72)) -> 0.455 | U72: =_xlfn.CONCAT(TEXT(A72,"#"), IF(AND(A72>=10, A72<=19), "th", IF(MOD(A72,10) = 1, "st", IF(MOD(A72,10) = 2, "nd", IF(MOD(A72,10) = 3, "rd", "th"))))) -> 29th | V72: TRUE | X72: =IF(V72, W72, "") | Y72: =IF(NOT(V72), W72, "") | Z72: =_xlfn.CONCAT("https://en.wikipedia.org/wiki/", C72, "_United_States_presidential_election") -> https://en.wikipedia.org/wiki/1900_United_States_presidential_election
A73: 30 | B73: =VLOOKUP(D73,party!A:E,5,0) -> 26 | C73: 1904 | D73: Democratic | G73: 5083880 | H73: 0.376 | I73: 140 | P73: =TEXT(H73,"0.0%") -> 37.6% | Q73: =IF(IFERROR(VLOOKUP($D73,party!$A:$D,2,0),"")="","",IFERROR(VLOOKUP($D73,party!$A:$D,2,0),"")) | R73: =IF(IFERROR(VLOOKUP($D73,party!$A:$D,3,0),"")="","",IFERROR(VLOOKUP($D73,party!$A:$D,3,0),"")) -> https://en.wikipedia.org/wiki/Democratic_Party_(United_States) | S73: =IF(IFERROR(VLOOKUP($D73,party!$A:$D,4,0),"")="","",IFERROR(VLOOKUP($D73,party!$A:$D,4,0),"")) -> The Democratic Party is one of the two major contemporary political parties in the United States. Since the late 1850s, its main political rival has been the Republican Party; the two parties have since dominated American politics. The Democratic Party was founded in 1828. The Democratic Party is the world's oldest active political party. It initially supported expansive presidential power, the interests of slave states, agrarianism, and geographical expansionism, while opposing a national bank and high tariffs. It split in 1860 over slavery and won the presidency only twice between 1860 and 1912, although it won the popular vote two more times in that period. | T73: =IF(H73="", "", VALUE(H73)) -> 0.376 | U73: =_xlfn.CONCAT(TEXT(A73,"#"), IF(AND(A73>=10, A73<=19), "th", IF(MOD(A73,10) = 1, "st", IF(MOD(A73,10) = 2, "nd", IF(MOD(A73,10) = 3, "rd", "th"))))) -> 30th | V73: FALSE | W73: Alton B. Parker | X73: =IF(V73, W73, "") | Y73: =IF(NOT(V73), W73, "") -> Alton B. Parker | Z73: =_xlfn.CONCAT("https://en.wikipedia.org/wiki/", C73, "_United_States_presidential_election") -> https://en.wikipedia.org/wiki/1904_United_States_presidential_election
A74: 30 | B74: =VLOOKUP(D74,party!A:E,5,0) -> 17 | C74: 1904 | D74: Republican | E74: Theodore Roosevelt | G74: 7630457 | H74: 0.564 | I74: 336 | P74: =TEXT(H74,"0.0%") -> 56.4% | Q74: =IF(IFERROR(VLOOKUP($D74,party!$A:$D,2,0),"")="","",IFERROR(VLOOKUP($D74,party!$A:$D,2,0),"")) | R74: =IF(IFERROR(VLOOKUP($D74,party!$A:$D,3,0),"")="","",IFERROR(VLOOKUP($D74,party!$A:$D,3,0),"")) -> https://en.wikipedia.org/wiki/Republican_Party_(United_States) | S74: =IF(IFERROR(VLOOKUP($D74,party!$A:$D,4,0),"")="","",IFERROR(VLOOKUP($D74,party!$A:$D,4,0),"")) -> The Republican Party, also known as the GOP (Grand Old Party), is one of the two major contemporary political parties in the United States. It emerged as the main political rival of the then-dominant Democratic Party in the mid-1850s, and the two parties have dominated American politics ever since. The party was founded in 1854 by anti-slavery activists who opposed the Kansas–Nebraska Act, an act which allowed for the potential expansion of chattel slavery into the western territories of Kansas and Nebraska. It supported classical liberalism and economic reform while opposing the expansion of slavery into the free territories. The party initially had a very limited presence in the South, but was successful in the North. | T74: =IF(H74="", "", VALUE(H74)) -> 0.564 | U74: =_xlfn.CONCAT(TEXT(A74,"#"), IF(AND(A74>=10, A74<=19), "th", IF(MOD(A74,10) = 1, "st", IF(MOD(A74,10) = 2, "nd", IF(MOD(A74,10) = 3, "rd", "th"))))) -> 30th | V74: TRUE | X74: =IF(V74, W74, "") | Y74: =IF(NOT(V74), W74, "") | Z74: =_xlfn.CONCAT("https://en.wikipedia.org/wiki/", C74, "_United_States_presidential_election") -> https://en.wikipedia.org/wiki/1904_United_States_presidential_election
A75: 31 | B75: =VLOOKUP(D75,party!A:E,5,0) -> 26 | C75: 1908 | D75: Democratic | G75: 6408979 | H75: 0.43 | I75: 162 | P75: =TEXT(H75,"0.0%") -> 43.0% | Q75: =IF(IFERROR(VLOOKUP($D75,party!$A:$D,2,0),"")="","",IFERROR(VLOOKUP($D75,party!$A:$D,2,0),"")) | R75: =IF(IFERROR(VLOOKUP($D75,party!$A:$D,3,0),"")="","",IFERROR(VLOOKUP($D75,party!$A:$D,3,0),"")) -> https://en.wikipedia.org/wiki/Democratic_Party_(United_States) | S75: =IF(IFERROR(VLOOKUP($D75,party!$A:$D,4,0),"")="","",IFERROR(VLOOKUP($D75,party!$A:$D,4,0),"")) -> The Democratic Party is one of the two major contemporary political parties in the United States. Since the late 1850s, its main political rival has been the Republican Party; the two parties have since dominated American politics. The Democratic Party was founded in 1828. The Democratic Party is the world's oldest active political party. It initially supported expansive presidential power, the interests of slave states, agrarianism, and geographical expansionism, while opposing a national bank and high tariffs. It split in 1860 over slavery and won the presidency only twice between 1860 and 1912, although it won the popular vote two more times in that period. | T75: =IF(H75="", "", VALUE(H75)) -> 0.43 | U75: =_xlfn.CONCAT(TEXT(A75,"#"), IF(AND(A75>=10, A75<=19), "th", IF(MOD(A75,10) = 1, "st", IF(MOD(A75,10) = 2, "nd", IF(MOD(A75,10) = 3, "rd", "th"))))) -> 31st | V75: FALSE | W75: William Jennings Bryan | X75: =IF(V75, W75, "") | Y75: =IF(NOT(V75), W75, "") -> William Jennings Bryan | Z75: =_xlfn.CONCAT("https://en.wikipedia.org/wiki/", C75, "_United_States_presidential_election") -> https://en.wikipedia.org/wiki/1908_United_States_presidential_election
A76: 31 | B76: =VLOOKUP(D76,party!A:E,5,0) -> 17 | C76: 1908 | D76: Republican | E76: William Howard Taft | G76: 7678335 | H76: 0.516 | I76: 321 | P76: =TEXT(H76,"0.0%") -> 51.6% | Q76: =IF(IFERROR(VLOOKUP($D76,party!$A:$D,2,0),"")="","",IFERROR(VLOOKUP($D76,party!$A:$D,2,0),"")) | R76: =IF(IFERROR(VLOOKUP($D76,party!$A:$D,3,0),"")="","",IFERROR(VLOOKUP($D76,party!$A:$D,3,0),"")) -> https://en.wikipedia.org/wiki/Republican_Party_(United_States) | S76: =IF(IFERROR(VLOOKUP($D76,party!$A:$D,4,0),"")="","",IFERROR(VLOOKUP($D76,party!$A:$D,4,0),"")) -> The Republican Party, also known as the GOP (Grand Old Party), is one of the two major contemporary political parties in the United States. It emerged as the main political rival of the then-dominant Democratic Party in the mid-1850s, and the two parties have dominated American politics ever since. The party was founded in 1854 by anti-slavery activists who opposed the Kansas–Nebraska Act, an act which allowed for the potential expansion of chattel slavery into the western territories of Kansas and Nebraska. It supported classical liberalism and economic reform while opposing the expansion of slavery into the free territories. The party initially had a very limited presence in the South, but was successful in the North. | T76: =IF(H76="", "", VALUE(H76)) -> 0.516 | U76: =_xlfn.CONCAT(TEXT(A76,"#"), IF(AND(A76>=10, A76<=19), "th", IF(MOD(A76,10) = 1, "st", IF(MOD(A76,10) = 2, "nd", IF(MOD(A76,10) = 3, "rd", "th"))))) -> 31st | V76: TRUE | X76: =IF(V76, W76, "") | Y76: =IF(NOT(V76), W76, "") | Z76: =_xlfn.CONCAT("https://en.wikipedia.org/wiki/", C76, "_United_States_presidential_election") -> https://en.wikipedia.org/wiki/1908_United_States_presidential_election
A77: 32 | B77: =VLOOKUP(D77,party!A:E,5,0) -> 26 | C77: 1912 | D77: Democratic | E77: Woodrow Wilson | G77: 6296284 | H77: 0.418 | I77: 435 | P77: =TEXT(H77,"0.0%") -> 41.8% | Q77: =IF(IFERROR(VLOOKUP($D77,party!$A:$D,2,0),"")="","",IFERROR(VLOOKUP($D77,party!$A:$D,2,0),"")) | R77: =IF(IFERROR(VLOOKUP($D77,party!$A:$D,3,0),"")="","",IFERROR(VLOOKUP($D77,party!$A:$D,3,0),"")) -> https://en.wikipedia.org/wiki/Democratic_Party_(United_States) | S77: =IF(IFERROR(VLOOKUP($D77,party!$A:$D,4,0),"")="","",IFERROR(VLOOKUP($D77,party!$A:$D,4,0),"")) -> The Democratic Party is one of the two major contemporary political parties in the United States. Since the late 1850s, its main political rival has been the Republican Party; the two parties have since dominated American politics. The Democratic Party was founded in 1828. The Democratic Party is the world's oldest active political party. It initially supported expansive presidential power, the interests of slave states, agrarianism, and geographical expansionism, while opposing a national bank and high tariffs. It split in 1860 over slavery and won the presidency only twice between 1860 and 1912, although it won the popular vote two more times in that period. | T77: =IF(H77="", "", VALUE(H77)) -> 0.418 | U77: =_xlfn.CONCAT(TEXT(A77,"#"), IF(AND(A77>=10, A77<=19), "th", IF(MOD(A77,10) = 1, "st", IF(MOD(A77,10) = 2, "nd", IF(MOD(A77,10) = 3, "rd", "th"))))) -> 32nd | V77: TRUE | X77: =IF(V77, W77, "") | Y77: =IF(NOT(V77), W77, "") | Z77: =_xlfn.CONCAT("https://en.wikipedia.org/wiki/", C77, "_United_States_presidential_election") -> https://en.wikipedia.org/wiki/1912_United_States_presidential_election
A78: 32 | B78: =VLOOKUP(D78,party!A:E,5,0) -> 17 | C78: 1912 | D78: Republican | G78: 3486242 | H78: 0.232 | I78: 8 | P78: =TEXT(H78,"0.0%") -> 23.2% | Q78: =IF(IFERROR(VLOOKUP($D78,party!$A:$D,2,0),"")="","",IFERROR(VLOOKUP($D78,party!$A:$D,2,0),"")) | R78: =IF(IFERROR(VLOOKUP($D78,party!$A:$D,3,0),"")="","",IFERROR(VLOOKUP($D78,party!$A:$D,3,0),"")) -> https://en.wikipedia.org/wiki/Republican_Party_(United_States) | S78: =IF(IFERROR(VLOOKUP($D78,party!$A:$D,4,0),"")="","",IFERROR(VLOOKUP($D78,party!$A:$D,4,0),"")) -> The Republican Party, also known as the GOP (Grand Old Party), is one of the two major contemporary political parties in the United States. It emerged as the main political rival of the then-dominant Democratic Party in the mid-1850s, and the two parties have dominated American politics ever since. The party was founded in 1854 by anti-slavery activists who opposed the Kansas–Nebraska Act, an act which allowed for the potential expansion of chattel slavery into the western territories of Kansas and Nebraska. It supported classical liberalism and economic reform while opposing the expansion of slavery into the free territories. The party initially had a very limited presence in the South, but was successful in the North. | T78: =IF(H78="", "", VALUE(H78)) -> 0.232 | U78: =_xlfn.CONCAT(TEXT(A78,"#"), IF(AND(A78>=10, A78<=19), "th", IF(MOD(A78,10) = 1, "st", IF(MOD(A78,10) = 2, "nd", IF(MOD(A78,10) = 3, "rd", "th"))))) -> 32nd | V78: FALSE | W78: William Howard Taft | X78: =IF(V78, W78, "") | Y78: =IF(NOT(V78), W78, "") -> William Howard Taft | Z78: =_xlfn.CONCAT("https://en.wikipedia.org/wiki/", C78, "_United_States_presidential_election") -> https://en.wikipedia.org/wiki/1912_United_States_presidential_election
A79: 32 | B79: =VLOOKUP(D79,party!A:E,5,0) -> 20 | C79: 1912 | D79: Progressive (Bull Moose) | G79: 4122721 | H79: 0.274 | I79: 88 | P79: =TEXT(H79,"0.0%") -> 27.4% | Q79: =IF(IFERROR(VLOOKUP($D79,party!$A:$D,2,0),"")="","",IFERROR(VLOOKUP($D79,party!$A:$D,2,0),"")) | R79: =IF(IFERROR(VLOOKUP($D79,party!$A:$D,3,0),"")="","",IFERROR(VLOOKUP($D79,party!$A:$D,3,0),"")) -> https://en.wikipedia.org/wiki/Bull_Moose_Party | S79: =IF(IFERROR(VLOOKUP($D79,party!$A:$D,4,0),"")="","",IFERROR(VLOOKUP($D79,party!$A:$D,4,0),"")) -> The Progressive Party, popularly nicknamed the Bull Moose Party, was a third party in the United States formed in 1912 by former president Theodore Roosevelt after he lost the presidential nomination of the Republican Party to his former protégé turned rival, incumbent president William Howard Taft. The new party was known for taking advanced positions on progressive reforms and attracting leading national reformers. The party was also ideologically deeply connected with America's radical-liberal tradition. After the party's defeat in the 1912 United States presidential election, it went into rapid decline in elections until 1918, disappearing by 1920. The "Bull Moose" nickname originated when Roosevelt boasted that he felt "strong as a bull moose" after losing the Republican nomination in June 1912 at the Chicago convention. | T79: =IF(H79="", "", VALUE(H79)) -> 0.274 | U79: =_xlfn.CONCAT(TEXT(A79,"#"), IF(AND(A79>=10, A79<=19), "th", IF(MOD(A79,10) = 1, "st", IF(MOD(A79,10) = 2, "nd", IF(MOD(A79,10) = 3, "rd", "th"))))) -> 32nd | V79: FALSE | W79: Theodore Roosevelt | X79: =IF(V79, W79, "") | Y79: =IF(NOT(V79), W79, "") -> Theodore Roosevelt | Z79: =_xlfn.CONCAT("https://en.wikipedia.org/wiki/", C79, "_United_States_presidential_election") -> https://en.wikipedia.org/wiki/1912_United_States_presidential_election
A80: 32 | B80: =VLOOKUP(D80,party!A:E,5,0) -> 5 | C80: 1912 | D80: Socialist | G80: 901551 | H80: 0.06 | I80: 0 | P80: =TEXT(H80,"0.0%") -> 6.0% | Q80: =IF(IFERROR(VLOOKUP($D80,party!$A:$D,2,0),"")="","",IFERROR(VLOOKUP($D80,party!$A:$D,2,0),"")) | R80: =IF(IFERROR(VLOOKUP($D80,party!$A:$D,3,0),"")="","",IFERROR(VLOOKUP($D80,party!$A:$D,3,0),"")) -> https://en.wikipedia.org/wiki/Socialist_Party_of_America | S80: =IF(IFERROR(VLOOKUP($D80,party!$A:$D,4,0),"")="","",IFERROR(VLOOKUP($D80,party!$A:$D,4,0),"")) -> The Socialist Party of America (SPA) was a socialist political party in the United States formed in 1901 by a merger between the three-year-old Social Democratic Party of America and disaffected elements of the Socialist Labor Party of America who had split from the main organization in 1899. | T80: =IF(H80="", "", VALUE(H80)) -> 0.06 | U80: =_xlfn.CONCAT(TEXT(A80,"#"), IF(AND(A80>=10, A80<=19), "th", IF(MOD(A80,10) = 1, "st", IF(MOD(A80,10) = 2, "nd", IF(MOD(A80,10) = 3, "rd", "th"))))) -> 32nd | V80: FALSE | W80: Eugene V. Debs | X80: =IF(V80, W80, "") | Y80: =IF(NOT(V80), W80, "") -> Eugene V. Debs | Z80: =_xlfn.CONCAT("https://en.wikipedia.org/wiki/", C80, "_United_States_presidential_election") -> https://en.wikipedia.org/wiki/1912_United_States_presidential_election
A81: 33 | B81: =VLOOKUP(D81,party!A:E,5,0) -> 26 | C81: 1916 | D81: Democratic | E81: Woodrow Wilson | G81: 9126868 | H81: 0.492 | I81: 277 | P81: =TEXT(H81,"0.0%") -> 49.2% | Q81: =IF(IFERROR(VLOOKUP($D81,party!$A:$D,2,0),"")="","",IFERROR(VLOOKUP($D81,party!$A:$D,2,0),"")) | R81: =IF(IFERROR(VLOOKUP($D81,party!$A:$D,3,0),"")="","",IFERROR(VLOOKUP($D81,party!$A:$D,3,0),"")) -> https://en.wikipedia.org/wiki/Democratic_Party_(United_States) | S81: =IF(IFERROR(VLOOKUP($D81,party!$A:$D,4,0),"")="","",IFERROR(VLOOKUP($D81,party!$A:$D,4,0),"")) -> The Democratic Party is one of the two major contemporary political parties in the United States. Since the late 1850s, its main political rival has been the Republican Party; the two parties have since dominated American politics. The Democratic Party was founded in 1828. The Democratic Party is the world's oldest active political party. It initially supported expansive presidential power, the interests of slave states, agrarianism, and geographical expansionism, while opposing a national bank and high tariffs. It split in 1860 over slavery and won the presidency only twice between 1860 and 1912, although it won the popular vote two more times in that period. | T81: =IF(H81="", "", VALUE(H81)) -> 0.492 | U81: =_xlfn.CONCAT(TEXT(A81,"#"), IF(AND(A81>=10, A81<=19), "th", IF(MOD(A81,10) = 1, "st", IF(MOD(A81,10) = 2, "nd", IF(MOD(A81,10) = 3, "rd", "th"))))) -> 33rd | V81: TRUE | X81: =IF(V81, W81, "") | Y81: =IF(NOT(V81), W81, "") | Z81: =_xlfn.CONCAT("https://en.wikipedia.org/wiki/", C81, "_United_States_presidential_election") -> https://en.wikipedia.org/wiki/1916_United_States_presidential_election
A82: 33 | B82: =VLOOKUP(D82,party!A:E,5,0) -> 17 | C82: 1916 | D82: Republican | G82: 8548728 | H82: 0.461 | I82: 254 | P82: =TEXT(H82,"0.0%") -> 46.1% | Q82: =IF(IFERROR(VLOOKUP($D82,party!$A:$D,2,0),"")="","",IFERROR(VLOOKUP($D82,party!$A:$D,2,0),"")) | R82: =IF(IFERROR(VLOOKUP($D82,party!$A:$D,3,0),"")="","",IFERROR(VLOOKUP($D82,party!$A:$D,3,0),"")) -> https://en.wikipedia.org/wiki/Republican_Party_(United_States) | S82: =IF(IFERROR(VLOOKUP($D82,party!$A:$D,4,0),"")="","",IFERROR(VLOOKUP($D82,party!$A:$D,4,0),"")) -> The Republican Party, also known as the GOP (Grand Old Party), is one of the two major contemporary political parties in the United States. It emerged as the main political rival of the then-dominant Democratic Party in the mid-1850s, and the two parties have dominated American politics ever since. The party was founded in 1854 by anti-slavery activists who opposed the Kansas–Nebraska Act, an act which allowed for the potential expansion of chattel slavery into the western territories of Kansas and Nebraska. It supported classical liberalism and economic reform while opposing the expansion of slavery into the free territories. The party initially had a very limited presence in the South, but was successful in the North. | T82: =IF(H82="", "", VALUE(H82)) -> 0.461 | U82: =_xlfn.CONCAT(TEXT(A82,"#"), IF(AND(A82>=10, A82<=19), "th", IF(MOD(A82,10) = 1, "st", IF(MOD(A82,10) = 2, "nd", IF(MOD(A82,10) = 3, "rd", "th"))))) -> 33rd | V82: FALSE | W82: Charles Evans Hughes | X82: =IF(V82, W82, "") | Y82: =IF(NOT(V82), W82, "") -> Charles Evans Hughes | Z82: =_xlfn.CONCAT("https://en.wikipedia.org/wiki/", C82, "_United_States_presidential_election") -> https://en.wikipedia.org/wiki/1916_United_States_presidential_election
A83: 34 | B83: =VLOOKUP(D83,party!A:E,5,0) -> 26 | C83: 1920 | D83: Democratic | G83: 9139661 | H83: 0.342 | I83: 127 | P83: =TEXT(H83,"0.0%") -> 34.2% | Q83: =IF(IFERROR(VLOOKUP($D83,party!$A:$D,2,0),"")="","",IFERROR(VLOOKUP($D83,party!$A:$D,2,0),"")) | R83: =IF(IFERROR(VLOOKUP($D83,party!$A:$D,3,0),"")="","",IFERROR(VLOOKUP($D83,party!$A:$D,3,0),"")) -> https://en.wikipedia.org/wiki/Democratic_Party_(United_States) | S83: =IF(IFERROR(VLOOKUP($D83,party!$A:$D,4,0),"")="","",IFERROR(VLOOKUP($D83,party!$A:$D,4,0),"")) -> The Democratic Party is one of the two major contemporary political parties in the United States. Since the late 1850s, its main political rival has been the Republican Party; the two parties have since dominated American politics. The Democratic Party was founded in 1828. The Democratic Party is the world's oldest active political party. It initially supported expansive presidential power, the interests of slave states, agrarianism, and geographical expansionism, while opposing a national bank and high tariffs. It split in 1860 over slavery and won the presidency only twice between 1860 and 1912, although it won the popular vote two more times in that period. | T83: =IF(H83="", "", VALUE(H83)) -> 0.342 | U83: =_xlfn.CONCAT(TEXT(A83,"#"), IF(AND(A83>=10, A83<=19), "th", IF(MOD(A83,10) = 1, "st", IF(MOD(A83,10) = 2, "nd", IF(MOD(A83,10) = 3, "rd", "th"))))) -> 34th | V83: FALSE | W83: James M. Cox | X83: =IF(V83, W83, "") | Y83: =IF(NOT(V83), W83, "") -> James M. Cox | Z83: =_xlfn.CONCAT("https://en.wikipedia.org/wiki/", C83, "_United_States_presidential_election") -> https://en.wikipedia.org/wiki/1920_United_States_presidential_election
A84: 34 | B84: =VLOOKUP(D84,party!A:E,5,0) -> 17 | C84: 1920 | D84: Republican | E84: Warren G. Harding | G84: 16144093 | H84: 0.603 | I84: 404 | P84: =TEXT(H84,"0.0%") -> 60.3% | Q84: =IF(IFERROR(VLOOKUP($D84,party!$A:$D,2,0),"")="","",IFERROR(VLOOKUP($D84,party!$A:$D,2,0),"")) | R84: =IF(IFERROR(VLOOKUP($D84,party!$A:$D,3,0),"")="","",IFERROR(VLOOKUP($D84,party!$A:$D,3,0),"")) -> https://en.wikipedia.org/wiki/Republican_Party_(United_States) | S84: =IF(IFERROR(VLOOKUP($D84,party!$A:$D,4,0),"")="","",IFERROR(VLOOKUP($D84,party!$A:$D,4,0),"")) -> The Republican Party, also known as the GOP (Grand Old Party), is one of the two major contemporary political parties in the United States. It emerged as the main political rival of the then-dominant Democratic Party in the mid-1850s, and the two parties have dominated American politics ever since. The party was founded in 1854 by anti-slavery activists who opposed the Kansas–Nebraska Act, an act which allowed for the potential expansion of chattel slavery into the western territories of Kansas and Nebraska. It supported classical liberalism and economic reform while opposing the expansion of slavery into the free territories. The party initially had a very limited presence in the South, but was successful in the North. | T84: =IF(H84="", "", VALUE(H84)) -> 0.603 | U84: =_xlfn.CONCAT(TEXT(A84,"#"), IF(AND(A84>=10, A84<=19), "th", IF(MOD(A84,10) = 1, "st", IF(MOD(A84,10) = 2, "nd", IF(MOD(A84,10) = 3, "rd", "th"))))) -> 34th | V84: TRUE | X84: =IF(V84, W84, "") | Y84: =IF(NOT(V84), W84, "") | Z84: =_xlfn.CONCAT("https://en.wikipedia.org/wiki/", C84, "_United_States_presidential_election") -> https://en.wikipedia.org/wiki/1920_United_States_presidential_election
A85: 35 | B85: =VLOOKUP(D85,party!A:E,5,0) -> 26 | C85: 1924 | D85: Democratic | G85: 8386242 | H85: 0.288 | I85: 136 | P85: =TEXT(H85,"0.0%") -> 28.8% | Q85: =IF(IFERROR(VLOOKUP($D85,party!$A:$D,2,0),"")="","",IFERROR(VLOOKUP($D85,party!$A:$D,2,0),"")) | R85: =IF(IFERROR(VLOOKUP($D85,party!$A:$D,3,0),"")="","",IFERROR(VLOOKUP($D85,party!$A:$D,3,0),"")) -> https://en.wikipedia.org/wiki/Democratic_Party_(United_States) | S85: =IF(IFERROR(VLOOKUP($D85,party!$A:$D,4,0),"")="","",IFERROR(VLOOKUP($D85,party!$A:$D,4,0),"")) -> The Democratic Party is one of the two major contemporary political parties in the United States. Since the late 1850s, its main political rival has been the Republican Party; the two parties have since dominated American politics. The Democratic Party was founded in 1828. The Democratic Party is the world's oldest active political party. It initially supported expansive presidential power, the interests of slave states, agrarianism, and geographical expansionism, while opposing a national bank and high tariffs. It split in 1860 over slavery and won the presidency only twice between 1860 and 1912, although it won the popular vote two more times in that period. | T85: =IF(H85="", "", VALUE(H85)) -> 0.288 | U85: =_xlfn.CONCAT(TEXT(A85,"#"), IF(AND(A85>=10, A85<=19), "th", IF(MOD(A85,10) = 1, "st", IF(MOD(A85,10) = 2, "nd", IF(MOD(A85,10) = 3, "rd", "th"))))) -> 35th | V85: FALSE | W85: John W. Davis | X85: =IF(V85, W85, "") | Y85: =IF(NOT(V85), W85, "") -> John W. Davis | Z85: =_xlfn.CONCAT("https://en.wikipedia.org/wiki/", C85, "_United_States_presidential_election") -> https://en.wikipedia.org/wiki/1924_United_States_presidential_election
A86: 35 | B86: =VLOOKUP(D86,party!A:E,5,0) -> 17 | C86: 1924 | D86: Republican | E86: Calvin Coolidge | G86: 15723789 | H86: 0.54 | I86: 382 | P86: =TEXT(H86,"0.0%") -> 54.0% | Q86: =IF(IFERROR(VLOOKUP($D86,party!$A:$D,2,0),"")="","",IFERROR(VLOOKUP($D86,party!$A:$D,2,0),"")) | R86: =IF(IFERROR(VLOOKUP($D86,party!$A:$D,3,0),"")="","",IFERROR(VLOOKUP($D86,party!$A:$D,3,0),"")) -> https://en.wikipedia.org/wiki/Republican_Party_(United_States) | S86: =IF(IFERROR(VLOOKUP($D86,party!$A:$D,4,0),"")="","",IFERROR(VLOOKUP($D86,party!$A:$D,4,0),"")) -> The Republican Party, also known as the GOP (Grand Old Party), is one of the two major contemporary political parties in the United States. It emerged as the main political rival of the then-dominant Democratic Party in the mid-1850s, and the two parties have dominated American politics ever since. The party was founded in 1854 by anti-slavery activists who opposed the Kansas–Nebraska Act, an act which allowed for the potential expansion of chattel slavery into the western territories of Kansas and Nebraska. It supported classical liberalism and economic reform while opposing the expansion of slavery into the free territories. The party initially had a very limited presence in the South, but was successful in the North. | T86: =IF(H86="", "", VALUE(H86)) -> 0.54 | U86: =_xlfn.CONCAT(TEXT(A86,"#"), IF(AND(A86>=10, A86<=19), "th", IF(MOD(A86,10) = 1, "st", IF(MOD(A86,10) = 2, "nd", IF(MOD(A86,10) = 3, "rd", "th"))))) -> 35th | V86: TRUE | X86: =IF(V86, W86, "") | Y86: =IF(NOT(V86), W86, "") | Z86: =_xlfn.CONCAT("https://en.wikipedia.org/wiki/", C86, "_United_States_presidential_election") -> https://en.wikipedia.org/wiki/1924_United_States_presidential_election
A87: 35 | B87: =VLOOKUP(D87,party!A:E,5,0) -> 6 | C87: 1924 | D87: Progressive | G87: 4831706 | H87: 0.166 | I87: 13 | P87: =TEXT(H87,"0.0%") -> 16.6% | Q87: =IF(IFERROR(VLOOKUP($D87,party!$A:$D,2,0),"")="","",IFERROR(VLOOKUP($D87,party!$A:$D,2,0),"")) | R87: =IF(IFERROR(VLOOKUP($D87,party!$A:$D,3,0),"")="","",IFERROR(VLOOKUP($D87,party!$A:$D,3,0),"")) -> https://en.wikipedia.org/wiki/Progressive_Party_(United_States,_1924%E2%80%931934) | S87: =IF(IFERROR(VLOOKUP($D87,party!$A:$D,4,0),"")="","",IFERROR(VLOOKUP($D87,party!$A:$D,4,0),"")) -> The Progressive Party was a political party created as a vehicle for Robert M. La Follette, Sr. to run for president in the 1924 election. It did not run candidates for other offices, and it disappeared after the election. The party advocated progressive positions such as government ownership of railroads and electric utilities, cheap credit for farmers, the outlawing of child labor, stronger laws to help labor unions, more protection of civil liberties, an end to American imperialism in Latin America, and a referendum before any president could lead the nation into war. | T87: =IF(H87="", "", VALUE(H87)) -> 0.166 | U87: =_xlfn.CONCAT(TEXT(A87,"#"), IF(AND(A87>=10, A87<=19), "th", IF(MOD(A87,10) = 1, "st", IF(MOD(A87,10) = 2, "nd", IF(MOD(A87,10) = 3, "rd", "th"))))) -> 35th | V87: FALSE | W87: Robert M. La Follette | X87: =IF(V87, W87, "") | Y87: =IF(NOT(V87), W87, "") -> Robert M. La Follette | Z87: =_xlfn.CONCAT("https://en.wikipedia.org/wiki/", C87, "_United_States_presidential_election") -> https://en.wikipedia.org/wiki/1924_United_States_presidential_election
A88: 36 | B88: =VLOOKUP(D88,party!A:E,5,0) -> 26 | C88: 1928 | D88: Democratic | G88: 15015464 | H88: 0.408 | I88: 87 | P88: =TEXT(H88,"0.0%") -> 40.8% | Q88: =IF(IFERROR(VLOOKUP($D88,party!$A:$D,2,0),"")="","",IFERROR(VLOOKUP($D88,party!$A:$D,2,0),"")) | R88: =IF(IFERROR(VLOOKUP($D88,party!$A:$D,3,0),"")="","",IFERROR(VLOOKUP($D88,party!$A:$D,3,0),"")) -> https://en.wikipedia.org/wiki/Democratic_Party_(United_States) | S88: =IF(IFERROR(VLOOKUP($D88,party!$A:$D,4,0),"")="","",IFERROR(VLOOKUP($D88,party!$A:$D,4,0),"")) -> The Democratic Party is one of the two major contemporary political parties in the United States. Since the late 1850s, its main political rival has been the Republican Party; the two parties have since dominated American politics. The Democratic Party was founded in 1828. The Democratic Party is the world's oldest active political party. It initially supported expansive presidential power, the interests of slave states, agrarianism, and geographical expansionism, while opposing a national bank and high tariffs. It split in 1860 over slavery and won the presidency only twice between 1860 and 1912, although it won the popular vote two more times in that period. | T88: =IF(H88="", "", VALUE(H88)) -> 0.408 | U88: =_xlfn.CONCAT(TEXT(A88,"#"), IF(AND(A88>=10, A88<=19), "th", IF(MOD(A88,10) = 1, "st", IF(MOD(A88,10) = 2, "nd", IF(MOD(A88,10) = 3, "rd", "th"))))) -> 36th | V88: FALSE | W88: Al Smith | X88: =IF(V88, W88, "") | Y88: =IF(NOT(V88), W88, "") -> Al Smith | Z88: =_xlfn.CONCAT("https://en.wikipedia.org/wiki/", C88, "_United_States_presidential_election") -> https://en.wikipedia.org/wiki/1928_United_States_presidential_election
A89: 36 | B89: =VLOOKUP(D89,party!A:E,5,0) -> 17 | C89: 1928 | D89: Republican | E89: Herbert Hoover | G89: 21427123 | H89: 0.582 | I89: 444 | P89: =TEXT(H89,"0.0%") -> 58.2% | Q89: =IF(IFERROR(VLOOKUP($D89,party!$A:$D,2,0),"")="","",IFERROR(VLOOKUP($D89,party!$A:$D,2,0),"")) | R89: =IF(IFERROR(VLOOKUP($D89,party!$A:$D,3,0),"")="","",IFERROR(VLOOKUP($D89,party!$A:$D,3,0),"")) -> https://en.wikipedia.org/wiki/Republican_Party_(United_States) | S89: =IF(IFERROR(VLOOKUP($D89,party!$A:$D,4,0),"")="","",IFERROR(VLOOKUP($D89,party!$A:$D,4,0),"")) -> The Republican Party, also known as the GOP (Grand Old Party), is one of the two major contemporary political parties in the United States. It emerged as the main political rival of the then-dominant Democratic Party in the mid-1850s, and the two parties have dominated American politics ever since. The party was founded in 1854 by anti-slavery activists who opposed the Kansas–Nebraska Act, an act which allowed for the potential expansion of chattel slavery into the western territories of Kansas and Nebraska. It supported classical liberalism and economic reform while opposing the expansion of slavery into the free territories. The party initially had a very limited presence in the South, but was successful in the North. | T89: =IF(H89="", "", VALUE(H89)) -> 0.582 | U89: =_xlfn.CONCAT(TEXT(A89,"#"), IF(AND(A89>=10, A89<=19), "th", IF(MOD(A89,10) = 1, "st", IF(MOD(A89,10) = 2, "nd", IF(MOD(A89,10) = 3, "rd", "th"))))) -> 36th | V89: TRUE | X89: =IF(V89, W89, "") | Y89: =IF(NOT(V89), W89, "") | Z89: =_xlfn.CONCAT("https://en.wikipedia.org/wiki/", C89, "_United_States_presidential_election") -> https://en.wikipedia.org/wiki/1928_United_States_presidential_election
A90: 37 | B90: =VLOOKUP(D90,party!A:E,5,0) -> 26 | C90: 1932 | D90: Democratic | E90: Franklin D. Roosevelt | G90: 22821277 | H90: 0.574 | I90: 472 | P90: =TEXT(H90,"0.0%") -> 57.4% | Q90: =IF(IFERROR(VLOOKUP($D90,party!$A:$D,2,0),"")="","",IFERROR(VLOOKUP($D90,party!$A:$D,2,0),"")) | R90: =IF(IFERROR(VLOOKUP($D90,party!$A:$D,3,0),"")="","",IFERROR(VLOOKUP($D90,party!$A:$D,3,0),"")) -> https://en.wikipedia.org/wiki/Democratic_Party_(United_States) | S90: =IF(IFERROR(VLOOKUP($D90,party!$A:$D,4,0),"")="","",IFERROR(VLOOKUP($D90,party!$A:$D,4,0),"")) -> The Democratic Party is one of the two major contemporary political parties in the United States. Since the late 1850s, its main political rival has been the Republican Party; the two parties have since dominated American politics. The Democratic Party was founded in 1828. The Democratic Party is the world's oldest active political party. It initially supported expansive presidential power, the interests of slave states, agrarianism, and geographical expansionism, while opposing a national bank and high tariffs. It split in 1860 over slavery and won the presidency only twice between 1860 and 1912, although it won the popular vote two more times in that period. | T90: =IF(H90="", "", VALUE(H90)) -> 0.574 | U90: =_xlfn.CONCAT(TEXT(A90,"#"), IF(AND(A90>=10, A90<=19), "th", IF(MOD(A90,10) = 1, "st", IF(MOD(A90,10) = 2, "nd", IF(MOD(A90,10) = 3, "rd", "th"))))) -> 37th | V90: TRUE | X90: =IF(V90, W90, "") | Y90: =IF(NOT(V90), W90, "") | Z90: =_xlfn.CONCAT("https://en.wikipedia.org/wiki/", C90, "_United_States_presidential_election") -> https://en.wikipedia.org/wiki/1932_United_States_presidential_election
A91: 37 | B91: =VLOOKUP(D91,party!A:E,5,0) -> 17 | C91: 1932 | D91: Republican | G91: 15761254 | H91: 0.397 | I91: 59 | P91: =TEXT(H91,"0.0%") -> 39.7% | Q91: =IF(IFERROR(VLOOKUP($D91,party!$A:$D,2,0),"")="","",IFERROR(VLOOKUP($D91,party!$A:$D,2,0),"")) | R91: =IF(IFERROR(VLOOKUP($D91,party!$A:$D,3,0),"")="","",IFERROR(VLOOKUP($D91,party!$A:$D,3,0),"")) -> https://en.wikipedia.org/wiki/Republican_Party_(United_States) | S91: =IF(IFERROR(VLOOKUP($D91,party!$A:$D,4,0),"")="","",IFERROR(VLOOKUP($D91,party!$A:$D,4,0),"")) -> The Republican Party, also known as the GOP (Grand Old Party), is one of the two major contemporary political parties in the United States. It emerged as the main political rival of the then-dominant Democratic Party in the mid-1850s, and the two parties have dominated American politics ever since. The party was founded in 1854 by anti-slavery activists who opposed the Kansas–Nebraska Act, an act which allowed for the potential expansion of chattel slavery into the western territories of Kansas and Nebraska. It supported classical liberalism and economic reform while opposing the expansion of slavery into the free territories. The party initially had a very limited presence in the South, but was successful in the North. | T91: =IF(H91="", "", VALUE(H91)) -> 0.397 | U91: =_xlfn.CONCAT(TEXT(A91,"#"), IF(AND(A91>=10, A91<=19), "th", IF(MOD(A91,10) = 1, "st", IF(MOD(A91,10) = 2, "nd", IF(MOD(A91,10) = 3, "rd", "th"))))) -> 37th | V91: FALSE | W91: Herbert Hoover | X91: =IF(V91, W91, "") | Y91: =IF(NOT(V91), W91, "") -> Herbert Hoover | Z91: =_xlfn.CONCAT("https://en.wikipedia.org/wiki/", C91, "_United_States_presidential_election") -> https://en.wikipedia.org/wiki/1932_United_States_presidential_election
A92: 38 | B92: =VLOOKUP(D92,party!A:E,5,0) -> 26 | C92: 1936 | D92: Democratic | E92: Franklin D. Roosevelt | G92: 27752648 | H92: 0.608 | I92: 523 | P92: =TEXT(H92,"0.0%") -> 60.8% | Q92: =IF(IFERROR(VLOOKUP($D92,party!$A:$D,2,0),"")="","",IFERROR(VLOOKUP($D92,party!$A:$D,2,0),"")) | R92: =IF(IFERROR(VLOOKUP($D92,party!$A:$D,3,0),"")="","",IFERROR(VLOOKUP($D92,party!$A:$D,3,0),"")) -> https://en.wikipedia.org/wiki/Democratic_Party_(United_States) | S92: =IF(IFERROR(VLOOKUP($D92,party!$A:$D,4,0),"")="","",IFERROR(VLOOKUP($D92,party!$A:$D,4,0),"")) -> The Democratic Party is one of the two major contemporary political parties in the United States. Since the late 1850s, its main political rival has been the Republican Party; the two parties have since dominated American politics. The Democratic Party was founded in 1828. The Democratic Party is the world's oldest active political party. It initially supported expansive presidential power, the interests of slave states, agrarianism, and geographical expansionism, while opposing a national bank and high tariffs. It split in 1860 over slavery and won the presidency only twice between 1860 and 1912, although it won the popular vote two more times in that period. | T92: =IF(H92="", "", VALUE(H92)) -> 0.608 | U92: =_xlfn.CONCAT(TEXT(A92,"#"), IF(AND(A92>=10, A92<=19), "th", IF(MOD(A92,10) = 1, "st", IF(MOD(A92,10) = 2, "nd", IF(MOD(A92,10) = 3, "rd", "th"))))) -> 38th | V92: TRUE | X92: =IF(V92, W92, "") | Y92: =IF(NOT(V92), W92, "") | Z92: =_xlfn.CONCAT("https://en.wikipedia.org/wiki/", C92, "_United_States_presidential_election") -> https://en.wikipedia.org/wiki/1936_United_States_presidential_election
A93: 38 | B93: =VLOOKUP(D93,party!A:E,5,0) -> 17 | C93: 1936 | D93: Republican | G93: 16681862 | H93: 0.365 | I93: 8 | P93: =TEXT(H93,"0.0%") -> 36.5% | Q93: =IF(IFERROR(VLOOKUP($D93,party!$A:$D,2,0),"")="","",IFERROR(VLOOKUP($D93,party!$A:$D,2,0),"")) | R93: =IF(IFERROR(VLOOKUP($D93,party!$A:$D,3,0),"")="","",IFERROR(VLOOKUP($D93,party!$A:$D,3,0),"")) -> https://en.wikipedia.org/wiki/Republican_Party_(United_States) | S93: =IF(IFERROR(VLOOKUP($D93,party!$A:$D,4,0),"")="","",IFERROR(VLOOKUP($D93,party!$A:$D,4,0),"")) -> The Republican Party, also known as the GOP (Grand Old Party), is one of the two major contemporary political parties in the United States. It emerged as the main political rival of the then-dominant Democratic Party in the mid-1850s, and the two parties have dominated American politics ever since. The party was founded in 1854 by anti-slavery activists who opposed the Kansas–Nebraska Act, an act which allowed for the potential expansion of chattel slavery into the western territories of Kansas and Nebraska. It supported classical liberalism and economic reform while opposing the expansion of slavery into the free territories. The party initially had a very limited presence in the South, but was successful in the North. | T93: =IF(H93="", "", VALUE(H93)) -> 0.365 | U93: =_xlfn.CONCAT(TEXT(A93,"#"), IF(AND(A93>=10, A93<=19), "th", IF(MOD(A93,10) = 1, "st", IF(MOD(A93,10) = 2, "nd", IF(MOD(A93,10) = 3, "rd", "th"))))) -> 38th | V93: FALSE | W93: Alf Landon | X93: =IF(V93, W93, "") | Y93: =IF(NOT(V93), W93, "") -> Alf Landon | Z93: =_xlfn.CONCAT("https://en.wikipedia.org/wiki/", C93, "_United_States_presidential_election") -> https://en.wikipedia.org/wiki/1936_United_States_presidential_election
A94: 39 | B94: =VLOOKUP(D94,party!A:E,5,0) -> 26 | C94: 1940 | D94: Democratic | E94: Franklin D. Roosevelt | G94: 27313945 | H94: 0.547 | I94: 449 | P94: =TEXT(H94,"0.0%") -> 54.7% | Q94: =IF(IFERROR(VLOOKUP($D94,party!$A:$D,2,0),"")="","",IFERROR(VLOOKUP($D94,party!$A:$D,2,0),"")) | R94: =IF(IFERROR(VLOOKUP($D94,party!$A:$D,3,0),"")="","",IFERROR(VLOOKUP($D94,party!$A:$D,3,0),"")) -> https://en.wikipedia.org/wiki/Democratic_Party_(United_States) | S94: =IF(IFERROR(VLOOKUP($D94,party!$A:$D,4,0),"")="","",IFERROR(VLOOKUP($D94,party!$A:$D,4,0),"")) -> The Democratic Party is one of the two major contemporary political parties in the United States. Since the late 1850s, its main political rival has been the Republican Party; the two parties have since dominated American politics. The Democratic Party was founded in 1828. The Democratic Party is the world's oldest active political party. It initially supported expansive presidential power, the interests of slave states, agrarianism, and geographical expansionism, while opposing a national bank and high tariffs. It split in 1860 over slavery and won the presidency only twice between 1860 and 1912, although it won the popular vote two more times in that period. | T94: =IF(H94="", "", VALUE(H94)) -> 0.547 | U94: =_xlfn.CONCAT(TEXT(A94,"#"), IF(AND(A94>=10, A94<=19), "th", IF(MOD(A94,10) = 1, "st", IF(MOD(A94,10) = 2, "nd", IF(MOD(A94,10) = 3, "rd", "th"))))) -> 39th | V94: TRUE | X94: =IF(V94, W94, "") | Y94: =IF(NOT(V94), W94, "") | Z94: =_xlfn.CONCAT("https://en.wikipedia.org/wiki/", C94, "_United_States_presidential_election") -> https://en.wikipedia.org/wiki/1940_United_States_presidential_election
A95: 39 | B95: =VLOOKUP(D95,party!A:E,5,0) -> 17 | C95: 1940 | D95: Republican | G95: 22347744 | H95: 0.448 | I95: 82 | P95: =TEXT(H95,"0.0%") -> 44.8% | Q95: =IF(IFERROR(VLOOKUP($D95,party!$A:$D,2,0),"")="","",IFERROR(VLOOKUP($D95,party!$A:$D,2,0),"")) | R95: =IF(IFERROR(VLOOKUP($D95,party!$A:$D,3,0),"")="","",IFERROR(VLOOKUP($D95,party!$A:$D,3,0),"")) -> https://en.wikipedia.org/wiki/Republican_Party_(United_States) | S95: =IF(IFERROR(VLOOKUP($D95,party!$A:$D,4,0),"")="","",IFERROR(VLOOKUP($D95,party!$A:$D,4,0),"")) -> The Republican Party, also known as the GOP (Grand Old Party), is one of the two major contemporary political parties in the United States. It emerged as the main political rival of the then-dominant Democratic Party in the mid-1850s, and the two parties have dominated American politics ever since. The party was founded in 1854 by anti-slavery activists who opposed the Kansas–Nebraska Act, an act which allowed for the potential expansion of chattel slavery into the western territories of Kansas and Nebraska. It supported classical liberalism and economic reform while opposing the expansion of slavery into the free territories. The party initially had a very limited presence in the South, but was successful in the North. | T95: =IF(H95="", "", VALUE(H95)) -> 0.448 | U95: =_xlfn.CONCAT(TEXT(A95,"#"), IF(AND(A95>=10, A95<=19), "th", IF(MOD(A95,10) = 1, "st", IF(MOD(A95,10) = 2, "nd", IF(MOD(A95,10) = 3, "rd", "th"))))) -> 39th | V95: FALSE | W95: Wendell Willkie | X95: =IF(V95, W95, "") | Y95: =IF(NOT(V95), W95, "") -> Wendell Willkie | Z95: =_xlfn.CONCAT("https://en.wikipedia.org/wiki/", C95, "_United_States_presidential_election") -> https://en.wikipedia.org/wiki/1940_United_States_presidential_election
A96: 40 | B96: =VLOOKUP(D96,party!A:E,5,0) -> 26 | C96: 1944 | D96: Democratic | E96: Franklin D. Roosevelt | G96: 25612916 | H96: 0.534 | I96: 432 | P96: =TEXT(H96,"0.0%") -> 53.4% | Q96: =IF(IFERROR(VLOOKUP($D96,party!$A:$D,2,0),"")="","",IFERROR(VLOOKUP($D96,party!$A:$D,2,0),"")) | R96: =IF(IFERROR(VLOOKUP($D96,party!$A:$D,3,0),"")="","",IFERROR(VLOOKUP($D96,party!$A:$D,3,0),"")) -> https://en.wikipedia.org/wiki/Democratic_Party_(United_States) | S96: =IF(IFERROR(VLOOKUP($D96,party!$A:$D,4,0),"")="","",IFERROR(VLOOKUP($D96,party!$A:$D,4,0),"")) -> The Democratic Party is one of the two major contemporary political parties in the United States. Since the late 1850s, its main political rival has been the Republican Party; the two parties have since dominated American politics. The Democratic Party was founded in 1828. The Democratic Party is the world's oldest active political party. It initially supported expansive presidential power, the interests of slave states, agrarianism, and geographical expansionism, while opposing a national bank and high tariffs. It split in 1860 over slavery and won the presidency only twice between 1860 and 1912, although it won the popular vote two more times in that period. | T96: =IF(H96="", "", VALUE(H96)) -> 0.534 | U96: =_xlfn.CONCAT(TEXT(A96,"#"), IF(AND(A96>=10, A96<=19), "th", IF(MOD(A96,10) = 1, "st", IF(MOD(A96,10) = 2, "nd", IF(MOD(A96,10) = 3, "rd", "th"))))) -> 40th | V96: TRUE | X96: =IF(V96, W96, "") | Y96: =IF(NOT(V96), W96, "") | Z96: =_xlfn.CONCAT("https://en.wikipedia.org/wiki/", C96, "_United_States_presidential_election") -> https://en.wikipedia.org/wiki/1944_United_States_presidential_election
A97: 40 | B97: =VLOOKUP(D97,party!A:E,5,0) -> 17 | C97: 1944 | D97: Republican | G97: 22017929 | H97: 0.459 | I97: 99 | P97: =TEXT(H97,"0.0%") -> 45.9% | Q97: =IF(IFERROR(VLOOKUP($D97,party!$A:$D,2,0),"")="","",IFERROR(VLOOKUP($D97,party!$A:$D,2,0),"")) | R97: =IF(IFERROR(VLOOKUP($D97,party!$A:$D,3,0),"")="","",IFERROR(VLOOKUP($D97,party!$A:$D,3,0),"")) -> https://en.wikipedia.org/wiki/Republican_Party_(United_States) | S97: =IF(IFERROR(VLOOKUP($D97,party!$A:$D,4,0),"")="","",IFERROR(VLOOKUP($D97,party!$A:$D,4,0),"")) -> The Republican Party, also known as the GOP (Grand Old Party), is one of the two major contemporary political parties in the United States. It emerged as the main political rival of the then-dominant Democratic Party in the mid-1850s, and the two parties have dominated American politics ever since. The party was founded in 1854 by anti-slavery activists who opposed the Kansas–Nebraska Act, an act which allowed for the potential expansion of chattel slavery into the western territories of Kansas and Nebraska. It supported classical liberalism and economic reform while opposing the expansion of slavery into the free territories. The party initially had a very limited presence in the South, but was successful in the North. | T97: =IF(H97="", "", VALUE(H97)) -> 0.459 | U97: =_xlfn.CONCAT(TEXT(A97,"#"), IF(AND(A97>=10, A97<=19), "th", IF(MOD(A97,10) = 1, "st", IF(MOD(A97,10) = 2, "nd", IF(MOD(A97,10) = 3, "rd", "th"))))) -> 40th | V97: FALSE | W97: Thomas E. Dewey | X97: =IF(V97, W97, "") | Y97: =IF(NOT(V97), W97, "") -> Thomas E. Dewey | Z97: =_xlfn.CONCAT("https://en.wikipedia.org/wiki/", C97, "_United_States_presidential_election") -> https://en.wikipedia.org/wiki/1944_United_States_presidential_election
A98: 41 | B98: =VLOOKUP(D98,party!A:E,5,0) -> 26 | C98: 1948 | D98: Democratic | E98: Harry S. Truman | G98: 24179347 | H98: 0.496 | I98: 303 | P98: =TEXT(H98,"0.0%") -> 49.6% | Q98: =IF(IFERROR(VLOOKUP($D98,party!$A:$D,2,0),"")="","",IFERROR(VLOOKUP($D98,party!$A:$D,2,0),"")) | R98: =IF(IFERROR(VLOOKUP($D98,party!$A:$D,3,0),"")="","",IFERROR(VLOOKUP($D98,party!$A:$D,3,0),"")) -> https://en.wikipedia.org/wiki/Democratic_Party_(United_States) | S98: =IF(IFERROR(VLOOKUP($D98,party!$A:$D,4,0),"")="","",IFERROR(VLOOKUP($D98,party!$A:$D,4,0),"")) -> The Democratic Party is one of the two major contemporary political parties in the United States. Since the late 1850s, its main political rival has been the Republican Party; the two parties have since dominated American politics. The Democratic Party was founded in 1828. The Democratic Party is the world's oldest active political party. It initially supported expansive presidential power, the interests of slave states, agrarianism, and geographical expansionism, while opposing a national bank and high tariffs. It split in 1860 over slavery and won the presidency only twice between 1860 and 1912, although it won the popular vote two more times in that period. | T98: =IF(H98="", "", VALUE(H98)) -> 0.496 | U98: =_xlfn.CONCAT(TEXT(A98,"#"), IF(AND(A98>=10, A98<=19), "th", IF(MOD(A98,10) = 1, "st", IF(MOD(A98,10) = 2, "nd", IF(MOD(A98,10) = 3, "rd", "th"))))) -> 41st | V98: TRUE | X98: =IF(V98, W98, "") | Y98: =IF(NOT(V98), W98, "") | Z98: =_xlfn.CONCAT("https://en.wikipedia.org/wiki/", C98, "_United_States_presidential_election") -> https://en.wikipedia.org/wiki/1948_United_States_presidential_election
A99: 41 | B99: =VLOOKUP(D99,party!A:E,5,0) -> 17 | C99: 1948 | D99: Republican | G99: 21991292 | H99: 0.451 | I99: 189 | P99: =TEXT(H99,"0.0%") -> 45.1% | Q99: =IF(IFERROR(VLOOKUP($D99,party!$A:$D,2,0),"")="","",IFERROR(VLOOKUP($D99,party!$A:$D,2,0),"")) | R99: =IF(IFERROR(VLOOKUP($D99,party!$A:$D,3,0),"")="","",IFERROR(VLOOKUP($D99,party!$A:$D,3,0),"")) -> https://en.wikipedia.org/wiki/Republican_Party_(United_States) | S99: =IF(IFERROR(VLOOKUP($D99,party!$A:$D,4,0),"")="","",IFERROR(VLOOKUP($D99,party!$A:$D,4,0),"")) -> The Republican Party, also known as the GOP (Grand Old Party), is one of the two major contemporary political parties in the United States. It emerged as the main political rival of the then-dominant Democratic Party in the mid-1850s, and the two parties have dominated American politics ever since. The party was founded in 1854 by anti-slavery activists who opposed the Kansas–Nebraska Act, an act which allowed for the potential expansion of chattel slavery into the western territories of Kansas and Nebraska. It supported classical liberalism and economic reform while opposing the expansion of slavery into the free territories. The party initially had a very limited presence in the South, but was successful in the North. | T99: =IF(H99="", "", VALUE(H99)) -> 0.451 | U99: =_xlfn.CONCAT(TEXT(A99,"#"), IF(AND(A99>=10, A99<=19), "th", IF(MOD(A99,10) = 1, "st", IF(MOD(A99,10) = 2, "nd", IF(MOD(A99,10) = 3, "rd", "th"))))) -> 41st | V99: FALSE | W99: Thomas E. Dewey | X99: =IF(V99, W99, "") | Y99: =IF(NOT(V99), W99, "") -> Thomas E. Dewey | Z99: =_xlfn.CONCAT("https://en.wikipedia.org/wiki/", C99, "_United_States_presidential_election") -> https://en.wikipedia.org/wiki/1948_United_States_presidential_election
A100: 41 | B100: =VLOOKUP(D100,party!A:E,5,0) -> 31 | C100: 1948 | D100: Dixiecrat | G100: 1175930 | H100: 0.024 | I100: 39 | P100: =TEXT(H100,"0.0%") -> 2.4% | Q100: =IF(IFERROR(VLOOKUP($D100,party!$A:$D,2,0),"")="","",IFERROR(VLOOKUP($D100,party!$A:$D,2,0),"")) | R100: =IF(IFERROR(VLOOKUP($D100,party!$A:$D,3,0),"")="","",IFERROR(VLOOKUP($D100,party!$A:$D,3,0),"")) -> https://en.wikipedia.org/wiki/Dixiecrat | S100: =IF(IFERROR(VLOOKUP($D100,party!$A:$D,4,0),"")="","",IFERROR(VLOOKUP($D100,party!$A:$D,4,0),"")) -> The States' Rights Democratic Party (whose members are often called the Dixiecrats), also colloquially referred to as the Dixiecrat Party was a short-lived segregationist political party in the United States, active primarily in the South. It arose due to a Southern regional split in opposition to the national Democratic Party. After President Harry S. Truman, the leader of the Democratic Party, ordered integration of the military in 1948 and other actions to address civil rights of African Americans, including the first presidential proposal for comprehensive civil and voting rights, many Southern white politicians who objected to this course organized themselves as a breakaway faction. They wished to protect the ability of states to maintain racial segregation. Its members were referred to as "Dixiecrats", a portmanteau of "Dixie", referring to the Southern United States, and "Democrat". | T100: =IF(H100="", "", VALUE(H100)) -> 0.024 | U100: =_xlfn.CONCAT(TEXT(A100,"#"), IF(AND(A100>=10, A100<=19), "th", IF(MOD(A100,10) = 1, "st", IF(MOD(A100,10) = 2, "nd", IF(MOD(A100,10) = 3, "rd", "th"))))) -> 41st | V100: FALSE | W100: Strom Thurmond | X100: =IF(V100, W100, "") | Y100: =IF(NOT(V100), W100, "") -> Strom Thurmond | Z100: =_xlfn.CONCAT("https://en.wikipedia.org/wiki/", C100, "_United_States_presidential_election") -> https://en.wikipedia.org/wiki/1948_United_States_presidential_election
...

Sheet party
A1: party | B1: misc | C1: link | D1: desc | E1: logical_order
A2: Independent | B2: Not a party. | C2: https://en.wikipedia.org/wiki/Independent_politician | D2: An independent, non-partisan politician or non-affiliated politician is a politician not affiliated with any political party or bureaucratic association. There are numerous reasons why someone may stand for office as an independent. George Washington is the only U.S. president elected as an independent to date. Washington opposed the development of political parties. He feared that partisanship would eventually destroy the country, and famously warned against "the baneful effects of the spirit of party" in his 1796 Farewell Address. | E2: 1
A3: Nullifier | C3: https://en.wikipedia.org/wiki/Nullifier_Party | D3: The Nullifier Party was an American political party based in South Carolina in the 1830s. Considered an early American third party, it was started by John C. Calhoun in 1828. The Nullifier Party was a states' rights, pro-slavery party that supported strict constructionism with regards to the U.S. government's enumerated powers, holding that states could nullify federal laws within their borders. It narrowly missed claiming the unofficial title of being the first ever third party to be created within the United States—that title belongs to the Anti-Masonic Party, which was created in New York in February 1828. | E3: 2
A4: American | C4: https://en.wikipedia.org/wiki/Know_Nothing | D4: The Know Nothings were a nativist political movement in the United States in the 1850s, officially known as the Native American Party before 1855, and afterwards simply the American Party. Members of the movement were required to say "I know nothing" whenever they were asked about its specifics by outsiders, providing the group with its colloquial name. Supporters of the Know Nothing movement believed that an alleged "Romanist" conspiracy to subvert civil and religious liberty in the United States was being hatched by Catholics. Therefore, they sought to politically organize native-born Protestants in defense of their traditional religious and political values. The Know Nothing movement briefly emerged as a major political party in the form of the American Party. The collapse of the Whig Party after the passage of the Kansas–Nebraska Act left an opening for the emergence of a new major political party in opposition to the Democratic Party. | E4: 3
A5: Constitutional Union | C5: https://en.wikipedia.org/wiki/Constitutional_Union_Party_(United_States) | D5: The Constitutional Union Party was a political party which stood in the 1860 United States elections. It mostly consisted of conservative former Whigs from the Southern United States who wanted to avoid secession over slavery and refused to join either the Republican Party or Democratic Party. | E5: 4
A6: Socialist | C6: https://en.wikipedia.org/wiki/Socialist_Party_of_America | D6: The Socialist Party of America (SPA) was a socialist political party in the United States formed in 1901 by a merger between the three-year-old Social Democratic Party of America and disaffected elements of the Socialist Labor Party of America who had split from the main organization in 1899. | E6: 5
A7: Progressive | C7: https://en.wikipedia.org/wiki/Progressive_Party_(United_States,_1924%E2%80%931934) | D7: The Progressive Party was a political party created as a vehicle for Robert M. La Follette, Sr. to run for president in the 1924 election. It did not run candidates for other offices, and it disappeared after the election. The party advocated progressive positions such as government ownership of railroads and electric utilities, cheap credit for farmers, the outlawing of child labor, stronger laws to help labor unions, more protection of civil liberties, an end to American imperialism in Latin America, and a referendum before any president could lead the nation into war. | E7: 6
A8: American Independent | C8: https://en.wikipedia.org/wiki/American_Independent_Party | D8: The American Independent Party (AIP) is a far-right political party in the United States that was established in 1967. The AIP is best known for its nomination of Democratic then-former Governor George Wallace of Alabama, who carried five states in the 1968 presidential election running on a populist, hard-line anti-Communist, pro-"law and order" platform, appealing to working-class white voters and widely understood by political analysts as having pro-segregationist or white supremacist undertones, against Richard Nixon and Hubert Humphrey. In 1976, the party split into the modern American Independent Party and the American Party. | E8: 7
A9: Libertarian | C9: https://en.wikipedia.org/wiki/Libertarian_Party_(United_States) | D9: The Libertarian Party (LP) is a classical liberal political party in the United States that promotes civil liberties, non-interventionism, laissez-faire capitalism, and limiting the size and scope of government. The party was officially formed on December 11, 1971, in Colorado Springs. The organizers of the party drew inspiration from the works and ideas of the prominent Austrian school economist Murray Rothbard. The founding of the party was prompted in part due to concerns about the Nixon administration, the Vietnam War, conscription, and the introduction of fiat money. | E9: 8
A10: Reform | C10: https://en.wikipedia.org/wiki/Reform_Party_of_the_United_States_of_America | D10: The Reform Party of the United States of America (RPUSA), generally known as the Reform Party USA or the Reform Party, is a centrist political party in the United States, founded in 1995 by Ross Perot. Perot believed Americans were disillusioned with the state of politics as being corrupt and unable to deal with vital issues. After he received 18.9 percent of the popular vote as an independent candidate in the 1992 presidential election, he founded the Reform Party and presented it as a viable alternative to Republicans and Democrats. | E10: 9
A11: Federalist | C11: https://en.wikipedia.org/wiki/Federalist_Party | D11: The Federalist Party was a conservative and nationalist American political party and the first political party in the United States. It dominated the national government under Alexander Hamilton from 1789 to 1801. The party was defeated by the Democratic-Republican Party in 1800, and it became a minority party while keeping its stronghold in New England. It made a brief resurgence by opposing the War of 1812, then collapsed with its last presidential candidate in 1816. Remnants lasted for a few years afterwards. | E11: 10
A12: Democratic-Republican (Clay faction) | B12: Not a party. | C12: https://en.wikipedia.org/wiki/1824_United_States_presidential_election | D12: The Democratic-Republican Party had won six consecutive presidential elections and by 1824 was the only national political party. However, as the election approached, the presence of multiple viable candidates resulted in there being multiple nominations by the contending factions, signaling the splintering of the party and an end to the Era of Good Feelings, as well as the First Party System. Adams won New England, Jackson and Adams split the mid-Atlantic states, Jackson and Clay split the Western states, and Jackson and Crawford split the Southern states. | E12: 11
A13: Democratic-Republican (Adams faction) | B13: Not a party. | C13: https://en.wikipedia.org/wiki/1824_United_States_presidential_election | D13: The Democratic-Republican Party had won six consecutive presidential elections and by 1824 was the only national political party. However, as the election approached, the presence of multiple viable candidates resulted in there being multiple nominations by the contending factions, signaling the splintering of the party and an end to the Era of Good Feelings, as well as the First Party System. Adams won New England, Jackson and Adams split the mid-Atlantic states, Jackson and Clay split the Western states, and Jackson and Crawford split the Southern states. | E13: 12
A14: National Republican | C14: https://en.wikipedia.org/wiki/National_Republican_Party | D14: The National Republican Party, also known as the Anti-Jacksonian Party or simply Republicans, was a political party in the United States which evolved from a conservative-leaning faction of the Democratic-Republican Party that supported John Quincy Adams in the 1824 presidential election. After the 1832 election, opponents of Jackson coalesced into the Whig Party. National Republicans, Anti-Masons and others joined the new party. | E14: 13
A15: Anti-Masonic | C15: https://en.wikipedia.org/wiki/Anti-Masonic_Party | D15: The Anti-Masonic Party was the earliest third party in the United States. Formally a single-issue party, it strongly opposed Freemasonry in the United States. It was active from the late 1820s, especially in the Northeast, and later attempted to become a major party by expanding its platform to take positions on other issues. It declined quickly after 1832 as most members joined the new Whig Party; it disappeared after 1838. | E15: 14
A16: Whig | C16: https://en.wikipedia.org/wiki/Whig_Party_(United_States) | D16: The Whig Party was a mid-19th century political party in the United States. Alongside the Democratic Party, it was one of two major parties between the late 1830s and the early 1850s and part of the Second Party System. The Whigs emerged in the 1830s in opposition to President Andrew Jackson, pulling together former members of the National Republican Party, the Anti-Masonic Party, and disaffected Democrats. | E16: 15
A17: Free Soil | C17: https://en.wikipedia.org/wiki/Free_Soil_Party | D17: The Free Soil Party was a political party in the United States from 1848 to 1854, when it merged into the Republican Party. The party was focused on opposing the expansion of slavery into the western territories of the United States. | E17: 16
A18: Republican | C18: https://en.wikipedia.org/wiki/Republican_Party_(United_States) | D18: The Republican Party, also known as the GOP (Grand Old Party), is one of the two major contemporary political parties in the United States. It emerged as the main political rival of the then-dominant Democratic Party in the mid-1850s, and the two parties have dominated American politics ever since. The party was founded in 1854 by anti-slavery activists who opposed the Kansas–Nebraska Act, an act which allowed for the potential expansion of chattel slavery into the western territories of Kansas and Nebraska. It supported classical liberalism and economic reform while opposing the expansion of slavery into the free territories. The party initially had a very limited presence in the South, but was successful in the North. | E18: 17
A19: National Union | C19: https://en.wikipedia.org/wiki/National_Union_Party_(United_States) | D19: The National Union Party, commonly the Union Party or Unionists, was a wartime coalition of Republicans, War Democrats, and border state Unconditional Unionists that supported the Lincoln Administration during the American Civil War. It held the 1864 National Union Convention that nominated Abraham Lincoln for president and Andrew Johnson for vice president in the 1864 United States presidential election. | E19: 18
A20: Liberal Republican | C20: https://en.wikipedia.org/wiki/Liberal_Republican_Party_(United_States) | D20: The Liberal Republican Party was an American political party that was organized in May 1872 to oppose the reelection of President Ulysses S. Grant and his Radical Republican supporters in the presidential election of 1872. The party opposed Grant's Reconstruction policies, particularly the Enforcement Acts that destroyed the Ku Klux Klan. It lost in a landslide, and disappeared from the national stage after the 1872 election. | E20: 19
A21: Progressive (Bull Moose) | C21: https://en.wikipedia.org/wiki/Bull_Moose_Party | D21: The Progressive Party, popularly nicknamed the Bull Moose Party, was a third party in the United States formed in 1912 by former president Theodore Roosevelt after he lost the presidential nomination of the Republican Party to his former protégé turned rival, incumbent president William Howard Taft. The new party was known for taking advanced positions on progressive reforms and attracting leading national reformers. The party was also ideologically deeply connected with America's radical-liberal tradition. After the party's defeat in the 1912 United States presidential election, it went into rapid decline in elections until 1918, disappearing by 1920. The "Bull Moose" nickname originated when Roosevelt boasted that he felt "strong as a bull moose" after losing the Republican nomination in June 1912 at the Chicago convention. | E21: 20
A22: Anti-Administration | B22: Not a party. | C22: https://en.wikipedia.org/wiki/Anti-Administration_party | D22: The Anti-Administration party was an informal political faction in the United States led by James Madison and Thomas Jefferson that opposed policies of then Secretary of the Treasury Alexander Hamilton in the first term of U.S. president George Washington. It was not an organized political party, but an unorganized faction. Most members had been Anti-Federalists in 1788, when they opposed ratification of the U.S. Constitution. Although contemporaries often referred to Hamilton's opponents as "Anti-Federalists", that term is now seen as imprecise since several Anti-Administration leaders supported ratification, including Virginia Representative James Madison. | E22: 21
A23: Democratic-Republican / Federalist | B23: Not a party. | C23: https://en.wikipedia.org/wiki/1812_United_States_presidential_election | D23: While commonly labeled as the Federalist candidate, Clinton technically ran as a Democratic-Republican and was not nominated by the Federalist party itself, the latter simply deciding not to field a candidate. This did not prevent endorsements from state Federalist parties (such as in Pennsylvania), but he received the endorsement from the New York state Democratic-Republicans as well. | E23: 22
A24: Democratic-Republican | C24: https://en.wikipedia.org/wiki/Democratic-Republican_Party | D24: The Republican Party, known retroactively as the Democratic-Republican Party (also referred to by historians as the Jeffersonian Republican Party), was an American political party founded by Thomas Jefferson and James Madison in the early 1790s. It championed liberalism, republicanism, individual liberty, equal rights, decentralization, free markets, free trade, and agrarianism. In foreign policy it was hostile to Great Britain and in sympathy with the French Revolution. The party became increasingly dominant after the 1800 elections as the opposing Federalist Party collapsed. | E24: 23
A25: Democratic-Republican (Crawford faction) | B25: Not a party. | C25: https://en.wikipedia.org/wiki/1824_United_States_presidential_election | D25: The Democratic-Republican Party had won six consecutive presidential elections and by 1824 was the only national political party. However, as the election approached, the presence of multiple viable candidates resulted in there being multiple nominations by the contending factions, signaling the splintering of the party and an end to the Era of Good Feelings, as well as the First Party System. Adams won New England, Jackson and Adams split the mid-Atlantic states, Jackson and Clay split the Western states, and Jackson and Crawford split the Southern states. | E25: 24
A26: Democratic-Republican (Jackson faction) | B26: Not a party. | C26: https://en.wikipedia.org/wiki/1824_United_States_presidential_election | D26: The Democratic-Republican Party had won six consecutive presidential elections and by 1824 was the only national political party. However, as the election approached, the presence of multiple viable candidates resulted in there being multiple nominations by the contending factions, signaling the splintering of the party and an end to the Era of Good Feelings, as well as the First Party System. Adams won New England, Jackson and Adams split the mid-Atlantic states, Jackson and Clay split the Western states, and Jackson and Crawford split the Southern states. | E26: 25
A27: Democratic | C27: https://en.wikipedia.org/wiki/Democratic_Party_(United_States) | D27: The Democratic Party is one of the two major contemporary political parties in the United States. Since the late 1850s, its main political rival has been the Republican Party; the two parties have since dominated American politics. The Democratic Party was founded in 1828. The Democratic Party is the world's oldest active political party. It initially supported expansive presidential power, the interests of slave states, agrarianism, and geographical expansionism, while opposing a national bank and high tariffs. It split in 1860 over slavery and won the presidency only twice between 1860 and 1912, although it won the popular vote two more times in that period. | E27: 26
A28: Democratic (Northern) | B28: Not a party. | C28: https://en.wikipedia.org/wiki/Northern_Democratic_Party | D28: The Northern Democratic Party was a leg of the Democratic Party during the 1860 presidential election, when the party split in two factions because of disagreements over slavery. They held two conventions before the election, in Charleston and Baltimore, where they established their platform. Democratic Candidate Stephen A. Douglas was the nominee and lost to Republican Candidate Abraham Lincoln, whose victory prompted the secession of 11 Southern states and the formation of the Confederate States of America. | E28: 27
A29: Democratic (Southerrn) | B29: Not a party. | C29: https://en.wikipedia.org/wiki/Southern_Democrats | D29: Southern Democrats are members of the U.S. Democratic Party who reside in the Southern United States. Before the American Civil War, Southern Democrats were mostly whites living in the South who believed in Jacksonian democracy. In the 19th century, they defended slavery in the United States and promoted its expansion into the Western United States against the Free Soil opposition in the Northern United States. The United States presidential election of 1860 formalized the split in the Democratic Party and brought about the American Civil War. After the Reconstruction Era ended in the late 1870s, so-called redeemers were Southern Democrats who controlled all the southern states and disenfranchised African-Americans. | E29: 28
A30: Populist | C30: https://en.wikipedia.org/wiki/People%27s_Party_(United_States) | D30: The People's Party, also known as the Populist Party or simply the Populists, was an agrarian populist political party in the United States in the late 19th century. The Populist Party emerged in the early 1890s as an important force in the Southern and Western United States, but declined rapidly after the 1896 United States presidential election in which most of its natural constituency was absorbed by the Bryan wing of the Democratic Party. | E30: 29
A31: Democratic/Populist | B31: Not a party. | C31: https://en.wikipedia.org/wiki/1896_United_States_presidential_election | D31: The 1896 Democratic National Convention repudiated the Cleveland administration and nominated Bryan on the fifth presidential ballot. Bryan then won the nomination of the Populist Party, which had won several states in 1892 and shared many of Bryan's policies. While the Democrats and Populists both nominated Bryan, the two parties had different vice presidential running mates. | E31: 30
A32: Dixiecrat | C32: https://en.wikipedia.org/wiki/Dixiecrat | D32: The States' Rights Democratic Party (whose members are often called the Dixiecrats), also colloquially referred to as the Dixiecrat Party was a short-lived segregationist political party in the United States, active primarily in the South. It arose due to a Southern regional split in opposition to the national Democratic Party. After President Harry S. Truman, the leader of the Democratic Party, ordered integration of the military in 1948 and other actions to address civil rights of African Americans, including the first presidential proposal for comprehensive civil and voting rights, many Southern white politicians who objected to this course organized themselves as a breakaway faction. They wished to protect the ability of states to maintain racial segregation. Its members were referred to as "Dixiecrats", a portmanteau of "Dixie", referring to the Southern United States, and "Democrat". | E32: 31
A33: Southern Democratic | B33: Not a party. | C33: https://en.wikipedia.org/wiki/1960_United_States_presidential_election | D33: A total of 15 electors – eight from Mississippi, six from Alabama, and one from Oklahoma – all refused to vote for either Kennedy or Nixon, and instead cast their votes for Senator Harry F. Byrd of Virginia, a conservative Democrat, even though he had not been a candidate for president. | E33: 32

Sheet party_system
A1: party_system | B1: party_system_title | C1: year_start | D1: year_end | E1: year_start_label | F1: year_end_label | G1: party_system_number | H1: color | I1: color_number | J1: ps_link
A2: First Party System | B2: Federalist vs Democratic-Republican | C2: 1792 | D2: 1824 | E2: 1792 | F2: 1824 | G2: 1st | H2: Federalist | I2: 1 | J2: https://en.wikipedia.org/wiki/First_Party_System
A3: Second Party System | B3: Democratic vs Whig | C3: 1828 | D3: 1854 | E3: 1828 | F3: 1854 | G3: 2nd | H3: Democratic | I3: 1 | J3: https://en.wikipedia.org/wiki/Second_Party_System
A4: Third Party System | B4: Democratic vs Republican | C4: 1854 | D4: 1890 | E4: 1854 | F4: 1890s | G4: 3rd | H4: Democratic | I4: 1 | J4: https://en.wikipedia.org/wiki/Third_Party_System
A5: Fourth Party System | B5: Democratic vs Republican | C5: 1896 | D5: 1932 | E5: 1896 | F5: 1932 | G5: 4th | H5: Democratic | I5: 1 | J5: https://en.wikipedia.org/wiki/Fourth_Party_System
A6: Fifth Party System | B6: Democratic vs Republican | C6: 1932 | D6: 1976 | E6: 1932 | F6: 1976 | G6: 5th | H6: Democratic | I6: 1 | J6: https://en.wikipedia.org/wiki/Fifth_Party_System
A7: Sixth Party System | B7: Democratic vs Republican | C7: 1976 | D7: 2016 | E7: 1976 | F7: 2016(?) | G7: 6th | H7: Democratic | I7: 1 | J7: https://en.wikipedia.org/wiki/Sixth_Party_System
A8: Seventh Party System (proposed) | B8: Democratic vs Republican | C8: 2016 | D8: 2028 | E8: 2016(?) | F8: now | G8: 7th(?) | H8: Democratic | I8: 1 | J8: https://en.wikipedia.org/wiki/Sixth_Party_System#Proposed_Seventh_Party_System
A9: First Party System | B9: Federalist vs Democratic-Republican | C9: 1792 | D9: 1824 | E9: 1792 | F9: 1824 | G9: 1st | H9: Democratic-Republican | I9: 2 | J9: =J2 -> https://en.wikipedia.org/wiki/First_Party_System
A10: Second Party System | B10: Democratic vs Whig | C10: 1828 | D10: 1854 | E10: 1828 | F10: 1854 | G10: 2nd | H10: Whig | I10: 2 | J10: =J3 -> https://en.wikipedia.org/wiki/Second_Party_System
A11: Third Party System | B11: Democratic vs Republican | C11: 1854 | D11: 1890 | E11: 1854 | F11: 1890s | G11: 3rd | H11: Republican | I11: 2 | J11: =J4 -> https://en.wikipedia.org/wiki/Third_Party_System
A12: Fourth Party System | B12: Democratic vs Republican | C12: 1896 | D12: 1932 | E12: 1896 | F12: 1932 | G12: 4th | H12: Republican | I12: 2 | J12: =J5 -> https://en.wikipedia.org/wiki/Fourth_Party_System
A13: Fifth Party System | B13: Democratic vs Republican | C13: 1932 | D13: 1976 | E13: 1932 | F13: 1976 | G13: 5th | H13: Republican | I13: 2 | J13: =J6 -> https://en.wikipedia.org/wiki/Fifth_Party_System
A14: Sixth Party System | B14: Democratic vs Republican | C14: 1976 | D14: 2016 | E14: 1976 | F14: 2016(?) | G14: 6th | H14: Republican | I14: 2 | J14: =J7 -> https://en.wikipedia.org/wiki/Sixth_Party_System
A15: Seventh Party System (proposed) | B15: Democratic vs Republican | C15: 2016 | D15: 2028 | E15: 2016(?) | F15: now | G15: 7th(?) | H15: Republican | I15: 2 | J15: =J8 -> https://en.wikipedia.org/wiki/Sixth_Party_System#Proposed_Seventh_Party_System
